Workbook
Name __VAR1: [1]Presentation!#REF!
Name __VAR2: [1]Presentation!#REF!
Name __VAR3: [1]Presentation!#REF!
Name __VAR4: [1]Presentation!#REF!
Name __VAR5: [1]Presentation!#REF!
Name __VAR6: [1]Presentation!#REF!
Name __VAR7: [1]Presentation!#REF!
Name __VAR8: [1]Presentation!#REF!
Name _VAR1: [1]Presentation!#REF!
Name _VAR1: [1]Presentation!#REF!
Name _VAR1: [1]Presentation!#REF!
Name _VAR2: [1]Presentation!#REF!
Name _VAR2: [1]Presentation!#REF!
Name _VAR2: [1]Presentation!#REF!
Name _VAR3: [1]Presentation!#REF!
Name _VAR3: [1]Presentation!#REF!
Name _VAR3: [1]Presentation!#REF!
Name _VAR4: [1]Presentation!#REF!
Name _VAR4: [1]Presentation!#REF!
Name _VAR4: [1]Presentation!#REF!
Name _VAR5: [1]Presentation!#REF!
Name _VAR5: [1]Presentation!#REF!
Name _VAR5: [1]Presentation!#REF!
Name _VAR6: [1]Presentation!#REF!
Name _VAR6: [1]Presentation!#REF!
Name _VAR6: [1]Presentation!#REF!
Name _VAR7: [1]Presentation!#REF!
Name _VAR7: [1]Presentation!#REF!
Name _VAR7: [1]Presentation!#REF!
Name _VAR8: [1]Presentation!#REF!
Name _VAR8: [1]Presentation!#REF!
Name _VAR8: [1]Presentation!#REF!
Name AN1PMIEGROUPE: #REF!
Name APMIEGROUPE2: '[1]T2 Actual N'!$B$134:$AL$151
Name B1OA060STEGROUPE: '[2]Budget N+1'!$A$191:$AC$208
Name base: [1]Presentation!#REF!
Name base: [1]Presentation!#REF!
Name base: [1]Presentation!#REF!
Name BCENTRALOA2: '[1]T2 Budget N'!$A$251:$H$268
Name BFRMPOA2: '[1]T2 Budget N'!$A$71:$U$88
Name BITA2: '[1]T2 Budget N'!$A$314:$J$332
Name BOA060STEGROUPE2: '[1]T2 Budget N'!$A$190:$AH$207
Name BOA061STEGROUPE2: '[1]T2 Budget N'!$A$221:$AH$238
Name BOAGROUPE2: '[1]T2 Budget N'!$A$11:$U$28
Name BPMIE2: '[1]T2 Budget N'!$C$130:$AL$147
Name BPROMOLUX2: '[1]T2 Budget N'!$A$346:$C$364
Name BSPOA2: '[1]T2 Budget N'!$A$101:$T$118
Name BSTEGROUPE2: '[1]T2 Budget N'!$A$41:$AH$58
Name DATE: [1]Presentation!#REF!
Name DATE: [1]Presentation!#REF!
Name DATE: [1]Presentation!#REF!
Name E1PMGBP: [3]GBP!$F$82:$I$92
Name EGBP: [3]GBP!$A$82:$D$92
Name EHDPMGROUP: '[3]Estimé N'!$A$162:$AE$179
Name ENCENTRALOA: #REF!
Name ENFRMPOA: #REF!
Name ENHDPMGROUP: '[3]Estimé précédent N'!$A$161:$AF$178
Name ENOAGROUPE: #REF!
Name ENSPOA: #REF!
Name ENSTEGROUPE: #REF!

Sheet 1. Business Lines (2)
B3: Code MAGNITUDE | C3: Code SOLARE | D3: English description
B4: OA020 | C4: PMA_8023 | D4: Consulting & Corporate Real Estate
B5: OA020O | C5: PMA_8047 | D5: Traker
B6: OA011E | C6: PMA_8026 | D6: CONSULTING - Debt Advisor
B7: OA024 | C7: PMA_8024 | D7: Rural Consultancy
B8: OA022 | C8: PMA_8025 | D8: Space consulting & Space Planning
B9: OA019O | C9: PMA_8038 | D9: Coordination Advisory
B10: OA011O | C10: NOT USED | D10: NOT USED
B11: OA011 | C11: PMA_8041 | D11: Investment
B12: OA010 | C12: PMA_8037 | D12: Letting & Sales
B13: OA023 | C13: PMA_8027 | D13: Residential Development & Planning
B14: OA017 | C14: PMA_8028 | D14: Residential Retail Sales/ Residential Agency
... B37: OA016 | C37: PMA_8007 | D37: Sales to Investors & Institutional

Sheet 2. Entities
B3: Code Magnitude | C3: Lib Magnitude | D3: Ccy | E3: Code SOLARE | F3: Lib SOLARE
B4: G-BE | C4: BNPP RE Belgium | D4: EUR | E4: EJ_21908 | F4: BNPP RE Belgium
B5: G-BE | C5: BNPP RE Belgium | D5: EUR | E5: EJ_47884 | F5: BNPP REIM Belgium
B6: G-DE | C6: BNPP RE Germany APM | D6: EUR | E6: EJ_21902 | F6: BNPPRE Holding GmbH
B7: G-DE | C7: BNPP RE Germany APM | D7: EUR | E7: EJ_21904 | F7: BNPPRE GmbH
B8: G-DE | C8: BNPP RE Germany APM | D8: EUR | E8: EJ_21905 | F8: BNPP REPM GmbH
B9: G-DE | C9: BNPP RE Germany APM | D9: EUR | E9: EJ_21906 | F9: BNPPRE Consult GmbH
B10: G-DEPROMO | C10: BNPP RE Germany Promotion | D10: EUR | E10: EJ_65631 | F10: BNP Paribas Real Estate Property Devlopment & Services
B11: G-REIMI | C11: BNPP REIM International | D11: EUR | E11: EJ_65631 | F11: BNP Paribas Real Estate Property Devlopment & Services
B12: G-REIMDE | C12: BNPP REIM Germany | D12: EUR | E12: EJ_58476 | F12: BNPP Real Estate Investment Management Germany GmbH
B13: G-IR | C13: BNPP RE Ireland | D13: EUR | E13: EJ_42444 | F13: BNPPRE APM Ireland
B14: G-ITAR | C14: BNPP RE Advisory Italy | D14: EUR | E14: EJ_40711 | F14: BNPPRE Advisory Italy
... B38: G-UKPROMO | C38: BNPP REPD UK | D38: GBP | E38: EJ_63264 | F38: REPD Parker Limited

Sheet Réalisé Vs Estimé
A1: SC=BNPPI-GEST
A2: CC=EUR
A3: FA sum AR002
A4: FL=F99 | E4: {AC=GFB001}+{AC=GFB002}+{AC=GFB004}+{AC=GFB008}+{AC=GFB009}+{AC=GFB003} | G4: {AC=GFB001}+{AC=GFB002}+{AC=GFB004}+{AC=GFB008}+{AC=GFB009}+{AC=GFB003} | K4: {AC=GFB005}+{AC=GFB006}+{AC=GFB110}+{AC=GFB111}+{AC=GFB112}+{AC=GFB120}+{AC=GFB121}+{AC=GFB122}+{AC=GFB100}+{AC=GFB101}+{AC=GFB102}+{AC=GFB130}+{AC=GFB131}+{AC=GFB132} | M4: {AC=GFB005}+{AC=GFB006}+{AC=GFB110}+{AC=GFB111}+{AC=GFB112}+{AC=GFB120}+{AC=GFB121}+{AC=GFB122}+{AC=GFB100}+{AC=GFB101}+{AC=GFB102}+{AC=GFB130}+{AC=GFB131}+{AC=GFB132} | Q4: AC sum RGFB | S4: AC sum RGFB | W4: AC sum RGFB | Y4: AC sum RGFB | AC4: AC sum RGFB | AE4: AC sum RGFB | AI4: AC sum RGFB | AK4: AC sum RGFB | AO4: AC sum RGFB | AQ4: AC sum RGFB | BA4: AC sum RGFB | BB4: AC sum RGFB | BC4: AC sum RGFB | BG4: =+AO4 -> AC sum RGFB | BI4: =+AQ4 -> AC sum RGFB | BN4: =+BG4 -> AC sum RGFB | BO4: =+BH4 -> 0 | BP4: =+BI4 -> AC sum RGFB
E5: CA=A | G5: CA=E | K5: =E5 -> CA=A | L5: =K5 -> CA=A | M5: =G5 -> CA=E | N5: =M5 -> CA=E | Q5: =E5 -> CA=A | R5: =Q5 -> CA=A | S5: =G5 -> CA=E | T5: =S5 -> CA=E | W5: =L5 -> CA=A | X5: =W5 -> CA=A | Y5: =N5 -> CA=E | Z5: =Y5 -> CA=E | AC5: =R5 -> CA=A | AD5: =AC5 -> CA=A | AE5: =T5 -> CA=E | AF5: =AE5 -> CA=E | AI5: =W5 -> CA=A | AJ5: =AI5 -> CA=A | AK5: =Y5 -> CA=E | AL5: =AK5 -> CA=E | AO5: =AC5 -> CA=A | AP5: =AO5 -> CA=A | AQ5: =AE5 -> CA=E | AR5: =AQ5 -> CA=E | BA5: =AO5 -> CA=A | BB5: =BA5 -> CA=A | BC5: =AQ5 -> CA=E | BD5: =BC5 -> CA=E | BG5: =+AO5 -> CA=A | BH5: =BG5 -> CA=A | BI5: =+AQ5 -> CA=E | BJ5: =BI5 -> CA=E | BN5: =+BG5 -> CA=A | BO5: =+BH5 -> CA=A | BP5: =+BI5 -> CA=E | BQ5: =BP5 -> CA=E
E6: DP=2026.03 | F6: DP=2024.13 | G6: DP=2026.03 | K6: =E6 -> DP=2026.03 | L6: =K6 -> DP=2026.03 | M6: =G6 -> DP=2026.03 | N6: =M6 -> DP=2026.03 | Q6: =E6 -> DP=2026.03 | R6: =Q6 -> DP=2026.03 | S6: =G6 -> DP=2026.03 | T6: =S6 -> DP=2026.03 | W6: =L6 -> DP=2026.03 | X6: =W6 -> DP=2026.03 | Y6: =N6 -> DP=2026.03 | Z6: =Y6 -> DP=2026.03 | AC6: =R6 -> DP=2026.03 | AD6: =AC6 -> DP=2026.03 | AE6: =T6 -> DP=2026.03 | AF6: =AE6 -> DP=2026.03 | AI6: =W6 -> DP=2026.03 | AJ6: =AI6 -> DP=2026.03 | AK6: =Y6 -> DP=2026.03 | AL6: =AK6 -> DP=2026.03 | AO6: =AC6 -> DP=2026.03 | AP6: =AO6 -> DP=2026.03 | AQ6: =AE6 -> DP=2026.03 | AR6: =AQ6 -> DP=2026.03 | BA6: =AO6 -> DP=2026.03 | BB6: =BA6 -> DP=2026.03 | BC6: =AQ6 -> DP=2026.03 | BD6: =BC6 -> DP=2026.03 | BG6: =+AO6 -> DP=2026.03 | BH6: =BG6 -> DP=2026.03 | BI6: =+AQ6 -> DP=2026.03 | BJ6: =BI6 -> DP=2026.03 | BN6: =+BG6 -> DP=2026.03 | BO6: =+BH6 -> DP=2026.03 | BP6: =+BI6 -> DP=2026.03 | BQ6: =BP6 -> DP=2026.03
E7: PE=2026.03 | F7: PE=2024.13 | G7: PE=2026.03 | K7: =E7 -> PE=2026.03 | L7: =K7 -> PE=2026.03 | M7: =G7 -> PE=2026.03 | N7: =M7 -> PE=2026.03 | Q7: =E7 -> PE=2026.03 | R7: =Q7 -> PE=2026.03 | S7: =G7 -> PE=2026.03 | T7: =S7 -> PE=2026.03 | W7: =L7 -> PE=2026.03 | X7: =W7 -> PE=2026.03 | Y7: =N7 -> PE=2026.03 | Z7: =Y7 -> PE=2026.03 | AC7: =R7 -> PE=2026.03 | AD7: =AC7 -> PE=2026.03 | AE7: =T7 -> PE=2026.03 | AF7: =AE7 -> PE=2026.03 | AI7: =W7 -> PE=2026.03 | AJ7: =AI7 -> PE=2026.03 | AK7: =Y7 -> PE=2026.03 | AL7: =AK7 -> PE=2026.03 | AO7: =AC7 -> PE=2026.03 | AP7: =AO7 -> PE=2026.03 | AQ7: =AE7 -> PE=2026.03 | AR7: =AQ7 -> PE=2026.03 | BA7: =AO7 -> PE=2026.03 | BB7: =BA7 -> PE=2026.03 | BC7: =AQ7 -> PE=2026.03 | BD7: =BC7 -> PE=2026.03 | BG7: =+AO7 -> PE=2026.03 | BH7: =BG7 -> PE=2026.03 | BI7: =+AQ7 -> PE=2026.03 | BJ7: =BI7 -> PE=2026.03 | BN7: =+BG7 -> PE=2026.03 | BO7: =+BH7 -> PE=2026.03 | BP7: =+BI7 -> PE=2026.03 | BQ7: =BP7 -> PE=2026.03
E8: =VLOOKUP([6]Présentation!$E$31,[6]Présentation!$B$93:$C$94,2,FALSE) -> AU sum GEST00 | G8: =VLOOKUP([6]Présentation!$E$31,[6]Présentation!$B$93:$C$94,2,FALSE) -> AU sum GEST00 | K8: =E8 -> AU sum GEST00 | L8: =K8 -> AU sum GEST00 | M8: =G8 -> AU sum GEST00 | N8: =M8 -> AU sum GEST00 | Q8: =E8 -> AU sum GEST00 | R8: =Q8 -> AU sum GEST00 | S8: =G8 -> AU sum GEST00 | T8: =S8 -> AU sum GEST00 | W8: =L8 -> AU sum GEST00 | X8: =W8 -> AU sum GEST00 | Y8: =N8 -> AU sum GEST00 | Z8: =Y8 -> AU sum GEST00 | AC8: =R8 -> AU sum GEST00 | AD8: =AC8 -> AU sum GEST00 | AE8: =T8 -> AU sum GEST00 | AF8: =AE8 -> AU sum GEST00 | AI8: =W8 -> AU sum GEST00 | AJ8: =AI8 -> AU sum GEST00 | AK8: =Y8 -> AU sum GEST00 | AL8: =AK8 -> AU sum GEST00 | AO8: =AC8 -> AU sum GEST00 | AP8: =AO8 -> AU sum GEST00 | AQ8: =AE8 -> AU sum GEST00 | AR8: =AQ8 -> AU sum GEST00 | BA8: =AO8 -> AU sum GEST00 | BB8: =BA8 -> AU sum GEST00 | BC8: =AQ8 -> AU sum GEST00 | BD8: =BC8 -> AU sum GEST00 | BG8: =+AO8 -> AU sum GEST00 | BH8: =BG8 -> AU sum GEST00 | BI8: =+AQ8 -> AU sum GEST00 | BJ8: =BI8 -> AU sum GEST00 | BN8: =+BG8 -> AU sum GEST00 | BO8: =+BH8 -> AU sum GEST00 | BP8: =+BI8 -> AU sum GEST00 | BQ8: =BP8 -> AU sum GEST00
E9: =VLOOKUP([6]Présentation!$E$38,[6]Présentation!$B$60:$C$61,2,FALSE) -> VA=RECOMPO | G9: =VLOOKUP([6]Présentation!$E$38,[6]Présentation!$B$60:$C$61,2,FALSE) -> VA=RECOMPO | K9: =E9 -> VA=RECOMPO | L9: =K9 -> VA=RECOMPO | M9: =G9 -> VA=RECOMPO | N9: =M9 -> VA=RECOMPO | Q9: =E9 -> VA=RECOMPO | R9: =Q9 -> VA=RECOMPO | S9: =G9 -> VA=RECOMPO | T9: =S9 -> VA=RECOMPO | W9: =L9 -> VA=RECOMPO | X9: =W9 -> VA=RECOMPO | Y9: =N9 -> VA=RECOMPO | Z9: =Y9 -> VA=RECOMPO | AC9: =R9 -> VA=RECOMPO | AD9: =AC9 -> VA=RECOMPO | AE9: =T9 -> VA=RECOMPO | AF9: =AE9 -> VA=RECOMPO | AI9: =W9 -> VA=RECOMPO | AJ9: =AI9 -> VA=RECOMPO | AK9: =Y9 -> VA=RECOMPO | AL9: =AK9 -> VA=RECOMPO | AO9: =AC9 -> VA=RECOMPO | AP9: =AO9 -> VA=RECOMPO | AQ9: =AE9 -> VA=RECOMPO | AR9: =AQ9 -> VA=RECOMPO | BA9: =AO9 -> VA=RECOMPO | BB9: =BA9 -> VA=RECOMPO | BC9: =AQ9 -> VA=RECOMPO | BD9: =BC9 -> VA=RECOMPO | BG9: =+AO9 -> VA=RECOMPO | BH9: =BG9 -> VA=RECOMPO | BI9: =+AQ9 -> VA=RECOMPO | BJ9: =BI9 -> VA=RECOMPO | BN9: =+BG9 -> VA=RECOMPO | BO9: =+BH9 -> VA=RECOMPO | BP9: =+BI9 -> VA=RECOMPO | BQ9: =BP9 -> VA=RECOMPO
E10: {AC=GPNBTOT}+{AC=GR5400} | G10: {AC=GPNBTOT}+{AC=GR5400} | K10: AC=GFDGT | L10: AC=GFDGHT | M10: AC=GFDGT | N10: AC=GFDGHT | Q10: AC=GRNAI | R10: AC=GS0911 | S10: AC=GRNAI | T10: AC=GS0911 | W10: AC=GRITC001 | X10: =W10 -> AC=GRITC001 | Y10: =W10 -> AC=GRITC001 | Z10: =Y10 -> AC=GRITC001 | AC10: AC=GRITC002 | AD10: =AC10 -> AC=GRITC002 | AE10: =AC10 -> AC=GRITC002 | AF10: =AE10 -> AC=GRITC002 | AI10: {AC=GRITC003}+{AC=GRITC004}+{AC=GRITC005} | AJ10: =AI10 -> {AC=GRITC003}+{AC=GRITC004}+{AC=GRITC005} | AK10: =AI10 -> {AC=GRITC003}+{AC=GRITC004}+{AC=GRITC005} | AL10: =AK10 -> {AC=GRITC003}+{AC=GRITC004}+{AC=GRITC005} | AO10: {AC=GFB130}+{AC=GFB110} | AP10: =AO10 -> {AC=GFB130}+{AC=GFB110} | AQ10: =AO10 -> {AC=GFB130}+{AC=GFB110} | AR10: =AQ10 -> {AC=GFB130}+{AC=GFB110} | BA10: AC=GRNAI | BB10: AC=GS0911 | BC10: AC=GRNAI | BD10: AC=GS0911 | BG10: {AC=GFB130} | BI10: {AC=GFB130} | BN10: {AC=GFB110} | BO10: =BN10 -> {AC=GFB110} | BP10: =+BN10 -> {AC=GFB110} | BQ10: =BP10 -> {AC=GFB110}
D11: m€ | E11: =CHOOSE([6]Traduction!$A$2,[6]Traduction!$A94,[6]Traduction!$B94) -> Net Banking Income + Result of Co-Dev JVs | K11: =CHOOSE([6]Traduction!$A$2,[6]Traduction!$A40,[6]Traduction!$B40) -> General Operating Expenses | Q11: =CHOOSE([6]Traduction!$A$2,[6]Traduction!$A41,[6]Traduction!$B41) -> Pre-Tax Income | W11: SLA Plateforms | Z11: =Y11 -> 0 | AC11: SLA Steering IM | AF11: =AE11 -> 0 | AI11: SLA IIC+Retail+Logistics | AL11: =AK11 -> 0 | AO11: Management Fees + BNPP SA rebilling | AR11: =AQ11 -> 0 | AU11: Total Internal SLA + MF + BNPP SA Rebilling | BG11: Management Fees + BNPP SA rebilling | BJ11: =BI11 -> 0 | BN11: Management Fees + BNPP SA rebilling | BQ11: =BP11 -> 0
A13: OA sum (TYPE-OA=OA06)
D14: Actual N vs Estimate-1 at perimeter & Historical conversion rate | E14: Actual Q1 2026 | G14: Estimate March Q1 2026 | I14: Variances | K14: =E14 -> Actual Q1 2026 | M14: =G14 -> Estimate March Q1 2026 | O14: =I14 -> Variances | Q14: =E14 -> Actual Q1 2026 | S14: =G14 -> Estimate March Q1 2026 | U14: =I14 -> Variances | W14: =E14 -> Actual Q1 2026 | Y14: =G14 -> Estimate March Q1 2026 | AA14: =I14 -> Variances | AC14: =W14 -> Actual Q1 2026 | AE14: =Y14 -> Estimate March Q1 2026 | AG14: =AA14 -> Variances | AI14: =W14 -> Actual Q1 2026 | AK14: =Y14 -> Estimate March Q1 2026 | AM14: =AA14 -> Variances | AO14: =AC14 -> Actual Q1 2026 | AQ14: =AE14 -> Estimate March Q1 2026 | AS14: =AG14 -> Variances | AU14: =AI14 -> Actual Q1 2026 | AW14: =AK14 -> Estimate March Q1 2026 | AY14: =AM14 -> Variances | BA14: =AO14 -> Actual Q1 2026 | BC14: =AQ14 -> Estimate March Q1 2026 | BE14: =AS14 & " excl. Management Fees and equivalent " -> Variances excl. Management Fees and equivalent | BG14: =AU14 -> Actual Q1 2026 | BI14: =AW14 -> Estimate March Q1 2026 | BK14: =AY14 -> Variances | BN14: =BB14 -> 0 | BP14: =BD14 -> 0 | BR14: =BF14 -> 0
E15: Standalone | G15: Standalone | K15: =VLOOKUP([6]Présentation!$D$30,[6]Présentation!#REF!,2,FALSE) -> #REF! | M15: =VLOOKUP([6]Présentation!$D$30,[6]Présentation!#REF!,8,FALSE) -> #REF! | Q15: Standalone | S15: Standalone | W15: Standalone | Y15: Standalone | AC15: Standalone | AE15: Standalone | AI15: Standalone | AK15: Standalone | AO15: Standalone | AQ15: Standalone | AU15: Standalone | AW15: Standalone | BA15: Standalone | BC15: Standalone | BE15: Σ | BG15: Standalone | BI15: Standalone | BN15: Standalone | BP15: Standalone
D17: Property Development | E17: =E18+E19+E25 -> #NAME? | G17: =G18+G19+G25 -> #NAME? | I17: =E17-G17 -> #NAME? | K17: =K18+K19+K25 -> #NAME? | M17: =M18+M19+M25 -> #NAME? | O17: =K17-M17 -> #NAME? | Q17: =Q18+Q19+Q25 -> #NAME? | S17: =S18+S19+S25 -> #NAME? | U17: =Q17-S17 -> #NAME? | W17: =SUM(W18:W33)-W31 -> #NAME? | Y17: =SUM(Y18:Y33)-Y31 -> #NAME? | AA17: =W17-Y17 -> #NAME? | AC17: =SUM(AC18:AC33)-AC31 -> #NAME? | AE17: =SUM(AE18:AE33)-AE31 -> #NAME? | AG17: =AC17-AE17 -> #NAME? | AI17: =SUM(AI18:AI33)-AI31 -> #NAME? | AK17: =SUM(AK18:AK33)-AK31 -> #NAME? | AM17: =AI17-AK17 -> #NAME? | AO17: =SUM(AO18:AO33)-AO31 -> #NAME? | AQ17: =SUM(AQ18:AQ33)-AQ31 -> #NAME? | AS17: =AO17-AQ17 -> #NAME? | AU17: =W17+AC17+AI17+AO17 -> #NAME? | AW17: =Y17+AE17+AK17+AQ17 -> #NAME? | AY17: =AU17-AW17 -> #NAME? | BA17: =+Q17-AO17 -> #NAME? | BC17: =+S17-AQ17 -> #NAME? | BE17: =BA17-BC17 -> #NAME? | BG17: =SUM(BG18:BG33)-BG31 -> #NAME? | BI17: =SUM(BI18:BI33)-BI31 -> #NAME? | BK17: =BG17-BI17 -> #NAME? | BN17: =SUM(BN18:BN33)-BN31 -> #NAME? | BP17: =SUM(BP18:BP33)-BP31 -> #NAME? | BR17: =BN17-BP17 -> #NAME?
A18: {OA=OA040}+{OA=OA041} | B18: {RU=G-CENTRAL}+{RU=P-CENTRAL} | C18: FR | D18: G-central | E18: =_xll.GetCtData("CO-AMOUNT","CONS-AMOUNT",$A$1:$A$4,$A18:$B18,E$5:E$10,"#") -> #NAME? | G18: =_xll.GetCtData("CO-AMOUNT","CONS-AMOUNT",$A$1:$A$4,$A18:$B18,G$5:G$10,"#") -> #NAME? | I18: =E18-G18 -> #NAME? | K18: =_xll.GetCtData("CO-AMOUNT","CONS-AMOUNT",$A$1:$A$4,$A18:$B18,K$5:K$10,"#") -> #NAME? | M18: =_xll.GetCtData("CO-AMOUNT","CONS-AMOUNT",$A$1:$A$4,$A18:$B18,M$5:M$10,"#") -> #NAME? | O18: =K18-M18 -> #NAME? | Q18: =_xll.GetCtData("CO-AMOUNT","CONS-AMOUNT",$A$1:$A$4,$A18:$B18,Q$5:Q$10,"#") -> #NAME? | S18: =_xll.GetCtData("CO-AMOUNT","CONS-AMOUNT",$A$1:$A$4,$A18:$B18,S$5:S$10,"#") -> #NAME? | U18: =Q18-S18 -> #NAME? | W18: =_xll.GetCtData("CO-AMOUNT","CONS-AMOUNT",$A$1:$A$4,$A18:$B18,W$5:W$10,"#") -> #NAME? | Y18: =_xll.GetCtData("CO-AMOUNT","CONS-AMOUNT",$A$1:$A$4,$A18:$B18,Y$5:Y$10,"#") -> #NAME? | AA18: =W18-Y18 -> #NAME? | AC18: =_xll.GetCtData("CO-AMOUNT","CONS-AMOUNT",$A$1:$A$4,$A18:$B18,AC$5:AC$10,"#") -> #NAME? | AE18: =_xll.GetCtData("CO-AMOUNT","CONS-AMOUNT",$A$1:$A$4,$A18:$B18,AE$5:AE$10,"#") -> #NAME? | AG18: =AC18-AE18 -> #NAME? | AI18: =_xll.GetCtData("CO-AMOUNT","CONS-AMOUNT",$A$1:$A$4,$A18:$B18,AI$5:AI$10,"#") -> #NAME? | AK18: =_xll.GetCtData("CO-AMOUNT","CONS-AMOUNT",$A$1:$A$4,$A18:$B18,AK$5:AK$10,"#") -> #NAME? | AM18: =AI18-AK18 -> #NAME? | AO18: =_xll.GetCtData("CO-AMOUNT","CONS-AMOUNT",$A$1:$A$4,$A18:$B18,AO$5:AO$10,"#") -> #NAME? | AQ18: =_xll.GetCtData("CO-AMOUNT","CONS-AMOUNT",$A$1:$A$4,$A18:$B18,AQ$5:AQ$10,"#") -> #NAME? | AS18: =AO18-AQ18 -> #NAME? | AU18: =W18+AC18+AI18+AO18 -> #NAME? | AW18: =Y18+AE18+AK18+AQ18 -> #NAME? | AY18: =AU18-AW18 -> #NAME? | BA18: =+Q18-AO18 -> #NAME? | BC18: =+S18-AQ18 -> #NAME? | BE18: =BA18-BC18 -> #NAME? | BG18: =_xll.GetCtData("CO-AMOUNT","CONS-AMOUNT",$A$1:$A$4,$A18:$B18,BG$5:BG$10,"#") -> #NAME? | BI18: =_xll.GetCtData("CO-AMOUNT","CONS-AMOUNT",$A$1:$A$4,$A18:$B18,BI$5:BI$10,"#") -> #NAME? | BK18: =BG18-BI18 -> #NAME? | BN18: =_xll.GetCtData("CO-AMOUNT","CONS-AMOUNT",$A$1:$A$4,$A18:$B18,BN$5:BN$10,"#") -> #NAME? | BP18: =_xll.GetCtData("CO-AMOUNT","CONS-AMOUNT",$A$1:$A$4,$A18:$B18,BP$5:BP$10,"#") -> #NAME? | BR18: =BN18-BP18 -> #NAME?
D19: =CHOOSE([6]Traduction!$A$2,[6]Traduction!$A45,[6]Traduction!$B45) -> o/w France | E19: =E22+E21+E20 -> #NAME? | G19: =G22+G21+G20 -> #NAME? | I19: =E19-G19 -> #NAME? | K19: =K22+K21+K20 -> #NAME? | M19: =M22+M21+M20 -> #NAME? | O19: =K19-M19 -> #NAME? | Q19: =Q22+Q21+Q20 -> #NAME? | S19: =S22+S21+S20 -> #NAME? | U19: =Q19-S19 -> #NAME? | W19: =_xll.GetCtData("CO-AMOUNT","CONS-AMOUNT",$A$1:$A$4,$A19:$B19,W$5:W$10,"#-119,137061911572") -> #NAME? | Y19: =_xll.GetCtData("CO-AMOUNT","CONS-AMOUNT",$A$1:$A$4,$A19:$B19,Y$5:Y$10,"#139,303394874322") -> #NAME? | AA19: =W19-Y19 -> #NAME? | AC19: =_xll.GetCtData("CO-AMOUNT","CONS-AMOUNT",$A$1:$A$4,$A19:$B19,AC$5:AC$10,"#22,98") -> #NAME? | AE19: =_xll.GetCtData("CO-AMOUNT","CONS-AMOUNT",$A$1:$A$4,$A19:$B19,AE$5:AE$10,"#7,27000000000001") -> #NAME? | AG19: =AC19-AE19 -> #NAME? | AI19: =_xll.GetCtData("CO-AMOUNT","CONS-AMOUNT",$A$1:$A$4,$A19:$B19,AI$5:AI$10,"#-65,1913655499592") -> #NAME? | AK19: =_xll.GetCtData("CO-AMOUNT","CONS-AMOUNT",$A$1:$A$4,$A19:$B19,AK$5:AK$10,"#418,511442896423") -> #NAME? | AM19: =AI19-AK19 -> #NAME? | AO19: =_xll.GetCtData("CO-AMOUNT","CONS-AMOUNT",$A$1:$A$4,$A19:$B19,AO$5:AO$10,"#-12821,1653475363") -> #NAME? | AQ19: =_xll.GetCtData("CO-AMOUNT","CONS-AMOUNT",$A$1:$A$4,$A19:$B19,AQ$5:AQ$10,"#-9611,83172873421") -> #NAME? | AS19: =AO19-AQ19 -> #NAME? | AU19: =W19+AC19+AI19+AO19 -> #NAME? | AW19: =Y19+AE19+AK19+AQ19 -> #NAME? | AY19: =AU19-AW19 -> #NAME? | BA19: =+Q19-AO19 -> #NAME? | BC19: =+S19-AQ19 -> #NAME? | BE19: =BA19-BC19 -> #NAME? | BG19: =_xll.GetCtData("CO-AMOUNT","CONS-AMOUNT",$A$1:$A$4,$A19:$B19,BG$5:BG$10,"#-6631,80636538518") -> #NAME? | BI19: =_xll.GetCtData("CO-AMOUNT","CONS-AMOUNT",$A$1:$A$4,$A19:$B19,BI$5:BI$10,"#-4370,58368251045") -> #NAME? | BK19: =BG19-BI19 -> #NAME? | BN19: =_xll.GetCtData("CO-AMOUNT","CONS-AMOUNT",$A$1:$A$4,$A19:$B19,BN$5:BN$10,"#-6189,3589821511") -> #NAME? | BP19: =_xll.GetCtData("CO-AMOUNT","CONS-AMOUNT",$A$1:$A$4,$A19:$B19,BP$5:BP$10,"#-5241,24804622376") -> #NAME? | BR19: =BN19-BP19 -> #NAME?
A20: {OA=OA040}+{OA=OA041} | B20: {RU=G-FRMP}+{RU=P-FRMP}+{RU=G-FRAR}+{RU=P-FRAR} | C20: FR | D20: o/w Prop Dev Offices and Resid | E20: =_xll.GetCtData("CO-AMOUNT","CONS-AMOUNT",$A$1:$A$4,$A20:$B20,E$5:E$10,"#-14399,59") -> #NAME? | G20: =_xll.GetCtData("CO-AMOUNT","CONS-AMOUNT",$A$1:$A$4,$A20:$B20,G$5:G$10,"#-14951,9") -> #NAME? | I20: =E20-G20 -> #NAME? | K20: =_xll.GetCtData("CO-AMOUNT","CONS-AMOUNT",$A$1:$A$4,$A20:$B20,K$5:K$10,"#-13734,963") -> #NAME? | M20: =_xll.GetCtData("CO-AMOUNT","CONS-AMOUNT",$A$1:$A$4,$A20:$B20,M$5:M$10,"#-14506,73") -> #NAME? | O20: =K20-M20 -> #NAME? | Q20: =_xll.GetCtData("CO-AMOUNT","CONS-AMOUNT",$A$1:$A$4,$A20:$B20,Q$5:Q$10,"#-28134,553") -> #NAME? | S20: =_xll.GetCtData("CO-AMOUNT","CONS-AMOUNT",$A$1:$A$4,$A20:$B20,S$5:S$10,"#-29458,63") -> #NAME? | U20: =Q20-S20 -> #NAME?
A21: OA=OA015 | B21: {RU=G-FRMP}+{RU=P-FRMP} | C21: FR | D21: o/w Residential sales | E21: =_xll.GetCtData("CO-AMOUNT","CONS-AMOUNT",$A$1:$A$4,$A21:$B21,E$5:E$10,"#") -> #NAME? | G21: =_xll.GetCtData("CO-AMOUNT","CONS-AMOUNT",$A$1:$A$4,$A21:$B21,G$5:G$10,"#") -> #NAME? | I21: =E21-G21 -> #NAME? | K21: =_xll.GetCtData("CO-AMOUNT","CONS-AMOUNT",$A$1:$A$4,$A21:$B21,K$5:K$10,"#") -> #NAME? | M21: =_xll.GetCtData("CO-AMOUNT","CONS-AMOUNT",$A$1:$A$4,$A21:$B21,M$5:M$10,"#") -> #NAME? | O21: =K21-M21 -> #NAME? | Q21: =_xll.GetCtData("CO-AMOUNT","CONS-AMOUNT",$A$1:$A$4,$A21:$B21,Q$5:Q$10,"#") -> #NAME? | S21: =_xll.GetCtData("CO-AMOUNT","CONS-AMOUNT",$A$1:$A$4,$A21:$B21,S$5:S$10,"#") -> #NAME? | U21: =Q21-S21 -> #NAME?
A22: OA sum AR021 | B22: {RU=G-FRMP}+{RU=P-FRMP} | C22: FR | D22: o/w Serviced Residences | E22: =_xll.GetCtData("CO-AMOUNT","CONS-AMOUNT",$A$1:$A$4,$A22:$B22,E$5:E$10,"#1714,35") -> #NAME? | G22: =_xll.GetCtData("CO-AMOUNT","CONS-AMOUNT",$A$1:$A$4,$A22:$B22,G$5:G$10,"#1485,056") -> #NAME? | I22: =E22-G22 -> #NAME? | K22: =_xll.GetCtData("CO-AMOUNT","CONS-AMOUNT",$A$1:$A$4,$A22:$B22,K$5:K$10,"#-1893,148") -> #NAME? | M22: =_xll.GetCtData("CO-AMOUNT","CONS-AMOUNT",$A$1:$A$4,$A22:$B22,M$5:M$10,"#-2067,487") -> #NAME? | O22: =K22-M22 -> #NAME? | Q22: =_xll.GetCtData("CO-AMOUNT","CONS-AMOUNT",$A$1:$A$4,$A22:$B22,Q$5:Q$10,"#-226,346000000001") -> #NAME? | S22: =_xll.GetCtData("CO-AMOUNT","CONS-AMOUNT",$A$1:$A$4,$A22:$B22,S$5:S$10,"#-596,373999999999") -> #NAME? | U22: =Q22-S22 -> #NAME?
A23: OA=OA036 | B23: {RU=G-FRMP}+{RU=P-FRMP} | C23: FR | D23: o/w Students Residences | E23: =_xll.GetCtData("CO-AMOUNT","CONS-AMOUNT",$A$1:$A$4,$A23:$B23,E$5:E$10,"#2620,14") -> #NAME? | G23: =_xll.GetCtData("CO-AMOUNT","CONS-AMOUNT",$A$1:$A$4,$A23:$B23,G$5:G$10,"#2458,496") -> #NAME? | I23: =E23-G23 -> #NAME? | K23: =_xll.GetCtData("CO-AMOUNT","CONS-AMOUNT",$A$1:$A$4,$A23:$B23,K$5:K$10,"#-1440,992") -> #NAME? | M23: =_xll.GetCtData("CO-AMOUNT","CONS-AMOUNT",$A$1:$A$4,$A23:$B23,M$5:M$10,"#-1562,699") -> #NAME? | O23: =K23-M23 -> #NAME? | Q23: =_xll.GetCtData("CO-AMOUNT","CONS-AMOUNT",$A$1:$A$4,$A23:$B23,Q$5:Q$10,"#1121,182") -> #NAME? | S23: =_xll.GetCtData("CO-AMOUNT","CONS-AMOUNT",$A$1:$A$4,$A23:$B23,S$5:S$10,"#870,797000000001") -> #NAME? | U23: =Q23-S23 -> #NAME?
A24: OA=OA037 | B24: {RU=G-FRMP}+{RU=P-FRMP} | C24: FR | D24: o/w Business Travellers Residences | E24: =_xll.GetCtData("CO-AMOUNT","CONS-AMOUNT",$A$1:$A$4,$A24:$B24,E$5:E$10,"#-905,79") -> #NAME? | G24: =_xll.GetCtData("CO-AMOUNT","CONS-AMOUNT",$A$1:$A$4,$A24:$B24,G$5:G$10,"#-973,44") -> #NAME? | I24: =E24-G24 -> #NAME? | K24: =_xll.GetCtData("CO-AMOUNT","CONS-AMOUNT",$A$1:$A$4,$A24:$B24,K$5:K$10,"#-452,156") -> #NAME? | M24: =_xll.GetCtData("CO-AMOUNT","CONS-AMOUNT",$A$1:$A$4,$A24:$B24,M$5:M$10,"#-504,788") -> #NAME? | O24: =K24-M24 -> #NAME? | Q24: =_xll.GetCtData("CO-AMOUNT","CONS-AMOUNT",$A$1:$A$4,$A24:$B24,Q$5:Q$10,"#-1347,528") -> #NAME? | S24: =_xll.GetCtData("CO-AMOUNT","CONS-AMOUNT",$A$1:$A$4,$A24:$B24,S$5:S$10,"#-1467,171") -> #NAME? | U24: =Q24-S24 -> #NAME?
D25: o/w International | E25: =E26+E27+E28+E29+E30+E32+E33 -> #NAME? | G25: =G26+G27+G28+G29+G30+G32+G33 -> #NAME? | I25: =E25-G25 -> #NAME? | K25: =K26+K27+K28+K29+K30+K32+K33 -> #NAME? | M25: =M26+M27+M28+M29+M30+M32+M33 -> #NAME? | O25: =K25-M25 -> #NAME? | Q25: =Q26+Q27+Q28+Q29+Q30+Q32+Q33 -> #NAME? | S25: =S26+S27+S28+S29+S30+S32+S33 -> #NAME? | U25: =Q25-S25 -> #NAME?
A26: OA sum AR028 | B26: RU sum AF026 | C26: ITA | D26: =CHOOSE([6]Traduction!$A$2,[6]Traduction!$A46,[6]Traduction!$B46) -> o/w Italy | E26: =_xll.GetCtData("CO-AMOUNT","CONS-AMOUNT",$A$1:$A$4,$A26:$B26,E$5:E$10,"#-88,982") -> #NAME? | G26: =_xll.GetCtData("CO-AMOUNT","CONS-AMOUNT",$A$1:$A$4,$A26:$B26,G$5:G$10,"#-88,772") -> #NAME? | I26: =E26-G26 -> #NAME? | K26: =_xll.GetCtData("CO-AMOUNT","CONS-AMOUNT",$A$1:$A$4,$A26:$B26,K$5:K$10,"#-67,413") -> #NAME? | M26: =_xll.GetCtData("CO-AMOUNT","CONS-AMOUNT",$A$1:$A$4,$A26:$B26,M$5:M$10,"#-60,617") -> #NAME? | O26: =K26-M26 -> #NAME? | Q26: =_xll.GetCtData("CO-AMOUNT","CONS-AMOUNT",$A$1:$A$4,$A26:$B26,Q$5:Q$10,"#-156,395") -> #NAME? | S26: =_xll.GetCtData("CO-AMOUNT","CONS-AMOUNT",$A$1:$A$4,$A26:$B26,S$5:S$10,"#-149,389") -> #NAME? | U26: =Q26-S26 -> #NAME? | W26: =_xll.GetCtData("CO-AMOUNT","CONS-AMOUNT",$A$1:$A$4,$A26:$B26,W$5:W$10,"#") -> #NAME? | Y26: =_xll.GetCtData("CO-AMOUNT","CONS-AMOUNT",$A$1:$A$4,$A26:$B26,Y$5:Y$10,"#") -> #NAME? | AA26: =W26-Y26 -> #NAME? | AC26: =_xll.GetCtData("CO-AMOUNT","CONS-AMOUNT",$A$1:$A$4,$A26:$B26,AC$5:AC$10,"#-1,438") -> #NAME? | AE26: =_xll.GetCtData("CO-AMOUNT","CONS-AMOUNT",$A$1:$A$4,$A26:$B26,AE$5:AE$10,"#-1,5") -> #NAME? | AG26: =AC26-AE26 -> #NAME? | AI26: =_xll.GetCtData("CO-AMOUNT","CONS-AMOUNT",$A$1:$A$4,$A26:$B26,AI$5:AI$10,"#") -> #NAME? | AK26: =_xll.GetCtData("CO-AMOUNT","CONS-AMOUNT",$A$1:$A$4,$A26:$B26,AK$5:AK$10,"#") -> #NAME? | AM26: =AI26-AK26 -> #NAME? | AO26: =_xll.GetCtData("CO-AMOUNT","CONS-AMOUNT",$A$1:$A$4,$A26:$B26,AO$5:AO$10,"#") -> #NAME? | AQ26: =_xll.GetCtData("CO-AMOUNT","CONS-AMOUNT",$A$1:$A$4,$A26:$B26,AQ$5:AQ$10,"#") -> #NAME? | AS26: =AO26-AQ26 -> #NAME? | AU26: =W26+AC26+AI26+AO26 -> #NAME? | AW26: =Y26+AE26+AK26+AQ26 -> #NAME? | AY26: =AU26-AW26 -> #NAME? | BA26: =+Q26-AO26 -> #NAME? | BC26: =+S26-AQ26 -> #NAME? | BE26: =BA26-BC26 -> #NAME? | BG26: =_xll.GetCtData("CO-AMOUNT","CONS-AMOUNT",$A$1:$A$4,$A26:$B26,BG$5:BG$10,"#") -> #NAME? | BI26: =_xll.GetCtData("CO-AMOUNT","CONS-AMOUNT",$A$1:$A$4,$A26:$B26,BI$5:BI$10,"#") -> #NAME? | BK26: =BG26-BI26 -> #NAME? | BN26: =_xll.GetCtData("CO-AMOUNT","CONS-AMOUNT",$A$1:$A$4,$A26:$B26,BN$5:BN$10,"#") -> #NAME? | BP26: =_xll.GetCtData("CO-AMOUNT","CONS-AMOUNT",$A$1:$A$4,$A26:$B26,BP$5:BP$10,"#") -> #NAME? | BR26: =BN26-BP26 -> #NAME?
A27: OA=OA040 | B27: RU=G-SP | C27: ESP | D27: =CHOOSE([6]Traduction!$A$2,[6]Traduction!$A48,[6]Traduction!$B48) -> o/w Spain | E27: =_xll.GetCtData("CO-AMOUNT","CONS-AMOUNT",$A$1:$A$4,$A27:$B27,E$5:E$10,"#24,798") -> #NAME? | G27: =_xll.GetCtData("CO-AMOUNT","CONS-AMOUNT",$A$1:$A$4,$A27:$B27,G$5:G$10,"#28,693") -> #NAME? | I27: =E27-G27 -> #NAME? | K27: =_xll.GetCtData("CO-AMOUNT","CONS-AMOUNT",$A$1:$A$4,$A27:$B27,K$5:K$10,"#-10,801") -> #NAME? | M27: =_xll.GetCtData("CO-AMOUNT","CONS-AMOUNT",$A$1:$A$4,$A27:$B27,M$5:M$10,"#-14,025") -> #NAME? | O27: =K27-M27 -> #NAME? | Q27: =_xll.GetCtData("CO-AMOUNT","CONS-AMOUNT",$A$1:$A$4,$A27:$B27,Q$5:Q$10,"#13,997") -> #NAME? | S27: =_xll.GetCtData("CO-AMOUNT","CONS-AMOUNT",$A$1:$A$4,$A27:$B27,S$5:S$10,"#14,668") -> #NAME? | U27: =Q27-S27 -> #NAME? | W27: =_xll.GetCtData("CO-AMOUNT","CONS-AMOUNT",$A$1:$A$4,$A27:$B27,W$5:W$10,"#") -> #NAME? | Y27: =_xll.GetCtData("CO-AMOUNT","CONS-AMOUNT",$A$1:$A$4,$A27:$B27,Y$5:Y$10,"#") -> #NAME? | AA27: =W27-Y27 -> #NAME? | AC27: =_xll.GetCtData("CO-AMOUNT","CONS-AMOUNT",$A$1:$A$4,$A27:$B27,AC$5:AC$10,"#4,75") -> #NAME? | AE27: =_xll.GetCtData("CO-AMOUNT","CONS-AMOUNT",$A$1:$A$4,$A27:$B27,AE$5:AE$10,"#-6,67") -> #NAME? | AG27: =AC27-AE27 -> #NAME? | AI27: =_xll.GetCtData("CO-AMOUNT","CONS-AMOUNT",$A$1:$A$4,$A27:$B27,AI$5:AI$10,"#") -> #NAME? | AK27: =_xll.GetCtData("CO-AMOUNT","CONS-AMOUNT",$A$1:$A$4,$A27:$B27,AK$5:AK$10,"#") -> #NAME? | AM27: =AI27-AK27 -> #NAME? | AO27: =_xll.GetCtData("CO-AMOUNT","CONS-AMOUNT",$A$1:$A$4,$A27:$B27,AO$5:AO$10,"#") -> #NAME? | AQ27: =_xll.GetCtData("CO-AMOUNT","CONS-AMOUNT",$A$1:$A$4,$A27:$B27,AQ$5:AQ$10,"#") -> #NAME? | AS27: =AO27-AQ27 -> #NAME? | AU27: =W27+AC27+AI27+AO27 -> #NAME? | AW27: =Y27+AE27+AK27+AQ27 -> #NAME? | AY27: =AU27-AW27 -> #NAME? | BA27: =+Q27-AO27 -> #NAME? | BC27: =+S27-AQ27 -> #NAME? | BE27: =BA27-BC27 -> #NAME? | BG27: =_xll.GetCtData("CO-AMOUNT","CONS-AMOUNT",$A$1:$A$4,$A27:$B27,BG$5:BG$10,"#") -> #NAME? | BI27: =_xll.GetCtData("CO-AMOUNT","CONS-AMOUNT",$A$1:$A$4,$A27:$B27,BI$5:BI$10,"#") -> #NAME? | BK27: =BG27-BI27 -> #NAME? | BN27: =_xll.GetCtData("CO-AMOUNT","CONS-AMOUNT",$A$1:$A$4,$A27:$B27,BN$5:BN$10,"#") -> #NAME? | BP27: =_xll.GetCtData("CO-AMOUNT","CONS-AMOUNT",$A$1:$A$4,$A27:$B27,BP$5:BP$10,"#") -> #NAME? | BR27: =BN27-BP27 -> #NAME?
A28: OA sum AR028 | B28: {RU=G-DE}+{RU=G-DEPROMO} | C28: DE | D28: =CHOOSE([6]Traduction!$A$2,[6]Traduction!$A49,[6]Traduction!$B49) -> o/w Germany | E28: =_xll.GetCtData("CO-AMOUNT","CONS-AMOUNT",$A$1:$A$4,$A28:$B28,E$5:E$10,"#-93,515") -> #NAME? | G28: =_xll.GetCtData("CO-AMOUNT","CONS-AMOUNT",$A$1:$A$4,$A28:$B28,G$5:G$10,"#-85,636") -> #NAME? | I28: =E28-G28 -> #NAME? | K28: =_xll.GetCtData("CO-AMOUNT","CONS-AMOUNT",$A$1:$A$4,$A28:$B28,K$5:K$10,"#-148,525") -> #NAME? | M28: =_xll.GetCtData("CO-AMOUNT","CONS-AMOUNT",$A$1:$A$4,$A28:$B28,M$5:M$10,"#-154,48") -> #NAME? | O28: =K28-M28 -> #NAME? | Q28: =_xll.GetCtData("CO-AMOUNT","CONS-AMOUNT",$A$1:$A$4,$A28:$B28,Q$5:Q$10,"#-242,04") -> #NAME? | S28: =_xll.GetCtData("CO-AMOUNT","CONS-AMOUNT",$A$1:$A$4,$A28:$B28,S$5:S$10,"#-240,116") -> #NAME? | U28: =Q28-S28 -> #NAME? | W28: =_xll.GetCtData("CO-AMOUNT","CONS-AMOUNT",$A$1:$A$4,$A28:$B28,W$5:W$10,"#") -> #NAME? | Y28: =_xll.GetCtData("CO-AMOUNT","CONS-AMOUNT",$A$1:$A$4,$A28:$B28,Y$5:Y$10,"#") -> #NAME? | AA28: =W28-Y28 -> #NAME? | AC28: =_xll.GetCtData("CO-AMOUNT","CONS-AMOUNT",$A$1:$A$4,$A28:$B28,AC$5:AC$10,"#-26,862") -> #NAME? | AE28: =_xll.GetCtData("CO-AMOUNT","CONS-AMOUNT",$A$1:$A$4,$A28:$B28,AE$5:AE$10,"#-26,003") -> #NAME? | AG28: =AC28-AE28 -> #NAME? | AI28: =_xll.GetCtData("CO-AMOUNT","CONS-AMOUNT",$A$1:$A$4,$A28:$B28,AI$5:AI$10,"#") -> #NAME? | AK28: =_xll.GetCtData("CO-AMOUNT","CONS-AMOUNT",$A$1:$A$4,$A28:$B28,AK$5:AK$10,"#") -> #NAME? | AM28: =AI28-AK28 -> #NAME? | AO28: =_xll.GetCtData("CO-AMOUNT","CONS-AMOUNT",$A$1:$A$4,$A28:$B28,AO$5:AO$10,"#-0,244") -> #NAME? | AQ28: =_xll.GetCtData("CO-AMOUNT","CONS-AMOUNT",$A$1:$A$4,$A28:$B28,AQ$5:AQ$10,"#-0,18") -> #NAME? | AS28: =AO28-AQ28 -> #NAME? | AU28: =W28+AC28+AI28+AO28 -> #NAME? | AW28: =Y28+AE28+AK28+AQ28 -> #NAME? | AY28: =AU28-AW28 -> #NAME? | BA28: =+Q28-AO28 -> #NAME? | BC28: =+S28-AQ28 -> #NAME? | BE28: =BA28-BC28 -> #NAME? | BG28: =_xll.GetCtData("CO-AMOUNT","CONS-AMOUNT",$A$1:$A$4,$A28:$B28,BG$5:BG$10,"#-0,244") -> #NAME? | BI28: =_xll.GetCtData("CO-AMOUNT","CONS-AMOUNT",$A$1:$A$4,$A28:$B28,BI$5:BI$10,"#-0,18") -> #NAME? | BK28: =BG28-BI28 -> #NAME? | BN28: =_xll.GetCtData("CO-AMOUNT","CONS-AMOUNT",$A$1:$A$4,$A28:$B28,BN$5:BN$10,"#") -> #NAME? | BP28: =_xll.GetCtData("CO-AMOUNT","CONS-AMOUNT",$A$1:$A$4,$A28:$B28,BP$5:BP$10,"#") -> #NAME? | BR28: =BN28-BP28 -> #NAME?
A29: OA sum AR028 | B29: {RU=G-PRTPROMO} | C29: PRT | D29: =CHOOSE([6]Traduction!$A$2,[6]Traduction!$A50,[6]Traduction!$B50) -> o/w Portugal | E29: =_xll.GetCtData("CO-AMOUNT","CONS-AMOUNT",$A$1:$A$4,$A29:$B29,E$5:E$10,"#321") -> #NAME? | G29: =_xll.GetCtData("CO-AMOUNT","CONS-AMOUNT",$A$1:$A$4,$A29:$B29,G$5:G$10,"#200,183") -> #NAME? | I29: =E29-G29 -> #NAME? | K29: =_xll.GetCtData("CO-AMOUNT","CONS-AMOUNT",$A$1:$A$4,$A29:$B29,K$5:K$10,"#-182,3") -> #NAME? | M29: =_xll.GetCtData("CO-AMOUNT","CONS-AMOUNT",$A$1:$A$4,$A29:$B29,M$5:M$10,"#-231,556") -> #NAME? | O29: =K29-M29 -> #NAME? | Q29: =_xll.GetCtData("CO-AMOUNT","CONS-AMOUNT",$A$1:$A$4,$A29:$B29,Q$5:Q$10,"#138,7") -> #NAME? | S29: =_xll.GetCtData("CO-AMOUNT","CONS-AMOUNT",$A$1:$A$4,$A29:$B29,S$5:S$10,"#-31,373") -> #NAME? | U29: =Q29-S29 -> #NAME? | W29: =_xll.GetCtData("CO-AMOUNT","CONS-AMOUNT",$A$1:$A$4,$A29:$B29,W$5:W$10,"#") -> #NAME? | Y29: =_xll.GetCtData("CO-AMOUNT","CONS-AMOUNT",$A$1:$A$4,$A29:$B29,Y$5:Y$10,"#") -> #NAME? | AA29: =W29-Y29 -> #NAME? | AC29: =_xll.GetCtData("CO-AMOUNT","CONS-AMOUNT",$A$1:$A$4,$A29:$B29,AC$5:AC$10,"#-24,25") -> #NAME? | AE29: =_xll.GetCtData("CO-AMOUNT","CONS-AMOUNT",$A$1:$A$4,$A29:$B29,AE$5:AE$10,"#-24,333") -> #NAME? | AG29: =AC29-AE29 -> #NAME? | AI29: =_xll.GetCtData("CO-AMOUNT","CONS-AMOUNT",$A$1:$A$4,$A29:$B29,AI$5:AI$10,"#") -> #NAME? | AK29: =_xll.GetCtData("CO-AMOUNT","CONS-AMOUNT",$A$1:$A$4,$A29:$B29,AK$5:AK$10,"#") -> #NAME? | AM29: =AI29-AK29 -> #NAME? | AO29: =_xll.GetCtData("CO-AMOUNT","CONS-AMOUNT",$A$1:$A$4,$A29:$B29,AO$5:AO$10,"#-8,1") -> #NAME? | AQ29: =_xll.GetCtData("CO-AMOUNT","CONS-AMOUNT",$A$1:$A$4,$A29:$B29,AQ$5:AQ$10,"#-8,692") -> #NAME? | AS29: =AO29-AQ29 -> #NAME? | AU29: =W29+AC29+AI29+AO29 -> #NAME? | AW29: =Y29+AE29+AK29+AQ29 -> #NAME? | AY29: =AU29-AW29 -> #NAME? | BA29: =+Q29-AO29 -> #NAME? | BC29: =+S29-AQ29 -> #NAME? | BE29: =BA29-BC29 -> #NAME? | BG29: =_xll.GetCtData("CO-AMOUNT","CONS-AMOUNT",$A$1:$A$4,$A29:$B29,BG$5:BG$10,"#") -> #NAME? | BI29: =_xll.GetCtData("CO-AMOUNT","CONS-AMOUNT",$A$1:$A$4,$A29:$B29,BI$5:BI$10,"#-8,692") -> #NAME? | BK29: =BG29-BI29 -> #NAME? | BN29: =_xll.GetCtData("CO-AMOUNT","CONS-AMOUNT",$A$1:$A$4,$A29:$B29,BN$5:BN$10,"#-8,1") -> #NAME? | BP29: =_xll.GetCtData("CO-AMOUNT","CONS-AMOUNT",$A$1:$A$4,$A29:$B29,BP$5:BP$10,"#") -> #NAME? | BR29: =BN29-BP29 -> #NAME?
A30: {OA=OA040}+{OA=OA041} | B30: RU=G-UKPROMO | C30: UK | D30: =CHOOSE([6]Traduction!$A$2,[6]Traduction!$A52,[6]Traduction!$B52) -> o/w UK | E30: =_xll.GetCtData("CO-AMOUNT","CONS-AMOUNT",$A$1:$A$4,$A30:$B30,E$5:E$10,"#12,6338514234335") -> #NAME? | G30: =_xll.GetCtData("CO-AMOUNT","CONS-AMOUNT",$A$1:$A$4,$A30:$B30,G$5:G$10,"#12,5719900262874") -> #NAME? | I30: =E30-G30 -> #NAME? | K30: =_xll.GetCtData("CO-AMOUNT","CONS-AMOUNT",$A$1:$A$4,$A30:$B30,K$5:K$10,"#-80,2485658327114") -> #NAME? | M30: =_xll.GetCtData("CO-AMOUNT","CONS-AMOUNT",$A$1:$A$4,$A30:$B30,M$5:M$10,"#-67,7849407197164") -> #NAME? | O30: =K30-M30 -> #NAME? | Q30: =_xll.GetCtData("CO-AMOUNT","CONS-AMOUNT",$A$1:$A$4,$A30:$B30,Q$5:Q$10,"#-67,6147144092779") -> #NAME? | S30: =_xll.GetCtData("CO-AMOUNT","CONS-AMOUNT",$A$1:$A$4,$A30:$B30,S$5:S$10,"#-55,212950693429") -> #NAME? | U30: =Q30-S30 -> #NAME? | W30: =_xll.GetCtData("CO-AMOUNT","CONS-AMOUNT",$A$1:$A$4,$A30:$B30,W$5:W$10,"#") -> #NAME? | Y30: =_xll.GetCtData("CO-AMOUNT","CONS-AMOUNT",$A$1:$A$4,$A30:$B30,Y$5:Y$10,"#") -> #NAME? | AA30: =W30-Y30 -> #NAME? | AC30: =_xll.GetCtData("CO-AMOUNT","CONS-AMOUNT",$A$1:$A$4,$A30:$B30,AC$5:AC$10,"#") -> #NAME? | AE30: =_xll.GetCtData("CO-AMOUNT","CONS-AMOUNT",$A$1:$A$4,$A30:$B30,AE$5:AE$10,"#") -> #NAME? | AG30: =AC30-AE30 -> #NAME? | AI30: =_xll.GetCtData("CO-AMOUNT","CONS-AMOUNT",$A$1:$A$4,$A30:$B30,AI$5:AI$10,"#") -> #NAME? | AK30: =_xll.GetCtData("CO-AMOUNT","CONS-AMOUNT",$A$1:$A$4,$A30:$B30,AK$5:AK$10,"#") -> #NAME? | AM30: =AI30-AK30 -> #NAME? | AO30: =_xll.GetCtData("CO-AMOUNT","CONS-AMOUNT",$A$1:$A$4,$A30:$B30,AO$5:AO$10,"#-1,47414127821284") -> #NAME? | AQ30: =_xll.GetCtData("CO-AMOUNT","CONS-AMOUNT",$A$1:$A$4,$A30:$B30,AQ$5:AQ$10,"#-1,4878777187074") -> #NAME? | AS30: =AO30-AQ30 -> #NAME? | AU30: =W30+AC30+AI30+AO30 -> #NAME? | AW30: =Y30+AE30+AK30+AQ30 -> #NAME? | AY30: =AU30-AW30 -> #NAME? | BA30: =+Q30-AO30 -> #NAME? | BC30: =+S30-AQ30 -> #NAME? | BE30: =BA30-BC30 -> #NAME? | BG30: =_xll.GetCtData("CO-AMOUNT","CONS-AMOUNT",$A$1:$A$4,$A30:$B30,BG$5:BG$10,"#-1,47414127821284") -> #NAME? | BI30: =_xll.GetCtData("CO-AMOUNT","CONS-AMOUNT",$A$1:$A$4,$A30:$B30,BI$5:BI$10,"#-1,4878777187074") -> #NAME? | BK30: =BG30-BI30 -> #NAME? | BN30: =_xll.GetCtData("CO-AMOUNT","CONS-AMOUNT",$A$1:$A$4,$A30:$B30,BN$5:BN$10,"#") -> #NAME? | BP30: =_xll.GetCtData("CO-AMOUNT","CONS-AMOUNT",$A$1:$A$4,$A30:$B30,BP$5:BP$10,"#") -> #NAME? | BR30: =BN30-BP30 -> #NAME?
A31: {OA=OA040}+{OA=OA041} | B31: RU=G-UKPROMO | C31: UK GBP | D31: UK (GBP) | E31: =_xll.GetCtData("CO-AMOUNT","AMOUNT",$A$1:$A$4,$A31:$B31,E$5:E$10,"#10,97") -> #NAME? | G31: =_xll.GetCtData("CO-AMOUNT","AMOUNT",$A$1:$A$4,$A31:$B31,G$5:G$10,"#10,9") -> #NAME? | I31: =E31-G31 -> #NAME? | K31: =_xll.GetCtData("CO-AMOUNT","AMOUNT",$A$1:$A$4,$A31:$B31,K$5:K$10,"#-69,68") -> #NAME? | M31: =_xll.GetCtData("CO-AMOUNT","AMOUNT",$A$1:$A$4,$A31:$B31,M$5:M$10,"#-58,77") -> #NAME? | O31: =K31-M31 -> #NAME? | Q31: =_xll.GetCtData("CO-AMOUNT","AMOUNT",$A$1:$A$4,$A31:$B31,Q$5:Q$10,"#-58,71") -> #NAME? | S31: =_xll.GetCtData("CO-AMOUNT","AMOUNT",$A$1:$A$4,$A31:$B31,S$5:S$10,"#-47,87") -> #NAME? | U31: =Q31-S31 -> #NAME? | W31: =_xll.GetCtData("CO-AMOUNT","AMOUNT",$A$1:$A$4,$A31:$B31,W$5:W$10,"#") -> #NAME? | Y31: =_xll.GetCtData("CO-AMOUNT","AMOUNT",$A$1:$A$4,$A31:$B31,Y$5:Y$10,"#") -> #NAME? | AA31: =W31-Y31 -> #NAME? | AC31: =_xll.GetCtData("CO-AMOUNT","AMOUNT",$A$1:$A$4,$A31:$B31,AC$5:AC$10,"#") -> #NAME? | AE31: =_xll.GetCtData("CO-AMOUNT","AMOUNT",$A$1:$A$4,$A31:$B31,AE$5:AE$10,"#") -> #NAME? | AG31: =AC31-AE31 -> #NAME? | AI31: =_xll.GetCtData("CO-AMOUNT","AMOUNT",$A$1:$A$4,$A31:$B31,AI$5:AI$10,"#") -> #NAME? | AK31: =_xll.GetCtData("CO-AMOUNT","AMOUNT",$A$1:$A$4,$A31:$B31,AK$5:AK$10,"#") -> #NAME? | AM31: =AI31-AK31 -> #NAME? | AO31: =_xll.GetCtData("CO-AMOUNT","AMOUNT",$A$1:$A$4,$A31:$B31,AO$5:AO$10,"#-1,28") -> #NAME? | AQ31: =_xll.GetCtData("CO-AMOUNT","AMOUNT",$A$1:$A$4,$A31:$B31,AQ$5:AQ$10,"#-1,29") -> #NAME? | AS31: =AO31-AQ31 -> #NAME? | AU31: =W31+AC31+AI31+AO31 -> #NAME? | AW31: =Y31+AE31+AK31+AQ31 -> #NAME? | AY31: =AU31-AW31 -> #NAME? | BA31: =+Q31-AO31 -> #NAME? | BC31: =+S31-AQ31 -> #NAME? | BE31: =BA31-BC31 -> #NAME? | BG31: =_xll.GetCtData("CO-AMOUNT","AMOUNT",$A$1:$A$4,$A31:$B31,BG$5:BG$10,"#-1,28") -> #NAME? | BI31: =_xll.GetCtData("CO-AMOUNT","AMOUNT",$A$1:$A$4,$A31:$B31,BI$5:BI$10,"#-1,29") -> #NAME? | BK31: =BG31-BI31 -> #NAME? | BN31: =_xll.GetCtData("CO-AMOUNT","AMOUNT",$A$1:$A$4,$A31:$B31,BN$5:BN$10,"#") -> #NAME? | BP31: =_xll.GetCtData("CO-AMOUNT","AMOUNT",$A$1:$A$4,$A31:$B31,BP$5:BP$10,"#") -> #NAME? | BR31: =BN31-BP31 -> #NAME?
A32: OA sum AR028 | B32: RU=G-LX | C32: LUX | D32: =CHOOSE([6]Traduction!$A$2,[6]Traduction!$A53,[6]Traduction!$B53) -> o/w Luxembourg | E32: =_xll.GetCtData("CO-AMOUNT","CONS-AMOUNT",$A$1:$A$4,$A32:$B32,E$5:E$10,"#") -> #NAME? | G32: =_xll.GetCtData("CO-AMOUNT","CONS-AMOUNT",$A$1:$A$4,$A32:$B32,G$5:G$10,"#") -> #NAME? | I32: =E32-G32 -> #NAME? | K32: =_xll.GetCtData("CO-AMOUNT","CONS-AMOUNT",$A$1:$A$4,$A32:$B32,K$5:K$10,"#") -> #NAME? | M32: =_xll.GetCtData("CO-AMOUNT","CONS-AMOUNT",$A$1:$A$4,$A32:$B32,M$5:M$10,"#") -> #NAME? | O32: =K32-M32 -> #NAME? | Q32: =_xll.GetCtData("CO-AMOUNT","CONS-AMOUNT",$A$1:$A$4,$A32:$B32,Q$5:Q$10,"#") -> #NAME? | S32: =_xll.GetCtData("CO-AMOUNT","CONS-AMOUNT",$A$1:$A$4,$A32:$B32,S$5:S$10,"#") -> #NAME? | U32: =Q32-S32 -> #NAME? | W32: =_xll.GetCtData("CO-AMOUNT","CONS-AMOUNT",$A$1:$A$4,$A32:$B32,W$5:W$10,"#") -> #NAME? | Y32: =_xll.GetCtData("CO-AMOUNT","CONS-AMOUNT",$A$1:$A$4,$A32:$B32,Y$5:Y$10,"#") -> #NAME? | AA32: =W32-Y32 -> #NAME? | AC32: =_xll.GetCtData("CO-AMOUNT","CONS-AMOUNT",$A$1:$A$4,$A32:$B32,AC$5:AC$10,"#") -> #NAME? | AE32: =_xll.GetCtData("CO-AMOUNT","CONS-AMOUNT",$A$1:$A$4,$A32:$B32,AE$5:AE$10,"#") -> #NAME? | AG32: =AC32-AE32 -> #NAME? | AI32: =_xll.GetCtData("CO-AMOUNT","CONS-AMOUNT",$A$1:$A$4,$A32:$B32,AI$5:AI$10,"#") -> #NAME? | AK32: =_xll.GetCtData("CO-AMOUNT","CONS-AMOUNT",$A$1:$A$4,$A32:$B32,AK$5:AK$10,"#") -> #NAME? | AM32: =AI32-AK32 -> #NAME? | AO32: =_xll.GetCtData("CO-AMOUNT","CONS-AMOUNT",$A$1:$A$4,$A32:$B32,AO$5:AO$10,"#") -> #NAME? | AQ32: =_xll.GetCtData("CO-AMOUNT","CONS-AMOUNT",$A$1:$A$4,$A32:$B32,AQ$5:AQ$10,"#") -> #NAME? | AS32: =AO32-AQ32 -> #NAME? | AU32: =W32+AC32+AI32+AO32 -> #NAME? | AW32: =Y32+AE32+AK32+AQ32 -> #NAME? | AY32: =AU32-AW32 -> #NAME? | BA32: =+Q32-AO32 -> #NAME? | BC32: =+S32-AQ32 -> #NAME? | BE32: =BA32-BC32 -> #NAME? | BG32: =_xll.GetCtData("CO-AMOUNT","CONS-AMOUNT",$A$1:$A$4,$A32:$B32,BG$5:BG$10,"#") -> #NAME? | BI32: =_xll.GetCtData("CO-AMOUNT","CONS-AMOUNT",$A$1:$A$4,$A32:$B32,BI$5:BI$10,"#") -> #NAME? | BK32: =BG32-BI32 -> #NAME? | BN32: =_xll.GetCtData("CO-AMOUNT","CONS-AMOUNT",$A$1:$A$4,$A32:$B32,BN$5:BN$10,"#") -> #NAME? | BP32: =_xll.GetCtData("CO-AMOUNT","CONS-AMOUNT",$A$1:$A$4,$A32:$B32,BP$5:BP$10,"#") -> #NAME? | BR32: =BN32-BP32 -> #NAME?
A33: OA=OA045 | B33: {RU=G-FRMP} | C33: FR | D33: =CHOOSE([6]Traduction!$A$2,[6]Traduction!$A54,[6]Traduction!$B54) -> o/w International Teams | E33: =_xll.GetCtData("CO-AMOUNT","CONS-AMOUNT",$A$1:$A$4,$A33:$B33,E$5:E$10,"#96,35") -> #NAME? | G33: =_xll.GetCtData("CO-AMOUNT","CONS-AMOUNT",$A$1:$A$4,$A33:$B33,G$5:G$10,"#426,4") -> #NAME? | I33: =E33-G33 -> #NAME? | K33: =_xll.GetCtData("CO-AMOUNT","CONS-AMOUNT",$A$1:$A$4,$A33:$B33,K$5:K$10,"#-108,71") -> #NAME? | M33: =_xll.GetCtData("CO-AMOUNT","CONS-AMOUNT",$A$1:$A$4,$A33:$B33,M$5:M$10,"#-111,61") -> #NAME? | O33: =K33-M33 -> #NAME? | Q33: =_xll.GetCtData("CO-AMOUNT","CONS-AMOUNT",$A$1:$A$4,$A33:$B33,Q$5:Q$10,"#-12,36") -> #NAME? | S33: =_xll.GetCtData("CO-AMOUNT","CONS-AMOUNT",$A$1:$A$4,$A33:$B33,S$5:S$10,"#314,79") -> #NAME? | U33: =Q33-S33 -> #NAME? | W33: =_xll.GetCtData("CO-AMOUNT","CONS-AMOUNT",$A$1:$A$4,$A33:$B33,W$5:W$10,"#") -> #NAME? | Y33: =_xll.GetCtData("CO-AMOUNT","CONS-AMOUNT",$A$1:$A$4,$A33:$B33,Y$5:Y$10,"#") -> #NAME? | AA33: =W33-Y33 -> #NAME? | AC33: =_xll.GetCtData("CO-AMOUNT","CONS-AMOUNT",$A$1:$A$4,$A33:$B33,AC$5:AC$10,"#70,78") -> #NAME? | AE33: =_xll.GetCtData("CO-AMOUNT","CONS-AMOUNT",$A$1:$A$4,$A33:$B33,AE$5:AE$10,"#67,77") -> #NAME? | AG33: =AC33-AE33 -> #NAME? | AI33: =_xll.GetCtData("CO-AMOUNT","CONS-AMOUNT",$A$1:$A$4,$A33:$B33,AI$5:AI$10,"#") -> #NAME? | AK33: =_xll.GetCtData("CO-AMOUNT","CONS-AMOUNT",$A$1:$A$4,$A33:$B33,AK$5:AK$10,"#") -> #NAME? | AM33: =AI33-AK33 -> #NAME? | AO33: =_xll.GetCtData("CO-AMOUNT","CONS-AMOUNT",$A$1:$A$4,$A33:$B33,AO$5:AO$10,"#") -> #NAME? | AQ33: =_xll.GetCtData("CO-AMOUNT","CONS-AMOUNT",$A$1:$A$4,$A33:$B33,AQ$5:AQ$10,"#") -> #NAME? | AS33: =AO33-AQ33 -> #NAME? | AU33: =W33+AC33+AI33+AO33 -> #NAME? | AW33: =Y33+AE33+AK33+AQ33 -> #NAME? | AY33: =AU33-AW33 -> #NAME? | BA33: =+Q33-AO33 -> #NAME? | BC33: =+S33-AQ33 -> #NAME? | BE33: =BA33-BC33 -> #NAME? | BG33: =_xll.GetCtData("CO-AMOUNT","CONS-AMOUNT",$A$1:$A$4,$A33:$B33,BG$5:BG$10,"#") -> #NAME? | BI33: =_xll.GetCtData("CO-AMOUNT","CONS-AMOUNT",$A$1:$A$4,$A33:$B33,BI$5:BI$10,"#") -> #NAME? | BK33: =BG33-BI33 -> #NAME? | BN33: =_xll.GetCtData("CO-AMOUNT","CONS-AMOUNT",$A$1:$A$4,$A33:$B33,BN$5:BN$10,"#") -> #NAME? | BP33: =_xll.GetCtData("CO-AMOUNT","CONS-AMOUNT",$A$1:$A$4,$A33:$B33,BP$5:BP$10,"#") -> #NAME? | BR33: =BN33-BP33 -> #NAME?
D34: Investment Management | E34: =SUM(E35:E46)-E44-E39-E40 -> #NAME? | G34: =SUM(G35:G46)-G44-G39-G40 -> #NAME? | I34: =E34-G34 -> #NAME? | K34: =SUM(K35:K46)-K44-K39-K40 -> #NAME? | M34: =SUM(M35:M46)-M44-M39-M40 -> #NAME? | O34: =K34-M34 -> #NAME? | Q34: =SUM(Q35:Q46)-Q44-Q39-Q40 -> #NAME? | S34: =SUM(S35:S46)-S44-S39-S40 -> #NAME? | U34: =Q34-S34 -> #NAME? | W34: =SUM(W35:W46)-W44 -> #NAME? | Y34: =SUM(Y35:Y46)-Y44 -> #NAME? | AA34: =W34-Y34 -> #NAME? | AC34: =SUM(AC35:AC46)-AC44 -> #NAME? | AE34: =SUM(AE35:AE46)-AE44 -> #NAME? | AG34: =AC34-AE34 -> #NAME? | AI34: =SUM(AI35:AI46)-AI44 -> #NAME? | AK34: =SUM(AK35:AK46)-AK44 -> #NAME? | AM34: =AI34-AK34 -> #NAME? | AO34: =SUM(AO35:AO46)-AO44 -> #NAME? | AQ34: =SUM(AQ35:AQ46)-AQ44 -> #NAME? | AS34: =AO34-AQ34 -> #NAME? | AU34: =W34+AC34+AI34+AO34 -> #NAME? | AW34: =Y34+AE34+AK34+AQ34 -> #NAME? | AY34: =AU34-AW34 -> #NAME? | BA34: =+Q34-AO34 -> #NAME? | BC34: =+S34-AQ34 -> #NAME? | BE34: =BA34-BC34 -> #NAME? | BG34: =SUM(BG35:BG46)-BG44 -> #NAME? | BI34: =SUM(BI35:BI46)-BI44 -> #NAME? | BK34: =BG34-BI34 -> #NAME? | BN34: =SUM(BN35:BN46)-BN44 -> #NAME? | BP34: =SUM(BP35:BP46)-BP44 -> #NAME? | BR34: =BN34-BP34 -> #NAME?
A35: {OA=OA060}+{OA=OA061}+{OA=OA069}+{OA=OA060E}+{OA=OA060O}+{OA=OA061O} | B35: {RU=G-CENTRAL}+{RU=P-CENTRAL} | C35: CENTRAL | D35: G-central | E35: =_xll.GetCtData("CO-AMOUNT","CONS-AMOUNT",$A$1:$A$4,$A35:$B35,E$5:E$10,"#") -> #NAME? | G35: =_xll.GetCtData("CO-AMOUNT","CONS-AMOUNT",$A$1:$A$4,$A35:$B35,G$5:G$10,"#") -> #NAME? | I35: =E35-G35 -> #NAME? | K35: =_xll.GetCtData("CO-AMOUNT","CONS-AMOUNT",$A$1:$A$4,$A35:$B35,K$5:K$10,"#") -> #NAME? | M35: =_xll.GetCtData("CO-AMOUNT","CONS-AMOUNT",$A$1:$A$4,$A35:$B35,M$5:M$10,"#") -> #NAME? | O35: =K35-M35 -> #NAME? | Q35: =_xll.GetCtData("CO-AMOUNT","CONS-AMOUNT",$A$1:$A$4,$A35:$B35,Q$5:Q$10,"#") -> #NAME? | S35: =_xll.GetCtData("CO-AMOUNT","CONS-AMOUNT",$A$1:$A$4,$A35:$B35,S$5:S$10,"#") -> #NAME? | U35: =Q35-S35 -> #NAME? | W35: =_xll.GetCtData("CO-AMOUNT","CONS-AMOUNT",$A$1:$A$4,$A35:$B35,W$5:W$10,"#") -> #NAME? | Y35: =_xll.GetCtData("CO-AMOUNT","CONS-AMOUNT",$A$1:$A$4,$A35:$B35,Y$5:Y$10,"#") -> #NAME? | AA35: =W35-Y35 -> #NAME? | AC35: =_xll.GetCtData("CO-AMOUNT","CONS-AMOUNT",$A$1:$A$4,$A35:$B35,AC$5:AC$10,"#") -> #NAME? | AE35: =_xll.GetCtData("CO-AMOUNT","CONS-AMOUNT",$A$1:$A$4,$A35:$B35,AE$5:AE$10,"#") -> #NAME? | AG35: =AC35-AE35 -> #NAME? | AI35: =_xll.GetCtData("CO-AMOUNT","CONS-AMOUNT",$A$1:$A$4,$A35:$B35,AI$5:AI$10,"#") -> #NAME? | AK35: =_xll.GetCtData("CO-AMOUNT","CONS-AMOUNT",$A$1:$A$4,$A35:$B35,AK$5:AK$10,"#") -> #NAME? | AM35: =AI35-AK35 -> #NAME? | AO35: =_xll.GetCtData("CO-AMOUNT","CONS-AMOUNT",$A$1:$A$4,$A35:$B35,AO$5:AO$10,"#") -> #NAME? | AQ35: =_xll.GetCtData("CO-AMOUNT","CONS-AMOUNT",$A$1:$A$4,$A35:$B35,AQ$5:AQ$10,"#") -> #NAME? | AS35: =AO35-AQ35 -> #NAME? | AU35: =W35+AC35+AI35+AO35 -> #NAME? | AW35: =Y35+AE35+AK35+AQ35 -> #NAME? | AY35: =AU35-AW35 -> #NAME? | BA35: =+Q35-AO35 -> #NAME? | BC35: =+S35-AQ35 -> #NAME? | BE35: =BA35-BC35 -> #NAME? | BG35: =_xll.GetCtData("CO-AMOUNT","CONS-AMOUNT",$A$1:$A$4,$A35:$B35,BG$5:BG$10,"#") -> #NAME? | BI35: =_xll.GetCtData("CO-AMOUNT","CONS-AMOUNT",$A$1:$A$4,$A35:$B35,BI$5:BI$10,"#") -> #NAME? | BK35: =BG35-BI35 -> #NAME? | BN35: =_xll.GetCtData("CO-AMOUNT","CONS-AMOUNT",$A$1:$A$4,$A35:$B35,BN$5:BN$10,"#") -> #NAME? | BP35: =_xll.GetCtData("CO-AMOUNT","CONS-AMOUNT",$A$1:$A$4,$A35:$B35,BP$5:BP$10,"#") -> #NAME? | BR35: =BN35-BP35 -> #NAME?
A36: {OA=OA069}+{OA=OA005} | B36: {RU=G-FRMP}+{RU=P-FRMP}+{RU=G-REIMDE}+{RU=G-REIMI} | C36: DE | D36: =CHOOSE([6]Traduction!$A$2,[6]Traduction!$A62,[6]Traduction!$B62) -> o/w Coordination Team | E36: =_xll.GetCtData("CO-AMOUNT","CONS-AMOUNT",$A$1:$A$4,$A36:$B36,E$5:E$10,"#1,00000000054479E-03") -> #NAME? | G36: =_xll.GetCtData("CO-AMOUNT","CONS-AMOUNT",$A$1:$A$4,$A36:$B36,G$5:G$10,"#-27,053") -> #NAME? | I36: =E36-G36 -> #NAME? | K36: =_xll.GetCtData("CO-AMOUNT","CONS-AMOUNT",$A$1:$A$4,$A36:$B36,K$5:K$10,"#-1,182") -> #NAME? | M36: =_xll.GetCtData("CO-AMOUNT","CONS-AMOUNT",$A$1:$A$4,$A36:$B36,M$5:M$10,"#-0,398") -> #NAME? | O36: =K36-M36 -> #NAME? | Q36: =_xll.GetCtData("CO-AMOUNT","CONS-AMOUNT",$A$1:$A$4,$A36:$B36,Q$5:Q$10,"#-1,18100000000015") -> #NAME? | S36: =_xll.GetCtData("CO-AMOUNT","CONS-AMOUNT",$A$1:$A$4,$A36:$B36,S$5:S$10,"#-27,451") -> #NAME? | U36: =Q36-S36 -> #NAME? | W36: =_xll.GetCtData("CO-AMOUNT","CONS-AMOUNT",$A$1:$A$4,$A36:$B36,W$5:W$10,"#") -> #NAME? | Y36: =_xll.GetCtData("CO-AMOUNT","CONS-AMOUNT",$A$1:$A$4,$A36:$B36,Y$5:Y$10,"#") -> #NAME? | AA36: =W36-Y36 -> #NAME? | AC36: =_xll.GetCtData("CO-AMOUNT","CONS-AMOUNT",$A$1:$A$4,$A36:$B36,AC$5:AC$10,"#") -> #NAME? | AE36: =_xll.GetCtData("CO-AMOUNT","CONS-AMOUNT",$A$1:$A$4,$A36:$B36,AE$5:AE$10,"#") -> #NAME? | AG36: =AC36-AE36 -> #NAME? | AI36: =_xll.GetCtData("CO-AMOUNT","CONS-AMOUNT",$A$1:$A$4,$A36:$B36,AI$5:AI$10,"#") -> #NAME? | AK36: =_xll.GetCtData("CO-AMOUNT","CONS-AMOUNT",$A$1:$A$4,$A36:$B36,AK$5:AK$10,"#") -> #NAME? | AM36: =AI36-AK36 -> #NAME? | AO36: =_xll.GetCtData("CO-AMOUNT","CONS-AMOUNT",$A$1:$A$4,$A36:$B36,AO$5:AO$10,"#") -> #NAME? | AQ36: =_xll.GetCtData("CO-AMOUNT","CONS-AMOUNT",$A$1:$A$4,$A36:$B36,AQ$5:AQ$10,"#") -> #NAME? | AS36: =AO36-AQ36 -> #NAME? | AU36: =W36+AC36+AI36+AO36 -> #NAME? | AW36: =Y36+AE36+AK36+AQ36 -> #NAME? | AY36: =AU36-AW36 -> #NAME? | BA36: =+Q36-AO36 -> #NAME? | BC36: =+S36-AQ36 -> #NAME? | BE36: =BA36-BC36 -> #NAME? | BG36: =_xll.GetCtData("CO-AMOUNT","CONS-AMOUNT",$A$1:$A$4,$A36:$B36,BG$5:BG$10,"#") -> #NAME? | BI36: =_xll.GetCtData("CO-AMOUNT","CONS-AMOUNT",$A$1:$A$4,$A36:$B36,BI$5:BI$10,"#") -> #NAME? | BK36: =BG36-BI36 -> #NAME? | BN36: =_xll.GetCtData("CO-AMOUNT","CONS-AMOUNT",$A$1:$A$4,$A36:$B36,BN$5:BN$10,"#") -> #NAME? | BP36: =_xll.GetCtData("CO-AMOUNT","CONS-AMOUNT",$A$1:$A$4,$A36:$B36,BP$5:BP$10,"#") -> #NAME? | BR36: =BN36-BP36 -> #NAME?
A37: {OA=OA060}+{OA=OA060E}+{OA=OA060O}+{OA=OA061}+{OA=OA061O} | B37: {RU=G-FRMP}+{RU=P-FRMP} | C37: FR | D37: =CHOOSE([6]Traduction!$A$2,[6]Traduction!$A45,[6]Traduction!$B45) -> o/w France | E37: =_xll.GetCtData("CO-AMOUNT","CONS-AMOUNT",$A$1:$A$4,$A37:$B37,E$5:E$10,"#-1,99999999995271E-03") -> #NAME? | G37: =_xll.GetCtData("CO-AMOUNT","CONS-AMOUNT",$A$1:$A$4,$A37:$B37,G$5:G$10,"#") -> #NAME? | I37: =E37-G37 -> #NAME? | K37: =_xll.GetCtData("CO-AMOUNT","CONS-AMOUNT",$A$1:$A$4,$A37:$B37,K$5:K$10,"#") -> #NAME? | M37: =_xll.GetCtData("CO-AMOUNT","CONS-AMOUNT",$A$1:$A$4,$A37:$B37,M$5:M$10,"#") -> #NAME? | O37: =K37-M37 -> #NAME? | Q37: =_xll.GetCtData("CO-AMOUNT","CONS-AMOUNT",$A$1:$A$4,$A37:$B37,Q$5:Q$10,"#-1,99999999995271E-03") -> #NAME? | S37: =_xll.GetCtData("CO-AMOUNT","CONS-AMOUNT",$A$1:$A$4,$A37:$B37,S$5:S$10,"#") -> #NAME? | U37: =Q37-S37 -> #NAME? | W37: =_xll.GetCtData("CO-AMOUNT","CONS-AMOUNT",$A$1:$A$4,$A37:$B37,W$5:W$10,"#") -> #NAME? | Y37: =_xll.GetCtData("CO-AMOUNT","CONS-AMOUNT",$A$1:$A$4,$A37:$B37,Y$5:Y$10,"#") -> #NAME? | AA37: =W37-Y37 -> #NAME? | AC37: =_xll.GetCtData("CO-AMOUNT","CONS-AMOUNT",$A$1:$A$4,$A37:$B37,AC$5:AC$10,"#") -> #NAME? | AE37: =_xll.GetCtData("CO-AMOUNT","CONS-AMOUNT",$A$1:$A$4,$A37:$B37,AE$5:AE$10,"#") -> #NAME? | AG37: =AC37-AE37 -> #NAME? | AI37: =_xll.GetCtData("CO-AMOUNT","CONS-AMOUNT",$A$1:$A$4,$A37:$B37,AI$5:AI$10,"#") -> #NAME? | AK37: =_xll.GetCtData("CO-AMOUNT","CONS-AMOUNT",$A$1:$A$4,$A37:$B37,AK$5:AK$10,"#") -> #NAME? | AM37: =AI37-AK37 -> #NAME? | AO37: =_xll.GetCtData("CO-AMOUNT","CONS-AMOUNT",$A$1:$A$4,$A37:$B37,AO$5:AO$10,"#") -> #NAME? | AQ37: =_xll.GetCtData("CO-AMOUNT","CONS-AMOUNT",$A$1:$A$4,$A37:$B37,AQ$5:AQ$10,"#") -> #NAME? | AS37: =AO37-AQ37 -> #NAME? | AU37: =W37+AC37+AI37+AO37 -> #NAME? | AW37: =Y37+AE37+AK37+AQ37 -> #NAME? | AY37: =AU37-AW37 -> #NAME? | BA37: =+Q37-AO37 -> #NAME? | BC37: =+S37-AQ37 -> #NAME? | BE37: =BA37-BC37 -> #NAME? | BG37: =_xll.GetCtData("CO-AMOUNT","CONS-AMOUNT",$A$1:$A$4,$A37:$B37,BG$5:BG$10,"#") -> #NAME? | BI37: =_xll.GetCtData("CO-AMOUNT","CONS-AMOUNT",$A$1:$A$4,$A37:$B37,BI$5:BI$10,"#") -> #NAME? | BK37: =BG37-BI37 -> #NAME? | BN37: =_xll.GetCtData("CO-AMOUNT","CONS-AMOUNT",$A$1:$A$4,$A37:$B37,BN$5:BN$10,"#") -> #NAME? | BP37: =_xll.GetCtData("CO-AMOUNT","CONS-AMOUNT",$A$1:$A$4,$A37:$B37,BP$5:BP$10,"#") -> #NAME? | BR37: =BN37-BP37 -> #NAME?
A38: {OA=OA060}+{OA=OA061}+{OA=OA060E}+{OA=OA061O} | B38: {RU=G-DE}+{RU=P-DE}+{RU=G-REIMDE}+{RU=G-REIMI} | C38: DE | D38: =CHOOSE([6]Traduction!$A$2,[6]Traduction!$A49,[6]Traduction!$B49) -> o/w Germany | E38: =_xll.GetCtData("CO-AMOUNT","CONS-AMOUNT",$A$1:$A$4,$A38:$B38,E$5:E$10,"#0") -> #NAME? | G38: =_xll.GetCtData("CO-AMOUNT","CONS-AMOUNT",$A$1:$A$4,$A38:$B38,G$5:G$10,"#") -> #NAME? | I38: =E38-G38 -> #NAME? | K38: =_xll.GetCtData("CO-AMOUNT","CONS-AMOUNT",$A$1:$A$4,$A38:$B38,K$5:K$10,"#") -> #NAME? | M38: =_xll.GetCtData("CO-AMOUNT","CONS-AMOUNT",$A$1:$A$4,$A38:$B38,M$5:M$10,"#") -> #NAME? | O38: =K38-M38 -> #NAME? | Q38: =_xll.GetCtData("CO-AMOUNT","CONS-AMOUNT",$A$1:$A$4,$A38:$B38,Q$5:Q$10,"#0") -> #NAME? | S38: =_xll.GetCtData("CO-AMOUNT","CONS-AMOUNT",$A$1:$A$4,$A38:$B38,S$5:S$10,"#") -> #NAME? | U38: =Q38-S38 -> #NAME? | W38: =_xll.GetCtData("CO-AMOUNT","CONS-AMOUNT",$A$1:$A$4,$A38:$B38,W$5:W$10,"#") -> #NAME? | Y38: =_xll.GetCtData("CO-AMOUNT","CONS-AMOUNT",$A$1:$A$4,$A38:$B38,Y$5:Y$10,"#") -> #NAME? | AA38: =W38-Y38 -> #NAME? | AC38: =_xll.GetCtData("CO-AMOUNT","CONS-AMOUNT",$A$1:$A$4,$A38:$B38,AC$5:AC$10,"#") -> #NAME? | AE38: =_xll.GetCtData("CO-AMOUNT","CONS-AMOUNT",$A$1:$A$4,$A38:$B38,AE$5:AE$10,"#") -> #NAME? | AG38: =AC38-AE38 -> #NAME? | AI38: =_xll.GetCtData("CO-AMOUNT","CONS-AMOUNT",$A$1:$A$4,$A38:$B38,AI$5:AI$10,"#") -> #NAME? | AK38: =_xll.GetCtData("CO-AMOUNT","CONS-AMOUNT",$A$1:$A$4,$A38:$B38,AK$5:AK$10,"#") -> #NAME? | AM38: =AI38-AK38 -> #NAME? | AO38: =_xll.GetCtData("CO-AMOUNT","CONS-AMOUNT",$A$1:$A$4,$A38:$B38,AO$5:AO$10,"#") -> #NAME? | AQ38: =_xll.GetCtData("CO-AMOUNT","CONS-AMOUNT",$A$1:$A$4,$A38:$B38,AQ$5:AQ$10,"#") -> #NAME? | AS38: =AO38-AQ38 -> #NAME? | AU38: =W38+AC38+AI38+AO38 -> #NAME? | AW38: =Y38+AE38+AK38+AQ38 -> #NAME? | AY38: =AU38-AW38 -> #NAME? | BA38: =+Q38-AO38 -> #NAME? | BC38: =+S38-AQ38 -> #NAME? | BE38: =BA38-BC38 -> #NAME? | BG38: =_xll.GetCtData("CO-AMOUNT","CONS-AMOUNT",$A$1:$A$4,$A38:$B38,BG$5:BG$10,"#") -> #NAME? | BI38: =_xll.GetCtData("CO-AMOUNT","CONS-AMOUNT",$A$1:$A$4,$A38:$B38,BI$5:BI$10,"#") -> #NAME? | BK38: =BG38-BI38 -> #NAME? | BN38: =_xll.GetCtData("CO-AMOUNT","CONS-AMOUNT",$A$1:$A$4,$A38:$B38,BN$5:BN$10,"#") -> #NAME? | BP38: =_xll.GetCtData("CO-AMOUNT","CONS-AMOUNT",$A$1:$A$4,$A38:$B38,BP$5:BP$10,"#") -> #NAME? | BR38: =BN38-BP38 -> #NAME?
A39: {OA=OA061} | B39: RU=G-REIMLUX | C39: ITA | D39: o/w Branch | E39: =_xll.GetCtData("CO-AMOUNT","CONS-AMOUNT",$A$1:$A$4,$A39:$B39,E$5:E$10,"#") -> #NAME? | G39: =_xll.GetCtData("CO-AMOUNT","CONS-AMOUNT",$A$1:$A$4,$A39:$B39,G$5:G$10,"#") -> #NAME? | I39: =E39-G39 -> #NAME? | K39: =_xll.GetCtData("CO-AMOUNT","CONS-AMOUNT",$A$1:$A$4,$A39:$B39,K$5:K$10,"#") -> #NAME? | M39: =_xll.GetCtData("CO-AMOUNT","CONS-AMOUNT",$A$1:$A$4,$A39:$B39,M$5:M$10,"#") -> #NAME? | O39: =K39-M39 -> #NAME? | Q39: =_xll.GetCtData("CO-AMOUNT","CONS-AMOUNT",$A$1:$A$4,$A39:$B39,Q$5:Q$10,"#") -> #NAME? | S39: =_xll.GetCtData("CO-AMOUNT","CONS-AMOUNT",$A$1:$A$4,$A39:$B39,S$5:S$10,"#") -> #NAME? | U39: =Q39-S39 -> #NAME? | W39: =_xll.GetCtData("CO-AMOUNT","CONS-AMOUNT",$A$1:$A$4,$A39:$B39,W$5:W$10,"#") -> #NAME? | Y39: =_xll.GetCtData("CO-AMOUNT","CONS-AMOUNT",$A$1:$A$4,$A39:$B39,Y$5:Y$10,"#") -> #NAME? | AA39: =W39-Y39 -> #NAME? | AC39: =_xll.GetCtData("CO-AMOUNT","CONS-AMOUNT",$A$1:$A$4,$A39:$B39,AC$5:AC$10,"#") -> #NAME? | AE39: =_xll.GetCtData("CO-AMOUNT","CONS-AMOUNT",$A$1:$A$4,$A39:$B39,AE$5:AE$10,"#") -> #NAME? | AG39: =AC39-AE39 -> #NAME? | AI39: =_xll.GetCtData("CO-AMOUNT","CONS-AMOUNT",$A$1:$A$4,$A39:$B39,AI$5:AI$10,"#") -> #NAME? | AK39: =_xll.GetCtData("CO-AMOUNT","CONS-AMOUNT",$A$1:$A$4,$A39:$B39,AK$5:AK$10,"#") -> #NAME? | AM39: =AI39-AK39 -> #NAME? | AO39: =_xll.GetCtData("CO-AMOUNT","CONS-AMOUNT",$A$1:$A$4,$A39:$B39,AO$5:AO$10,"#") -> #NAME? | AQ39: =_xll.GetCtData("CO-AMOUNT","CONS-AMOUNT",$A$1:$A$4,$A39:$B39,AQ$5:AQ$10,"#") -> #NAME? | AS39: =AO39-AQ39 -> #NAME? | AU39: =W39+AC39+AI39+AO39 -> #NAME? | AW39: =Y39+AE39+AK39+AQ39 -> #NAME? | AY39: =AU39-AW39 -> #NAME? | BA39: =+Q39-AO39 -> #NAME? | BC39: =+S39-AQ39 -> #NAME? | BE39: =BA39-BC39 -> #NAME? | BG39: =_xll.GetCtData("CO-AMOUNT","CONS-AMOUNT",$A$1:$A$4,$A39:$B39,BG$5:BG$10,"#") -> #NAME? | BI39: =_xll.GetCtData("CO-AMOUNT","CONS-AMOUNT",$A$1:$A$4,$A39:$B39,BI$5:BI$10,"#") -> #NAME? | BK39: =BG39-BI39 -> #NAME? | BN39: =_xll.GetCtData("CO-AMOUNT","CONS-AMOUNT",$A$1:$A$4,$A39:$B39,BN$5:BN$10,"#") -> #NAME? | BP39: =_xll.GetCtData("CO-AMOUNT","CONS-AMOUNT",$A$1:$A$4,$A39:$B39,BP$5:BP$10,"#") -> #NAME? | BR39: =BN39-BP39 -> #NAME?
A40: {OA=OA060}+{OA=OA060E}+{OA=OA060O} | B40: RU sum AF026 | C40: ITA | D40: o/w REIM Italy | E40: =_xll.GetCtData("CO-AMOUNT","CONS-AMOUNT",$A$1:$A$4,$A40:$B40,E$5:E$10,"#") -> #NAME? | G40: =_xll.GetCtData("CO-AMOUNT","CONS-AMOUNT",$A$1:$A$4,$A40:$B40,G$5:G$10,"#") -> #NAME? | I40: =E40-G40 -> #NAME? | K40: =_xll.GetCtData("CO-AMOUNT","CONS-AMOUNT",$A$1:$A$4,$A40:$B40,K$5:K$10,"#-2,00000000001666E-03") -> #NAME? | M40: =_xll.GetCtData("CO-AMOUNT","CONS-AMOUNT",$A$1:$A$4,$A40:$B40,M$5:M$10,"#0,12700000000001") -> #NAME? | O40: =K40-M40 -> #NAME? | Q40: =_xll.GetCtData("CO-AMOUNT","CONS-AMOUNT",$A$1:$A$4,$A40:$B40,Q$5:Q$10,"#-2,00000000001799E-03") -> #NAME? | S40: =_xll.GetCtData("CO-AMOUNT","CONS-AMOUNT",$A$1:$A$4,$A40:$B40,S$5:S$10,"#0,12700000000001") -> #NAME? | U40: =Q40-S40 -> #NAME?
C41: ITA | D41: o/w Italy | E41: =E39+E40 -> #NAME? | G41: =G39+G40 -> #NAME? | I41: =E41-G41 -> #NAME? | K41: =K39+K40 -> #NAME? | M41: =M39+M40 -> #NAME? | O41: =K41-M41 -> #NAME? | Q41: =Q39+Q40 -> #NAME? | S41: =S39+S40 -> #NAME? | U41: =Q41-S41 -> #NAME?
A42: {OA=OA060}+{OA=OA060E}+{OA=OA060O} | B42: RU=G-REIMLUX | C42: LUX | D42: =CHOOSE([6]Traduction!$A$2,[6]Traduction!$A53,[6]Traduction!$B53) -> o/w Luxembourg | E42: =_xll.GetCtData("CO-AMOUNT","CONS-AMOUNT",$A$1:$A$4,$A42:$B42,E$5:E$10,"#") -> #NAME? | G42: =_xll.GetCtData("CO-AMOUNT","CONS-AMOUNT",$A$1:$A$4,$A42:$B42,G$5:G$10,"#") -> #NAME? | I42: =E42-G42 -> #NAME? | K42: =_xll.GetCtData("CO-AMOUNT","CONS-AMOUNT",$A$1:$A$4,$A42:$B42,K$5:K$10,"#") -> #NAME? | M42: =_xll.GetCtData("CO-AMOUNT","CONS-AMOUNT",$A$1:$A$4,$A42:$B42,M$5:M$10,"#") -> #NAME? | O42: =K42-M42 -> #NAME? | Q42: =_xll.GetCtData("CO-AMOUNT","CONS-AMOUNT",$A$1:$A$4,$A42:$B42,Q$5:Q$10,"#") -> #NAME? | S42: =_xll.GetCtData("CO-AMOUNT","CONS-AMOUNT",$A$1:$A$4,$A42:$B42,S$5:S$10,"#") -> #NAME? | U42: =Q42-S42 -> #NAME? | W42: =_xll.GetCtData("CO-AMOUNT","CONS-AMOUNT",$A$1:$A$4,$A42:$B42,W$5:W$10,"#") -> #NAME? | Y42: =_xll.GetCtData("CO-AMOUNT","CONS-AMOUNT",$A$1:$A$4,$A42:$B42,Y$5:Y$10,"#") -> #NAME? | AA42: =W42-Y42 -> #NAME? | AC42: =_xll.GetCtData("CO-AMOUNT","CONS-AMOUNT",$A$1:$A$4,$A42:$B42,AC$5:AC$10,"#") -> #NAME? | AE42: =_xll.GetCtData("CO-AMOUNT","CONS-AMOUNT",$A$1:$A$4,$A42:$B42,AE$5:AE$10,"#") -> #NAME? | AG42: =AC42-AE42 -> #NAME? | AI42: =_xll.GetCtData("CO-AMOUNT","CONS-AMOUNT",$A$1:$A$4,$A42:$B42,AI$5:AI$10,"#") -> #NAME? | AK42: =_xll.GetCtData("CO-AMOUNT","CONS-AMOUNT",$A$1:$A$4,$A42:$B42,AK$5:AK$10,"#") -> #NAME? | AM42: =AI42-AK42 -> #NAME? | AO42: =_xll.GetCtData("CO-AMOUNT","CONS-AMOUNT",$A$1:$A$4,$A42:$B42,AO$5:AO$10,"#") -> #NAME? | AQ42: =_xll.GetCtData("CO-AMOUNT","CONS-AMOUNT",$A$1:$A$4,$A42:$B42,AQ$5:AQ$10,"#") -> #NAME? | AS42: =AO42-AQ42 -> #NAME? | AU42: =W42+AC42+AI42+AO42 -> #NAME? | AW42: =Y42+AE42+AK42+AQ42 -> #NAME? | AY42: =AU42-AW42 -> #NAME? | BA42: =+Q42-AO42 -> #NAME? | BC42: =+S42-AQ42 -> #NAME? | BE42: =BA42-BC42 -> #NAME? | BG42: =_xll.GetCtData("CO-AMOUNT","CONS-AMOUNT",$A$1:$A$4,$A42:$B42,BG$5:BG$10,"#") -> #NAME? | BI42: =_xll.GetCtData("CO-AMOUNT","CONS-AMOUNT",$A$1:$A$4,$A42:$B42,BI$5:BI$10,"#") -> #NAME? | BK42: =BG42-BI42 -> #NAME? | BN42: =_xll.GetCtData("CO-AMOUNT","CONS-AMOUNT",$A$1:$A$4,$A42:$B42,BN$5:BN$10,"#") -> #NAME? | BP42: =_xll.GetCtData("CO-AMOUNT","CONS-AMOUNT",$A$1:$A$4,$A42:$B42,BP$5:BP$10,"#") -> #NAME? | BR42: =BN42-BP42 -> #NAME?
A43: {OA=OA060}+{OA=OA061}+{OA=OA060E}+{OA=OA060O} | B43: {RU=G-UK}+{RU=P-UK}+{RU=G-REIMI} | C43: UK | D43: =CHOOSE([6]Traduction!$A$2,[6]Traduction!$A52,[6]Traduction!$B52) -> o/w UK | E43: =_xll.GetCtData("CO-AMOUNT","CONS-AMOUNT",$A$1:$A$4,$A43:$B43,E$5:E$10,"#0") -> #NAME? | G43: =_xll.GetCtData("CO-AMOUNT","CONS-AMOUNT",$A$1:$A$4,$A43:$B43,G$5:G$10,"#") -> #NAME? | I43: =E43-G43 -> #NAME? | K43: =_xll.GetCtData("CO-AMOUNT","CONS-AMOUNT",$A$1:$A$4,$A43:$B43,K$5:K$10,"#") -> #NAME? | M43: =_xll.GetCtData("CO-AMOUNT","CONS-AMOUNT",$A$1:$A$4,$A43:$B43,M$5:M$10,"#") -> #NAME? | O43: =K43-M43 -> #NAME? | Q43: =_xll.GetCtData("CO-AMOUNT","CONS-AMOUNT",$A$1:$A$4,$A43:$B43,Q$5:Q$10,"#0") -> #NAME? | S43: =_xll.GetCtData("CO-AMOUNT","CONS-AMOUNT",$A$1:$A$4,$A43:$B43,S$5:S$10,"#") -> #NAME? | U43: =Q43-S43 -> #NAME? | W43: =_xll.GetCtData("CO-AMOUNT","CONS-AMOUNT",$A$1:$A$4,$A43:$B43,W$5:W$10,"#") -> #NAME? | Y43: =_xll.GetCtData("CO-AMOUNT","CONS-AMOUNT",$A$1:$A$4,$A43:$B43,Y$5:Y$10,"#") -> #NAME? | AA43: =W43-Y43 -> #NAME? | AC43: =_xll.GetCtData("CO-AMOUNT","CONS-AMOUNT",$A$1:$A$4,$A43:$B43,AC$5:AC$10,"#") -> #NAME? | AE43: =_xll.GetCtData("CO-AMOUNT","CONS-AMOUNT",$A$1:$A$4,$A43:$B43,AE$5:AE$10,"#") -> #NAME? | AG43: =AC43-AE43 -> #NAME? | AI43: =_xll.GetCtData("CO-AMOUNT","CONS-AMOUNT",$A$1:$A$4,$A43:$B43,AI$5:AI$10,"#") -> #NAME? | AK43: =_xll.GetCtData("CO-AMOUNT","CONS-AMOUNT",$A$1:$A$4,$A43:$B43,AK$5:AK$10,"#") -> #NAME? | AM43: =AI43-AK43 -> #NAME? | AO43: =_xll.GetCtData("CO-AMOUNT","CONS-AMOUNT",$A$1:$A$4,$A43:$B43,AO$5:AO$10,"#") -> #NAME? | AQ43: =_xll.GetCtData("CO-AMOUNT","CONS-AMOUNT",$A$1:$A$4,$A43:$B43,AQ$5:AQ$10,"#") -> #NAME? | AS43: =AO43-AQ43 -> #NAME? | AU43: =W43+AC43+AI43+AO43 -> #NAME? | AW43: =Y43+AE43+AK43+AQ43 -> #NAME? | AY43: =AU43-AW43 -> #NAME? | BA43: =+Q43-AO43 -> #NAME? | BC43: =+S43-AQ43 -> #NAME? | BE43: =BA43-BC43 -> #NAME? | BG43: =_xll.GetCtData("CO-AMOUNT","CONS-AMOUNT",$A$1:$A$4,$A43:$B43,BG$5:BG$10,"#") -> #NAME? | BI43: =_xll.GetCtData("CO-AMOUNT","CONS-AMOUNT",$A$1:$A$4,$A43:$B43,BI$5:BI$10,"#") -> #NAME? | BK43: =BG43-BI43 -> #NAME? | BN43: =_xll.GetCtData("CO-AMOUNT","CONS-AMOUNT",$A$1:$A$4,$A43:$B43,BN$5:BN$10,"#") -> #NAME? | BP43: =_xll.GetCtData("CO-AMOUNT","CONS-AMOUNT",$A$1:$A$4,$A43:$B43,BP$5:BP$10,"#") -> #NAME? | BR43: =BN43-BP43 -> #NAME?
A44: {OA=OA060}+{OA=OA061}+{OA=OA060E}+{OA=OA060O} | B44: {RU=G-UK}+{RU=P-UK} | C44: UK GBP | D44: UK (GBP) | E44: =_xll.GetCtData("CO-AMOUNT","AMOUNT",$A$1:$A$4,$A44:$B44,E$5:E$10,"#") -> #NAME? | G44: =_xll.GetCtData("CO-AMOUNT","AMOUNT",$A$1:$A$4,$A44:$B44,G$5:G$10,"#") -> #NAME? | I44: =E44-G44 -> #NAME? | K44: =_xll.GetCtData("CO-AMOUNT","AMOUNT",$A$1:$A$4,$A44:$B44,K$5:K$10,"#") -> #NAME? | M44: =_xll.GetCtData("CO-AMOUNT","AMOUNT",$A$1:$A$4,$A44:$B44,M$5:M$10,"#") -> #NAME? | O44: =K44-M44 -> #NAME? | Q44: =_xll.GetCtData("CO-AMOUNT","AMOUNT",$A$1:$A$4,$A44:$B44,Q$5:Q$10,"#") -> #NAME? | S44: =_xll.GetCtData("CO-AMOUNT","AMOUNT",$A$1:$A$4,$A44:$B44,S$5:S$10,"#") -> #NAME? | U44: =Q44-S44 -> #NAME? | W44: =_xll.GetCtData("CO-AMOUNT","AMOUNT",$A$1:$A$4,$A44:$B44,W$5:W$10,"#") -> #NAME? | Y44: =_xll.GetCtData("CO-AMOUNT","AMOUNT",$A$1:$A$4,$A44:$B44,Y$5:Y$10,"#") -> #NAME? | AA44: =W44-Y44 -> #NAME? | AC44: =_xll.GetCtData("CO-AMOUNT","AMOUNT",$A$1:$A$4,$A44:$B44,AC$5:AC$10,"#") -> #NAME? | AE44: =_xll.GetCtData("CO-AMOUNT","AMOUNT",$A$1:$A$4,$A44:$B44,AE$5:AE$10,"#") -> #NAME? | AG44: =AC44-AE44 -> #NAME? | AI44: =_xll.GetCtData("CO-AMOUNT","AMOUNT",$A$1:$A$4,$A44:$B44,AI$5:AI$10,"#") -> #NAME? | AK44: =_xll.GetCtData("CO-AMOUNT","AMOUNT",$A$1:$A$4,$A44:$B44,AK$5:AK$10,"#") -> #NAME? | AM44: =AI44-AK44 -> #NAME? | AO44: =_xll.GetCtData("CO-AMOUNT","AMOUNT",$A$1:$A$4,$A44:$B44,AO$5:AO$10,"#") -> #NAME? | AQ44: =_xll.GetCtData("CO-AMOUNT","AMOUNT",$A$1:$A$4,$A44:$B44,AQ$5:AQ$10,"#") -> #NAME? | AS44: =AO44-AQ44 -> #NAME? | AU44: =W44+AC44+AI44+AO44 -> #NAME? | AW44: =Y44+AE44+AK44+AQ44 -> #NAME? | AY44: =AU44-AW44 -> #NAME? | BA44: =+Q44-AO44 -> #NAME? | BC44: =+S44-AQ44 -> #NAME? | BE44: =BA44-BC44 -> #NAME? | BG44: =_xll.GetCtData("CO-AMOUNT","AMOUNT",$A$1:$A$4,$A44:$B44,BG$5:BG$10,"#") -> #NAME? | BI44: =_xll.GetCtData("CO-AMOUNT","AMOUNT",$A$1:$A$4,$A44:$B44,BI$5:BI$10,"#") -> #NAME? | BK44: =BG44-BI44 -> #NAME? | BN44: =_xll.GetCtData("CO-AMOUNT","AMOUNT",$A$1:$A$4,$A44:$B44,BN$5:BN$10,"#") -> #NAME? | BP44: =_xll.GetCtData("CO-AMOUNT","AMOUNT",$A$1:$A$4,$A44:$B44,BP$5:BP$10,"#") -> #NAME? | BR44: =BN44-BP44 -> #NAME?
A45: {OA=OA060}+{OA=OA060E}+{OA=OA060O} | B45: {RU=G-BE}+{RU=P-BE} | C45: BEL | D45: =CHOOSE([6]Traduction!$A$2,[6]Traduction!$A66,[6]Traduction!$B66) -> o/w Belgium | E45: =_xll.GetCtData("CO-AMOUNT","CONS-AMOUNT",$A$1:$A$4,$A45:$B45,E$5:E$10,"#") -> #NAME? | G45: =_xll.GetCtData("CO-AMOUNT","CONS-AMOUNT",$A$1:$A$4,$A45:$B45,G$5:G$10,"#") -> #NAME? | I45: =E45-G45 -> #NAME? | K45: =_xll.GetCtData("CO-AMOUNT","CONS-AMOUNT",$A$1:$A$4,$A45:$B45,K$5:K$10,"#") -> #NAME? | M45: =_xll.GetCtData("CO-AMOUNT","CONS-AMOUNT",$A$1:$A$4,$A45:$B45,M$5:M$10,"#") -> #NAME? | O45: =K45-M45 -> #NAME? | Q45: =_xll.GetCtData("CO-AMOUNT","CONS-AMOUNT",$A$1:$A$4,$A45:$B45,Q$5:Q$10,"#") -> #NAME? | S45: =_xll.GetCtData("CO-AMOUNT","CONS-AMOUNT",$A$1:$A$4,$A45:$B45,S$5:S$10,"#") -> #NAME? | U45: =Q45-S45 -> #NAME? | W45: =_xll.GetCtData("CO-AMOUNT","CONS-AMOUNT",$A$1:$A$4,$A45:$B45,W$5:W$10,"#") -> #NAME? | Y45: =_xll.GetCtData("CO-AMOUNT","CONS-AMOUNT",$A$1:$A$4,$A45:$B45,Y$5:Y$10,"#") -> #NAME? | AA45: =W45-Y45 -> #NAME? | AC45: =_xll.GetCtData("CO-AMOUNT","CONS-AMOUNT",$A$1:$A$4,$A45:$B45,AC$5:AC$10,"#") -> #NAME? | AE45: =_xll.GetCtData("CO-AMOUNT","CONS-AMOUNT",$A$1:$A$4,$A45:$B45,AE$5:AE$10,"#") -> #NAME? | AG45: =AC45-AE45 -> #NAME? | AI45: =_xll.GetCtData("CO-AMOUNT","CONS-AMOUNT",$A$1:$A$4,$A45:$B45,AI$5:AI$10,"#") -> #NAME? | AK45: =_xll.GetCtData("CO-AMOUNT","CONS-AMOUNT",$A$1:$A$4,$A45:$B45,AK$5:AK$10,"#") -> #NAME? | AM45: =AI45-AK45 -> #NAME? | AO45: =_xll.GetCtData("CO-AMOUNT","CONS-AMOUNT",$A$1:$A$4,$A45:$B45,AO$5:AO$10,"#") -> #NAME? | AQ45: =_xll.GetCtData("CO-AMOUNT","CONS-AMOUNT",$A$1:$A$4,$A45:$B45,AQ$5:AQ$10,"#") -> #NAME? | AS45: =AO45-AQ45 -> #NAME? | AU45: =W45+AC45+AI45+AO45 -> #NAME? | AW45: =Y45+AE45+AK45+AQ45 -> #NAME? | AY45: =AU45-AW45 -> #NAME? | BA45: =+Q45-AO45 -> #NAME? | BC45: =+S45-AQ45 -> #NAME? | BE45: =BA45-BC45 -> #NAME? | BG45: =_xll.GetCtData("CO-AMOUNT","CONS-AMOUNT",$A$1:$A$4,$A45:$B45,BG$5:BG$10,"#") -> #NAME? | BI45: =_xll.GetCtData("CO-AMOUNT","CONS-AMOUNT",$A$1:$A$4,$A45:$B45,BI$5:BI$10,"#") -> #NAME? | BK45: =BG45-BI45 -> #NAME? | BN45: =_xll.GetCtData("CO-AMOUNT","CONS-AMOUNT",$A$1:$A$4,$A45:$B45,BN$5:BN$10,"#") -> #NAME? | BP45: =_xll.GetCtData("CO-AMOUNT","CONS-AMOUNT",$A$1:$A$4,$A45:$B45,BP$5:BP$10,"#") -> #NAME? | BR45: =BN45-BP45 -> #NAME?
A46: {OA=OA060}+{OA=OA060E}+{OA=OA060O} | B46: {RU=G-REIMSP}+{RU=G-SP} | C46: ESP | D46: =CHOOSE([6]Traduction!$A$2,[6]Traduction!$A48,[6]Traduction!$B48) -> o/w Spain | E46: =_xll.GetCtData("CO-AMOUNT","CONS-AMOUNT",$A$1:$A$4,$A46:$B46,E$5:E$10,"#") -> #NAME? | G46: =_xll.GetCtData("CO-AMOUNT","CONS-AMOUNT",$A$1:$A$4,$A46:$B46,G$5:G$10,"#") -> #NAME? | I46: =E46-G46 -> #NAME? | K46: =_xll.GetCtData("CO-AMOUNT","CONS-AMOUNT",$A$1:$A$4,$A46:$B46,K$5:K$10,"#") -> #NAME? | M46: =_xll.GetCtData("CO-AMOUNT","CONS-AMOUNT",$A$1:$A$4,$A46:$B46,M$5:M$10,"#") -> #NAME? | O46: =K46-M46 -> #NAME? | Q46: =_xll.GetCtData("CO-AMOUNT","CONS-AMOUNT",$A$1:$A$4,$A46:$B46,Q$5:Q$10,"#") -> #NAME? | S46: =_xll.GetCtData("CO-AMOUNT","CONS-AMOUNT",$A$1:$A$4,$A46:$B46,S$5:S$10,"#") -> #NAME? | U46: =Q46-S46 -> #NAME? | W46: =_xll.GetCtData("CO-AMOUNT","CONS-AMOUNT",$A$1:$A$4,$A46:$B46,W$5:W$10,"#") -> #NAME? | Y46: =_xll.GetCtData("CO-AMOUNT","CONS-AMOUNT",$A$1:$A$4,$A46:$B46,Y$5:Y$10,"#") -> #NAME? | AA46: =W46-Y46 -> #NAME? | AC46: =_xll.GetCtData("CO-AMOUNT","CONS-AMOUNT",$A$1:$A$4,$A46:$B46,AC$5:AC$10,"#") -> #NAME? | AE46: =_xll.GetCtData("CO-AMOUNT","CONS-AMOUNT",$A$1:$A$4,$A46:$B46,AE$5:AE$10,"#") -> #NAME? | AG46: =AC46-AE46 -> #NAME? | AI46: =_xll.GetCtData("CO-AMOUNT","CONS-AMOUNT",$A$1:$A$4,$A46:$B46,AI$5:AI$10,"#") -> #NAME? | AK46: =_xll.GetCtData("CO-AMOUNT","CONS-AMOUNT",$A$1:$A$4,$A46:$B46,AK$5:AK$10,"#") -> #NAME? | AM46: =AI46-AK46 -> #NAME? | AO46: =_xll.GetCtData("CO-AMOUNT","CONS-AMOUNT",$A$1:$A$4,$A46:$B46,AO$5:AO$10,"#") -> #NAME? | AQ46: =_xll.GetCtData("CO-AMOUNT","CONS-AMOUNT",$A$1:$A$4,$A46:$B46,AQ$5:AQ$10,"#") -> #NAME? | AS46: =AO46-AQ46 -> #NAME? | AU46: =W46+AC46+AI46+AO46 -> #NAME? | AW46: =Y46+AE46+AK46+AQ46 -> #NAME? | AY46: =AU46-AW46 -> #NAME? | BA46: =+Q46-AO46 -> #NAME? | BC46: =+S46-AQ46 -> #NAME? | BE46: =BA46-BC46 -> #NAME? | BG46: =_xll.GetCtData("CO-AMOUNT","CONS-AMOUNT",$A$1:$A$4,$A46:$B46,BG$5:BG$10,"#") -> #NAME? | BI46: =_xll.GetCtData("CO-AMOUNT","CONS-AMOUNT",$A$1:$A$4,$A46:$B46,BI$5:BI$10,"#") -> #NAME? | BK46: =BG46-BI46 -> #NAME? | BN46: =_xll.GetCtData("CO-AMOUNT","CONS-AMOUNT",$A$1:$A$4,$A46:$B46,BN$5:BN$10,"#") -> #NAME? | BP46: =_xll.GetCtData("CO-AMOUNT","CONS-AMOUNT",$A$1:$A$4,$A46:$B46,BP$5:BP$10,"#") -> #NAME? | BR46: =BN46-BP46 -> #NAME?
D47: Advisory | E47: =SUM(E48:E68)-E50-E56-E59-E57-E52-E53-E54-E51 -> #NAME? | G47: =SUM(G48:G68)-G50-G56-G59-G57-G52-G53-G54-G51 -> #NAME? | H47: =SUM(H48:H67)-H50-H56 -> 0 | I47: =E47-G47 -> #NAME? | K47: =SUM(K48:K68)-K50-K56-K59-K57-K52-K53-K54-K51 -> #NAME? | M47: =SUM(M48:M68)-M50-M56-M59-M57-M52-M53-M54-M51 -> #NAME? | N47: =SUM(N48:N67)-N50-N56 -> 0 | O47: =K47-M47 -> #NAME? | Q47: =SUM(Q48:Q68)-Q50-Q56-Q59-Q57-Q52-Q53-Q54-Q51 -> #NAME? | S47: =SUM(S48:S68)-S50-S56-S59-S57-S52-S53-S54-S51 -> #NAME? | T47: =SUM(T48:T67)-T50-T56 -> 0 | U47: =Q47-S47 -> #NAME? | W47: =SUM(W48:W68)-W50-W56-W59-W57 -> #NAME? | Y47: =SUM(Y48:Y68)-Y50-Y56-Y59-Y57 -> #NAME? | Z47: =SUM(Z48:Z67)-Z50-Z56 -> 0 | AA47: =SUM(AA48:AA68)-AA50-AA56-AA59-AA57 -> #NAME? | AC47: =SUM(AC48:AC68)-AC50-AC56-AC59-AC57 -> #NAME? | AE47: =SUM(AE48:AE68)-AE50-AE56-AE59-AE57 -> #NAME? | AF47: =SUM(AF48:AF67)-AF50-AF56 -> 0 | AG47: =SUM(AG48:AG68)-AG50-AG56-AG59-AG57 -> #NAME? | AI47: =SUM(AI48:AI68)-AI50-AI56-AI59-AI57 -> #NAME? | AK47: =SUM(AK48:AK68)-AK50-AK56-AK59-AK57 -> #NAME? | AL47: =SUM(AL48:AL67)-AL50-AL56 -> 0 | AM47: =SUM(AM48:AM68)-AM50-AM56-AM59-AM57 -> #NAME? | AO47: =SUM(AO48:AO68)-AO50-AO56-AO59-AO57 -> #NAME? | AQ47: =SUM(AQ48:AQ68)-AQ50-AQ56-AQ59-AQ57 -> #NAME? | AR47: =SUM(AR48:AR67)-AR50-AR56 -> 0 | AS47: =SUM(AS48:AS68)-AS50-AS56-AS59-AS57 -> #NAME? | AU47: =W47+AC47+AI47+AO47 -> #NAME? | AW47: =Y47+AE47+AK47+AQ47 -> #NAME? | AX47: =SUM(AX48:AX67)-AX50-AX56 -> 0 | AY47: =AA47+AG47+AM47+AS47 -> #NAME? | BA47: =SUM(BA48:BA68)-BA50-BA56-BA59-BA57 -> #NAME? | BC47: =SUM(BC48:BC68)-BC50-BC56-BC59-BC57 -> #NAME? | BD47: =SUM(BD48:BD67)-BD50-BD56 -> 0 | BE47: =SUM(BE48:BE68)-BE50-BE56-BE59-BE57 -> #NAME? | BG47: =SUM(BG48:BG68)-BG50-BG56-BG59-BG57 -> #NAME? | BI47: =SUM(BI48:BI68)-BI50-BI56-BI59-BI57 -> #NAME? | BJ47: =SUM(BJ48:BJ67)-BJ50-BJ56 -> 0 | BK47: =SUM(BK48:BK68)-BK50-BK56-BK59-BK57 -> #NAME? | BN47: =SUM(BN48:BN68)-BN50-BN56-BN59-BN57 -> #NAME? | BP47: =SUM(BP48:BP68)-BP50-BP56-BP59-BP57 -> #NAME? | BQ47: =SUM(BQ48:BQ67)-BQ50-BQ56 -> 0 | BR47: =SUM(BR48:BR68)-BR50-BR56-BR59-BR57 -> #NAME?
A48: OA sum AR0121 | B48: {RU=G-CENTRAL}+{RU=P-CENTRAL} | C48: CENTRAL | D48: G-central | E48: =_xll.GetCtData("CO-AMOUNT","CONS-AMOUNT",$A$1:$A$4,$A48:$B48,E$5:E$10,"#") -> #NAME? | G48: =_xll.GetCtData("CO-AMOUNT","CONS-AMOUNT",$A$1:$A$4,$A48:$B48,G$5:G$10,"#930") -> #NAME? | I48: =E48-G48 -> #NAME? | K48: =_xll.GetCtData("CO-AMOUNT","CONS-AMOUNT",$A$1:$A$4,$A48:$B48,K$5:K$10,"#") -> #NAME? | M48: =_xll.GetCtData("CO-AMOUNT","CONS-AMOUNT",$A$1:$A$4,$A48:$B48,M$5:M$10,"#-684,5") -> #NAME? | O48: =K48-M48 -> #NAME? | Q48: =_xll.GetCtData("CO-AMOUNT","CONS-AMOUNT",$A$1:$A$4,$A48:$B48,Q$5:Q$10,"#") -> #NAME? | S48: =_xll.GetCtData("CO-AMOUNT","CONS-AMOUNT",$A$1:$A$4,$A48:$B48,S$5:S$10,"#245,5") -> #NAME? | U48: =Q48-S48 -> #NAME? | W48: =_xll.GetCtData("CO-AMOUNT","CONS-AMOUNT",$A$1:$A$4,$A48:$B48,W$5:W$10,"#") -> #NAME? | Y48: =_xll.GetCtData("CO-AMOUNT","CONS-AMOUNT",$A$1:$A$4,$A48:$B48,Y$5:Y$10,"#") -> #NAME? | AA48: =W48-Y48 -> #NAME? | AC48: =_xll.GetCtData("CO-AMOUNT","CONS-AMOUNT",$A$1:$A$4,$A48:$B48,AC$5:AC$10,"#") -> #NAME? | AE48: =_xll.GetCtData("CO-AMOUNT","CONS-AMOUNT",$A$1:$A$4,$A48:$B48,AE$5:AE$10,"#") -> #NAME? | AG48: =AC48-AE48 -> #NAME? | AI48: =_xll.GetCtData("CO-AMOUNT","CONS-AMOUNT",$A$1:$A$4,$A48:$B48,AI$5:AI$10,"#") -> #NAME? | AK48: =_xll.GetCtData("CO-AMOUNT","CONS-AMOUNT",$A$1:$A$4,$A48:$B48,AK$5:AK$10,"#") -> #NAME? | AM48: =AI48-AK48 -> #NAME? | AO48: =_xll.GetCtData("CO-AMOUNT","CONS-AMOUNT",$A$1:$A$4,$A48:$B48,AO$5:AO$10,"#") -> #NAME? | AQ48: =_xll.GetCtData("CO-AMOUNT","CONS-AMOUNT",$A$1:$A$4,$A48:$B48,AQ$5:AQ$10,"#") -> #NAME? | AS48: =AO48-AQ48 -> #NAME? | AU48: =W48+AC48+AI48+AO48 -> #NAME? | AW48: =Y48+AE48+AK48+AQ48 -> #NAME? | AY48: =AU48-AW48 -> #NAME? | BA48: =+Q48-AO48 -> #NAME? | BC48: =+S48-AQ48 -> #NAME? | BE48: =BA48-BC48 -> #NAME? | BG48: =_xll.GetCtData("CO-AMOUNT","CONS-AMOUNT",$A$1:$A$4,$A48:$B48,BG$5:BG$10,"#") -> #NAME? | BI48: =_xll.GetCtData("CO-AMOUNT","CONS-AMOUNT",$A$1:$A$4,$A48:$B48,BI$5:BI$10,"#") -> #NAME? | BK48: =BG48-BI48 -> #NAME? | BN48: =_xll.GetCtData("CO-AMOUNT","CONS-AMOUNT",$A$1:$A$4,$A48:$B48,BN$5:BN$10,"#") -> #NAME? | BP48: =_xll.GetCtData("CO-AMOUNT","CONS-AMOUNT",$A$1:$A$4,$A48:$B48,BP$5:BP$10,"#") -> #NAME? | BR48: =BN48-BP48 -> #NAME?
A49: {OA=OA005O}+{OA=OA006}+{OA=OA010}+{OA=OA011}+{OA=OA017}+{OA=OA021}+{OA=OA021O}+{OA=OA023}+{OA=OA024} | B49: {RU=G-UK}+{RU=P-UK}+{RU=G-UKSP} | C49: UK | D49: =CHOOSE([6]Traduction!$A$2,[6]Traduction!$A52,[6]Traduction!$B52) -> o/w UK | E49: =_xll.GetCtData("CO-AMOUNT","CONS-AMOUNT",$A$1:$A$4,$A49:$B49,E$5:E$10,"#15362,7978810813") -> #NAME? | G49: =_xll.GetCtData("CO-AMOUNT","CONS-AMOUNT",$A$1:$A$4,$A49:$B49,G$5:G$10,"#17116,1254407467") -> #NAME? | I49: =E49-G49 -> #NAME? | K49: =_xll.GetCtData("CO-AMOUNT","CONS-AMOUNT",$A$1:$A$4,$A49:$B49,K$5:K$10,"#-26205,8728447977") -> #NAME? | M49: =_xll.GetCtData("CO-AMOUNT","CONS-AMOUNT",$A$1:$A$4,$A49:$B49,M$5:M$10,"#-27176,4175561483") -> #NAME? | O49: =K49-M49 -> #NAME? | Q49: =_xll.GetCtData("CO-AMOUNT","CONS-AMOUNT",$A$1:$A$4,$A49:$B49,Q$5:Q$10,"#-10931,3126842733") -> #NAME? | S49: =_xll.GetCtData("CO-AMOUNT","CONS-AMOUNT",$A$1:$A$4,$A49:$B49,S$5:S$10,"#-9989,20385546763") -> #NAME? | U49: =Q49-S49 -> #NAME? | W49: =_xll.GetCtData("CO-AMOUNT","CONS-AMOUNT",$A$1:$A$4,$A49:$B49,W$5:W$10,"#-144,995614786716") -> #NAME? | Y49: =_xll.GetCtData("CO-AMOUNT","CONS-AMOUNT",$A$1:$A$4,$A49:$B49,Y$5:Y$10,"#-142,109623040263") -> #NAME? | AA49: =W49-Y49 -> #NAME? | AC49: =_xll.GetCtData("CO-AMOUNT","CONS-AMOUNT",$A$1:$A$4,$A49:$B49,AC$5:AC$10,"#") -> #NAME? | AE49: =_xll.GetCtData("CO-AMOUNT","CONS-AMOUNT",$A$1:$A$4,$A49:$B49,AE$5:AE$10,"#") -> #NAME? | AG49: =AC49-AE49 -> #NAME? | AI49: =_xll.GetCtData("CO-AMOUNT","CONS-AMOUNT",$A$1:$A$4,$A49:$B49,AI$5:AI$10,"#205,815459241732") -> #NAME? | AK49: =_xll.GetCtData("CO-AMOUNT","CONS-AMOUNT",$A$1:$A$4,$A49:$B49,AK$5:AK$10,"#210,528930229196") -> #NAME? | AM49: =AI49-AK49 -> #NAME? | AO49: =_xll.GetCtData("CO-AMOUNT","CONS-AMOUNT",$A$1:$A$4,$A49:$B49,AO$5:AO$10,"#-1288,53767790285") -> #NAME? | AQ49: =_xll.GetCtData("CO-AMOUNT","CONS-AMOUNT",$A$1:$A$4,$A49:$B49,AQ$5:AQ$10,"#-1442,89767585923") -> #NAME? | AS49: =AO49-AQ49 -> #NAME? | AU49: =W49+AC49+AI49+AO49 -> #NAME? | AW49: =Y49+AE49+AK49+AQ49 -> #NAME? | AY49: =AU49-AW49 -> #NAME? | BA49: =+Q49-AO49 -> #NAME? | BC49: =+S49-AQ49 -> #NAME? | BE49: =BA49-BC49 -> #NAME? | BG49: =_xll.GetCtData("CO-AMOUNT","CONS-AMOUNT",$A$1:$A$4,$A49:$B49,BG$5:BG$10,"#-904,489324742201") -> #NAME? | BI49: =_xll.GetCtData("CO-AMOUNT","CONS-AMOUNT",$A$1:$A$4,$A49:$B49,BI$5:BI$10,"#-1061,75415364393") -> #NAME? | BK49: =BG49-BI49 -> #NAME? | BN49: =_xll.GetCtData("CO-AMOUNT","CONS-AMOUNT",$A$1:$A$4,$A49:$B49,BN$5:BN$10,"#-384,048353160652") -> #NAME? | BP49: =_xll.GetCtData("CO-AMOUNT","CONS-AMOUNT",$A$1:$A$4,$A49:$B49,BP$5:BP$10,"#-381,1435222153") -> #NAME? | BR49: =BN49-BP49 -> #NAME?
A50: {OA=OA005O}+{OA=OA017}+{OA=OA021O}+{OA=OA024} | B50: {RU=G-UK}+{RU=P-UK}+{RU=G-UKSP}+{RU=G-UKPROMO} | C50: UK S&P | D50: o/w UK S&P | E50: =_xll.GetCtData("CO-AMOUNT","CONS-AMOUNT",$A$1:$A$4,$A50:$B50,E$5:E$10,"#11653,6879775125") -> #NAME? | G50: =_xll.GetCtData("CO-AMOUNT","CONS-AMOUNT",$A$1:$A$4,$A50:$B50,G$5:G$10,"#12886,0429507184") -> #NAME? | I50: =E50-G50 -> #NAME? | K50: =_xll.GetCtData("CO-AMOUNT","CONS-AMOUNT",$A$1:$A$4,$A50:$B50,K$5:K$10,"#-19815,2999561597") -> #NAME? | M50: =_xll.GetCtData("CO-AMOUNT","CONS-AMOUNT",$A$1:$A$4,$A50:$B50,M$5:M$10,"#-20487,1638522789") -> #NAME? | O50: =K50-M50 -> #NAME? | Q50: =_xll.GetCtData("CO-AMOUNT","CONS-AMOUNT",$A$1:$A$4,$A50:$B50,Q$5:Q$10,"#-8374,20503275011") -> #NAME? | S50: =_xll.GetCtData("CO-AMOUNT","CONS-AMOUNT",$A$1:$A$4,$A50:$B50,S$5:S$10,"#-7811,99238968309") -> #NAME? | U50: =Q50-S50 -> #NAME? | W50: =_xll.GetCtData("CO-AMOUNT","AMOUNT",$A$1:$A$4,$A50:$B50,W$5:W$10,"#") -> #NAME? | Y50: =_xll.GetCtData("CO-AMOUNT","AMOUNT",$A$1:$A$4,$A50:$B50,Y$5:Y$10,"#") -> #NAME? | AA50: =W50-Y50 -> #NAME? | AC50: =_xll.GetCtData("CO-AMOUNT","AMOUNT",$A$1:$A$4,$A50:$B50,AC$5:AC$10,"#") -> #NAME? | AE50: =_xll.GetCtData("CO-AMOUNT","AMOUNT",$A$1:$A$4,$A50:$B50,AE$5:AE$10,"#") -> #NAME? | AG50: =AC50-AE50 -> #NAME? | AI50: =_xll.GetCtData("CO-AMOUNT","AMOUNT",$A$1:$A$4,$A50:$B50,AI$5:AI$10,"#") -> #NAME? | AK50: =_xll.GetCtData("CO-AMOUNT","AMOUNT",$A$1:$A$4,$A50:$B50,AK$5:AK$10,"#") -> #NAME? | AM50: =AI50-AK50 -> #NAME? | AO50: =_xll.GetCtData("CO-AMOUNT","AMOUNT",$A$1:$A$4,$A50:$B50,AO$5:AO$10,"#-833,88") -> #NAME? | AQ50: =_xll.GetCtData("CO-AMOUNT","AMOUNT",$A$1:$A$4,$A50:$B50,AQ$5:AQ$10,"#-934,629") -> #NAME? | AS50: =AO50-AQ50 -> #NAME? | AU50: =W50+AC50+AI50+AO50 -> #NAME? | AW50: =Y50+AE50+AK50+AQ50 -> #NAME? | AY50: =AU50-AW50 -> #NAME? | BA50: =+Q50-AO50 -> #NAME? | BC50: =+S50-AQ50 -> #NAME? | BE50: =BA50-BC50 -> #NAME? | BG50: =_xll.GetCtData("CO-AMOUNT","AMOUNT",$A$1:$A$4,$A50:$B50,BG$5:BG$10,"#-585,35") -> #NAME? | BI50: =_xll.GetCtData("CO-AMOUNT","AMOUNT",$A$1:$A$4,$A50:$B50,BI$5:BI$10,"#-687,755") -> #NAME? | BK50: =BG50-BI50 -> #NAME? | BN50: =_xll.GetCtData("CO-AMOUNT","AMOUNT",$A$1:$A$4,$A50:$B50,BN$5:BN$10,"#-248,53") -> #NAME? | BP50: =_xll.GetCtData("CO-AMOUNT","AMOUNT",$A$1:$A$4,$A50:$B50,BP$5:BP$10,"#-246,874") -> #NAME? | BR50: =BN50-BP50 -> #NAME?
A51: {OA=OA006}+{OA=OA010}+{OA=OA011}+{OA=OA021}+{OA=OA023} | B51: {RU=G-UK}+{RU=P-UK}+{RU=G-UKSP}+{RU=G-UKPROMO} | C51: UK | D51: o/w UK Commercial | E51: =_xll.GetCtData("CO-AMOUNT","CONS-AMOUNT",$A$1:$A$4,$A51:$B51,E$5:E$10,"#3709,10990356879") -> #NAME? | G51: =_xll.GetCtData("CO-AMOUNT","CONS-AMOUNT",$A$1:$A$4,$A51:$B51,G$5:G$10,"#4230,08249002837") -> #NAME? | I51: =E51-G51 -> #NAME? | K51: =_xll.GetCtData("CO-AMOUNT","CONS-AMOUNT",$A$1:$A$4,$A51:$B51,K$5:K$10,"#-6390,57288863795") -> #NAME? | M51: =_xll.GetCtData("CO-AMOUNT","CONS-AMOUNT",$A$1:$A$4,$A51:$B51,M$5:M$10,"#-6689,25370386945") -> #NAME? | O51: =K51-M51 -> #NAME? | Q51: =_xll.GetCtData("CO-AMOUNT","CONS-AMOUNT",$A$1:$A$4,$A51:$B51,Q$5:Q$10,"#-2557,10765152316") -> #NAME? | S51: =_xll.GetCtData("CO-AMOUNT","CONS-AMOUNT",$A$1:$A$4,$A51:$B51,S$5:S$10,"#-2177,21146578454") -> #NAME? | U51: =Q51-S51 -> #NAME?
A52: {OA=OA005O}+{OA=OA006}+{OA=OA010}+{OA=OA011}+{OA=OA017}+{OA=OA021}+{OA=OA021O}+{OA=OA023}+{OA=OA024} | B52: {RU=G-UK}+{RU=P-UK}+{RU=G-UKSP} | C52: UK | D52: o/w UK (GBP) | E52: =_xll.GetCtData("CO-AMOUNT","AMOUNT",$A$1:$A$4,$A52:$B52,E$5:E$10,"#13339,55") -> #NAME? | G52: =_xll.GetCtData("CO-AMOUNT","AMOUNT",$A$1:$A$4,$A52:$B52,G$5:G$10,"#14839,796") -> #NAME? | I52: =E52-G52 -> #NAME? | K52: =_xll.GetCtData("CO-AMOUNT","AMOUNT",$A$1:$A$4,$A52:$B52,K$5:K$10,"#-22754,615") -> #NAME? | M52: =_xll.GetCtData("CO-AMOUNT","AMOUNT",$A$1:$A$4,$A52:$B52,M$5:M$10,"#-23562,137") -> #NAME? | O52: =K52-M52 -> #NAME? | Q52: =_xll.GetCtData("CO-AMOUNT","AMOUNT",$A$1:$A$4,$A52:$B52,Q$5:Q$10,"#-9491,682") -> #NAME? | S52: =_xll.GetCtData("CO-AMOUNT","AMOUNT",$A$1:$A$4,$A52:$B52,S$5:S$10,"#-8660,707") -> #NAME? | U52: =Q52-S52 -> #NAME?
A53: {OA=OA005O}+{OA=OA017}+{OA=OA021O}+{OA=OA024} | B53: {RU=G-UK}+{RU=P-UK}+{RU=G-UKSP}+{RU=G-UKPROMO} | D53: o/w UK S&P (GBP) | E53: =_xll.GetCtData("CO-AMOUNT","AMOUNT",$A$1:$A$4,$A53:$B53,E$5:E$10,"#10118,922") -> #NAME? | G53: =_xll.GetCtData("CO-AMOUNT","AMOUNT",$A$1:$A$4,$A53:$B53,G$5:G$10,"#11172,286") -> #NAME? | I53: =E53-G53 -> #NAME? | K53: =_xll.GetCtData("CO-AMOUNT","AMOUNT",$A$1:$A$4,$A53:$B53,K$5:K$10,"#-17205,667") -> #NAME? | M53: =_xll.GetCtData("CO-AMOUNT","AMOUNT",$A$1:$A$4,$A53:$B53,M$5:M$10,"#-17762,509") -> #NAME? | O53: =K53-M53 -> #NAME? | Q53: =_xll.GetCtData("CO-AMOUNT","AMOUNT",$A$1:$A$4,$A53:$B53,Q$5:Q$10,"#-7271,34") -> #NAME? | S53: =_xll.GetCtData("CO-AMOUNT","AMOUNT",$A$1:$A$4,$A53:$B53,S$5:S$10,"#-6773,04999999999") -> #NAME? | U53: =Q53-S53 -> #NAME?
A54: {OA=OA006}+{OA=OA010}+{OA=OA011}+{OA=OA021}+{OA=OA023} | B54: {RU=G-UK}+{RU=P-UK}+{RU=G-UKSP}+{RU=G-UKPROMO} | C54: UK | D54: o/w UK Commercial (GBP) | E54: =_xll.GetCtData("CO-AMOUNT","AMOUNT",$A$1:$A$4,$A54:$B54,E$5:E$10,"#3220,628") -> #NAME? | G54: =_xll.GetCtData("CO-AMOUNT","AMOUNT",$A$1:$A$4,$A54:$B54,G$5:G$10,"#3667,51") -> #NAME? | I54: =E54-G54 -> #NAME? | K54: =_xll.GetCtData("CO-AMOUNT","AMOUNT",$A$1:$A$4,$A54:$B54,K$5:K$10,"#-5548,948") -> #NAME? | M54: =_xll.GetCtData("CO-AMOUNT","AMOUNT",$A$1:$A$4,$A54:$B54,M$5:M$10,"#-5799,628") -> #NAME? | O54: =K54-M54 -> #NAME? | Q54: =_xll.GetCtData("CO-AMOUNT","AMOUNT",$A$1:$A$4,$A54:$B54,Q$5:Q$10,"#-2220,342") -> #NAME? | S54: =_xll.GetCtData("CO-AMOUNT","AMOUNT",$A$1:$A$4,$A54:$B54,S$5:S$10,"#-1887,657") -> #NAME? | U54: =Q54-S54 -> #NAME?
A55: OA sum AR0121 | B55: {RU=G-FRAR}+{RU=P-FRAR}+{RU=G-FRMP}+{RU=P-FRMP} | C55: FR | D55: =CHOOSE([6]Traduction!$A$2,[6]Traduction!$A45,[6]Traduction!$B45) -> o/w France | E55: =_xll.GetCtData("CO-AMOUNT","CONS-AMOUNT",$A$1:$A$4,$A55:$B55,E$5:E$10,"#25752,536")-E92 -> #NAME? | G55: =_xll.GetCtData("CO-AMOUNT","CONS-AMOUNT",$A$1:$A$4,$A55:$B55,G$5:G$10,"#26491,339")-G92 -> #NAME? | I55: =E55-G55 -> #NAME? | K55: =_xll.GetCtData("CO-AMOUNT","CONS-AMOUNT",$A$1:$A$4,$A55:$B55,K$5:K$10,"#-30349,721")-K92 -> #NAME? | M55: =_xll.GetCtData("CO-AMOUNT","CONS-AMOUNT",$A$1:$A$4,$A55:$B55,M$5:M$10,"#-30744,635")-M92 -> #NAME? | O55: =K55-M55 -> #NAME? | Q55: =_xll.GetCtData("CO-AMOUNT","CONS-AMOUNT",$A$1:$A$4,$A55:$B55,Q$5:Q$10,"#-4724,692")-Q92 -> #NAME? | S55: =_xll.GetCtData("CO-AMOUNT","CONS-AMOUNT",$A$1:$A$4,$A55:$B55,S$5:S$10,"#-4328,296")-S92 -> #NAME? | U55: =Q55-S55 -> #NAME? | W55: =_xll.GetCtData("CO-AMOUNT","CONS-AMOUNT",$A$1:$A$4,$A55:$B55,W$5:W$10,"#-218,085")-W92 -> #NAME? | Y55: =_xll.GetCtData("CO-AMOUNT","CONS-AMOUNT",$A$1:$A$4,$A55:$B55,Y$5:Y$10,"#-145,417")-Y92 -> #NAME? | AA55: =W55-Y55 -> #NAME? | AC55: =_xll.GetCtData("CO-AMOUNT","CONS-AMOUNT",$A$1:$A$4,$A55:$B55,AC$5:AC$10,"#")-AC92 -> #NAME? | AE55: =_xll.GetCtData("CO-AMOUNT","CONS-AMOUNT",$A$1:$A$4,$A55:$B55,AE$5:AE$10,"#")-AE92 -> #NAME? | AG55: =AC55-AE55 -> #NAME? | AI55: =_xll.GetCtData("CO-AMOUNT","CONS-AMOUNT",$A$1:$A$4,$A55:$B55,AI$5:AI$10,"#-309,395")-AI92 -> #NAME? | AK55: =_xll.GetCtData("CO-AMOUNT","CONS-AMOUNT",$A$1:$A$4,$A55:$B55,AK$5:AK$10,"#-206,135")-AK92 -> #NAME? | AM55: =AI55-AK55 -> #NAME? | AO55: =_xll.GetCtData("CO-AMOUNT","CONS-AMOUNT",$A$1:$A$4,$A55:$B55,AO$5:AO$10,"#-6598,033")-AO92 -> #NAME? | AQ55: =_xll.GetCtData("CO-AMOUNT","CONS-AMOUNT",$A$1:$A$4,$A55:$B55,AQ$5:AQ$10,"#-6601,72")-AQ92 -> #NAME? | AS55: =AO55-AQ55 -> #NAME? | AU55: =W55+AC55+AI55+AO55 -> #NAME? | AW55: =Y55+AE55+AK55+AQ55 -> #NAME? | AY55: =AU55-AW55 -> #NAME? | BA55: =+Q55-AO55 -> #NAME? | BC55: =+S55-AQ55 -> #NAME? | BE55: =BA55-BC55 -> #NAME? | BG55: =_xll.GetCtData("CO-AMOUNT","CONS-AMOUNT",$A$1:$A$4,$A55:$B55,BG$5:BG$10,"#-6290,398")-BG92 -> #NAME? | BI55: =_xll.GetCtData("CO-AMOUNT","CONS-AMOUNT",$A$1:$A$4,$A55:$B55,BI$5:BI$10,"#-6290,348")-BI92 -> #NAME? | BK55: =BG55-BI55 -> #NAME? | BN55: =_xll.GetCtData("CO-AMOUNT","CONS-AMOUNT",$A$1:$A$4,$A55:$B55,BN$5:BN$10,"#-307,635")-BN92 -> #NAME? | BP55: =_xll.GetCtData("CO-AMOUNT","CONS-AMOUNT",$A$1:$A$4,$A55:$B55,BP$5:BP$10,"#-311,372")-BP92 -> #NAME? | BR55: =BN55-BP55 -> #NAME?
A56: {OA=OA016}+{OA=OA017} | B56: {RU=G-FRMP}+{RU=P-FRMP} | D56: =CHOOSE([6]Traduction!$A$2,[6]Traduction!$A68,[6]Traduction!$B68) -> o/w residential | E56: =_xll.GetCtData("CO-AMOUNT","CONS-AMOUNT",$A$1:$A$4,$A56:$B56,E$5:E$10,"#") -> #NAME? | G56: =_xll.GetCtData("CO-AMOUNT","CONS-AMOUNT",$A$1:$A$4,$A56:$B56,G$5:G$10,"#1042,088") -> #NAME? | I56: =E56-G56 -> #NAME? | K56: =_xll.GetCtData("CO-AMOUNT","CONS-AMOUNT",$A$1:$A$4,$A56:$B56,K$5:K$10,"#") -> #NAME? | M56: =_xll.GetCtData("CO-AMOUNT","CONS-AMOUNT",$A$1:$A$4,$A56:$B56,M$5:M$10,"#-1283,16") -> #NAME? | O56: =K56-M56 -> #NAME? | Q56: =_xll.GetCtData("CO-AMOUNT","CONS-AMOUNT",$A$1:$A$4,$A56:$B56,Q$5:Q$10,"#") -> #NAME? | S56: =_xll.GetCtData("CO-AMOUNT","CONS-AMOUNT",$A$1:$A$4,$A56:$B56,S$5:S$10,"#-241,072") -> #NAME? | U56: =Q56-S56 -> #NAME? | W56: =_xll.GetCtData("CO-AMOUNT","CONS-AMOUNT",$A$1:$A$4,$A56:$B56,W$5:W$10,"#") -> #NAME? | Y56: =_xll.GetCtData("CO-AMOUNT","CONS-AMOUNT",$A$1:$A$4,$A56:$B56,Y$5:Y$10,"#") -> #NAME? | AA56: =W56-Y56 -> #NAME? | AC56: =_xll.GetCtData("CO-AMOUNT","CONS-AMOUNT",$A$1:$A$4,$A56:$B56,AC$5:AC$10,"#") -> #NAME? | AE56: =_xll.GetCtData("CO-AMOUNT","CONS-AMOUNT",$A$1:$A$4,$A56:$B56,AE$5:AE$10,"#") -> #NAME? | AG56: =AC56-AE56 -> #NAME? | AI56: =_xll.GetCtData("CO-AMOUNT","CONS-AMOUNT",$A$1:$A$4,$A56:$B56,AI$5:AI$10,"#") -> #NAME? | AK56: =_xll.GetCtData("CO-AMOUNT","CONS-AMOUNT",$A$1:$A$4,$A56:$B56,AK$5:AK$10,"#") -> #NAME? | AM56: =AI56-AK56 -> #NAME? | AO56: =_xll.GetCtData("CO-AMOUNT","CONS-AMOUNT",$A$1:$A$4,$A56:$B56,AO$5:AO$10,"#") -> #NAME? | AQ56: =_xll.GetCtData("CO-AMOUNT","CONS-AMOUNT",$A$1:$A$4,$A56:$B56,AQ$5:AQ$10,"#-275,133") -> #NAME? | AS56: =AO56-AQ56 -> #NAME? | AU56: =W56+AC56+AI56+AO56 -> #NAME? | AW56: =Y56+AE56+AK56+AQ56 -> #NAME? | AY56: =AU56-AW56 -> #NAME? | BA56: =+Q56-AO56 -> #NAME? | BC56: =+S56-AQ56 -> #NAME? | BE56: =BA56-BC56 -> #NAME? | BG56: =_xll.GetCtData("CO-AMOUNT","CONS-AMOUNT",$A$1:$A$4,$A56:$B56,BG$5:BG$10,"#") -> #NAME? | BI56: =_xll.GetCtData("CO-AMOUNT","CONS-AMOUNT",$A$1:$A$4,$A56:$B56,BI$5:BI$10,"#-275,133") -> #NAME? | BK56: =BG56-BI56 -> #NAME? | BN56: =_xll.GetCtData("CO-AMOUNT","CONS-AMOUNT",$A$1:$A$4,$A56:$B56,BN$5:BN$10,"#") -> #NAME? | BP56: =_xll.GetCtData("CO-AMOUNT","CONS-AMOUNT",$A$1:$A$4,$A56:$B56,BP$5:BP$10,"#") -> #NAME? | BR56: =BN56-BP56 -> #NAME?
A57: {OA=OA020O} | B57: {RU=G-FRAR}+{RU=P-FRAR} | D57: =CHOOSE([6]Traduction!$A$2,[6]Traduction!$A70,[6]Traduction!$B70) -> o/w Tracker | E57: =_xll.GetCtData("CO-AMOUNT","CONS-AMOUNT",$A$1:$A$4,$A57:$B57,E$5:E$10,"#") -> #NAME? | G57: =_xll.GetCtData("CO-AMOUNT","CONS-AMOUNT",$A$1:$A$4,$A57:$B57,G$5:G$10,"#239,754") -> #NAME? | I57: =E57-G57 -> #NAME? | K57: =_xll.GetCtData("CO-AMOUNT","CONS-AMOUNT",$A$1:$A$4,$A57:$B57,K$5:K$10,"#31,525") -> #NAME? | M57: =_xll.GetCtData("CO-AMOUNT","CONS-AMOUNT",$A$1:$A$4,$A57:$B57,M$5:M$10,"#-309,335") -> #NAME? | O57: =K57-M57 -> #NAME? | Q57: =_xll.GetCtData("CO-AMOUNT","CONS-AMOUNT",$A$1:$A$4,$A57:$B57,Q$5:Q$10,"#31,525") -> #NAME? | S57: =_xll.GetCtData("CO-AMOUNT","CONS-AMOUNT",$A$1:$A$4,$A57:$B57,S$5:S$10,"#-69,5810000000001") -> #NAME? | U57: =Q57-S57 -> #NAME? | W57: =_xll.GetCtData("CO-AMOUNT","CONS-AMOUNT",$A$1:$A$4,$A57:$B57,W$5:W$10,"#") -> #NAME? | Y57: =_xll.GetCtData("CO-AMOUNT","CONS-AMOUNT",$A$1:$A$4,$A57:$B57,Y$5:Y$10,"#") -> #NAME? | AA57: =W57-Y57 -> #NAME? | AC57: =_xll.GetCtData("CO-AMOUNT","CONS-AMOUNT",$A$1:$A$4,$A57:$B57,AC$5:AC$10,"#") -> #NAME? | AE57: =_xll.GetCtData("CO-AMOUNT","CONS-AMOUNT",$A$1:$A$4,$A57:$B57,AE$5:AE$10,"#") -> #NAME? | AG57: =AC57-AE57 -> #NAME? | AI57: =_xll.GetCtData("CO-AMOUNT","CONS-AMOUNT",$A$1:$A$4,$A57:$B57,AI$5:AI$10,"#") -> #NAME? | AK57: =_xll.GetCtData("CO-AMOUNT","CONS-AMOUNT",$A$1:$A$4,$A57:$B57,AK$5:AK$10,"#") -> #NAME? | AM57: =AI57-AK57 -> #NAME? | AO57: =_xll.GetCtData("CO-AMOUNT","CONS-AMOUNT",$A$1:$A$4,$A57:$B57,AO$5:AO$10,"#") -> #NAME? | AQ57: =_xll.GetCtData("CO-AMOUNT","CONS-AMOUNT",$A$1:$A$4,$A57:$B57,AQ$5:AQ$10,"#-54,263") -> #NAME? | AS57: =AO57-AQ57 -> #NAME? | AU57: =W57+AC57+AI57+AO57 -> #NAME? | AW57: =Y57+AE57+AK57+AQ57 -> #NAME? | AY57: =AU57-AW57 -> #NAME? | BA57: =+Q57-AO57 -> #NAME? | BC57: =+S57-AQ57 -> #NAME? | BE57: =BA57-BC57 -> #NAME? | BG57: =_xll.GetCtData("CO-AMOUNT","CONS-AMOUNT",$A$1:$A$4,$A57:$B57,BG$5:BG$10,"#") -> #NAME? | BI57: =_xll.GetCtData("CO-AMOUNT","CONS-AMOUNT",$A$1:$A$4,$A57:$B57,BI$5:BI$10,"#-54,263") -> #NAME? | BK57: =BG57-BI57 -> #NAME? | BN57: =_xll.GetCtData("CO-AMOUNT","CONS-AMOUNT",$A$1:$A$4,$A57:$B57,BN$5:BN$10,"#") -> #NAME? | BP57: =_xll.GetCtData("CO-AMOUNT","CONS-AMOUNT",$A$1:$A$4,$A57:$B57,BP$5:BP$10,"#") -> #NAME? | BR57: =BN57-BP57 -> #NAME?
A58: OA sum AR0121 | B58: {RU=G-DE}+{RU=P-DE} | C58: DE | D58: =CHOOSE([6]Traduction!$A$2,[6]Traduction!$A49,[6]Traduction!$B49) -> o/w Germany | E58: =_xll.GetCtData("CO-AMOUNT","CONS-AMOUNT",$A$1:$A$4,$A58:$B58,E$5:E$10,"#21503,992") -> #NAME? | G58: =_xll.GetCtData("CO-AMOUNT","CONS-AMOUNT",$A$1:$A$4,$A58:$B58,G$5:G$10,"#17276,575") -> #NAME? | I58: =E58-G58 -> #NAME? | K58: =_xll.GetCtData("CO-AMOUNT","CONS-AMOUNT",$A$1:$A$4,$A58:$B58,K$5:K$10,"#-22361,018") -> #NAME? | M58: =_xll.GetCtData("CO-AMOUNT","CONS-AMOUNT",$A$1:$A$4,$A58:$B58,M$5:M$10,"#-21612,791") -> #NAME? | O58: =K58-M58 -> #NAME? | Q58: =_xll.GetCtData("CO-AMOUNT","CONS-AMOUNT",$A$1:$A$4,$A58:$B58,Q$5:Q$10,"#-1198,962") -> #NAME? | S58: =_xll.GetCtData("CO-AMOUNT","CONS-AMOUNT",$A$1:$A$4,$A58:$B58,S$5:S$10,"#-4362,803") -> #NAME? | U58: =Q58-S58 -> #NAME? | W58: =_xll.GetCtData("CO-AMOUNT","CONS-AMOUNT",$A$1:$A$4,$A58:$B58,W$5:W$10,"#-218") -> #NAME? | Y58: =_xll.GetCtData("CO-AMOUNT","CONS-AMOUNT",$A$1:$A$4,$A58:$B58,Y$5:Y$10,"#-218,085") -> #NAME? | AA58: =W58-Y58 -> #NAME? | AC58: =_xll.GetCtData("CO-AMOUNT","CONS-AMOUNT",$A$1:$A$4,$A58:$B58,AC$5:AC$10,"#") -> #NAME? | AE58: =_xll.GetCtData("CO-AMOUNT","CONS-AMOUNT",$A$1:$A$4,$A58:$B58,AE$5:AE$10,"#") -> #NAME? | AG58: =AC58-AE58 -> #NAME? | AI58: =_xll.GetCtData("CO-AMOUNT","CONS-AMOUNT",$A$1:$A$4,$A58:$B58,AI$5:AI$10,"#-148") -> #NAME? | AK58: =_xll.GetCtData("CO-AMOUNT","CONS-AMOUNT",$A$1:$A$4,$A58:$B58,AK$5:AK$10,"#-148,272") -> #NAME? | AM58: =AI58-AK58 -> #NAME? | AO58: =_xll.GetCtData("CO-AMOUNT","CONS-AMOUNT",$A$1:$A$4,$A58:$B58,AO$5:AO$10,"#-936,59") -> #NAME? | AQ58: =_xll.GetCtData("CO-AMOUNT","CONS-AMOUNT",$A$1:$A$4,$A58:$B58,AQ$5:AQ$10,"#-944,585") -> #NAME? | AS58: =AO58-AQ58 -> #NAME? | AU58: =W58+AC58+AI58+AO58 -> #NAME? | AW58: =Y58+AE58+AK58+AQ58 -> #NAME? | AY58: =AU58-AW58 -> #NAME? | BA58: =+Q58-AO58 -> #NAME? | BC58: =+S58-AQ58 -> #NAME? | BE58: =BA58-BC58 -> #NAME? | BG58: =_xll.GetCtData("CO-AMOUNT","CONS-AMOUNT",$A$1:$A$4,$A58:$B58,BG$5:BG$10,"#-742,014") -> #NAME? | BI58: =_xll.GetCtData("CO-AMOUNT","CONS-AMOUNT",$A$1:$A$4,$A58:$B58,BI$5:BI$10,"#-742,012") -> #NAME? | BK58: =BG58-BI58 -> #NAME? | BN58: =_xll.GetCtData("CO-AMOUNT","CONS-AMOUNT",$A$1:$A$4,$A58:$B58,BN$5:BN$10,"#-194,576") -> #NAME? | BP58: =_xll.GetCtData("CO-AMOUNT","CONS-AMOUNT",$A$1:$A$4,$A58:$B58,BP$5:BP$10,"#-202,573") -> #NAME? | BR58: =BN58-BP58 -> #NAME?
D59: =CHOOSE([6]Traduction!$A$2,[6]Traduction!$A71,[6]Traduction!$B71) -> o/w Advisory 7 | E59: =E60+E61+E62+E63+E64+E65+E66 -> #NAME? | G59: =G60+G61+G62+G63+G64+G65+G66 -> #NAME? | I59: =E59-G59 -> #NAME? | K59: =K60+K61+K62+K63+K64+K65+K66 -> #NAME? | M59: =M60+M61+M62+M63+M64+M65+M66 -> #NAME? | O59: =K59-M59 -> #NAME? | Q59: =Q60+Q61+Q62+Q63+Q64+Q65+Q66 -> #NAME? | S59: =S60+S61+S62+S63+S64+S65+S66 -> #NAME? | U59: =Q59-S59 -> #NAME? | W59: =W60+W61+W62+W63+W64+W65+W66 -> #NAME? | Y59: =Y60+Y61+Y62+Y63+Y64+Y65+Y66 -> #NAME? | AA59: =W59-Y59 -> #NAME? | AC59: =AC60+AC61+AC62+AC63+AC64+AC65+AC66 -> #NAME? | AE59: =AE60+AE61+AE62+AE63+AE64+AE65+AE66 -> #NAME? | AG59: =AC59-AE59 -> #NAME? | AI59: =AI60+AI61+AI62+AI63+AI64+AI65+AI66 -> #NAME? | AK59: =AK60+AK61+AK62+AK63+AK64+AK65+AK66 -> #NAME? | AM59: =AI59-AK59 -> #NAME? | AO59: =AO60+AO61+AO62+AO63+AO64+AO65+AO66 -> #NAME? | AQ59: =AQ60+AQ61+AQ62+AQ63+AQ64+AQ65+AQ66 -> #NAME? | AS59: =AO59-AQ59 -> #NAME? | AU59: =W59+AC59+AI59+AO59 -> #NAME? | AW59: =Y59+AE59+AK59+AQ59 -> #NAME? | AY59: =AU59-AW59 -> #NAME? | BA59: =+Q59-AO59 -> #NAME? | BC59: =+S59-AQ59 -> #NAME? | BE59: =BA59-BC59 -> #NAME? | BG59: =BG60+BG61+BG62+BG63+BG64+BG65+BG66 -> #NAME? | BI59: =BI60+BI61+BI62+BI63+BI64+BI65+BI66 -> #NAME? | BK59: =BG59-BI59 -> #NAME? | BN59: =BN60+BN61+BN62+BN63+BN64+BN65+BN66 -> #NAME? | BP59: =BP60+BP61+BP62+BP63+BP64+BP65+BP66 -> #NAME? | BR59: =BN59-BP59 -> #NAME?
A60: OA sum AR0121 | B60: RU=G-SP | C60: ESP | D60: =CHOOSE([6]Traduction!$A$2,[6]Traduction!$A48,[6]Traduction!$B48) -> o/w Spain | E60: =_xll.GetCtData("CO-AMOUNT","CONS-AMOUNT",$A$1:$A$4,$A60:$B60,E$5:E$10,"#1419,642") -> #NAME? | G60: =_xll.GetCtData("CO-AMOUNT","CONS-AMOUNT",$A$1:$A$4,$A60:$B60,G$5:G$10,"#1491,872") -> #NAME? | I60: =E60-G60 -> #NAME? | K60: =_xll.GetCtData("CO-AMOUNT","CONS-AMOUNT",$A$1:$A$4,$A60:$B60,K$5:K$10,"#-2517,165") -> #NAME? | M60: =_xll.GetCtData("CO-AMOUNT","CONS-AMOUNT",$A$1:$A$4,$A60:$B60,M$5:M$10,"#-2588,046") -> #NAME? | O60: =K60-M60 -> #NAME? | Q60: =_xll.GetCtData("CO-AMOUNT","CONS-AMOUNT",$A$1:$A$4,$A60:$B60,Q$5:Q$10,"#-1187,182") -> #NAME? | S60: =_xll.GetCtData("CO-AMOUNT","CONS-AMOUNT",$A$1:$A$4,$A60:$B60,S$5:S$10,"#-1131,034") -> #NAME? | U60: =Q60-S60 -> #NAME? | W60: =_xll.GetCtData("CO-AMOUNT","CONS-AMOUNT",$A$1:$A$4,$A60:$B60,W$5:W$10,"#-16,72") -> #NAME? | Y60: =_xll.GetCtData("CO-AMOUNT","CONS-AMOUNT",$A$1:$A$4,$A60:$B60,Y$5:Y$10,"#-17,048") -> #NAME? | AA60: =W60-Y60 -> #NAME? | AC60: =_xll.GetCtData("CO-AMOUNT","CONS-AMOUNT",$A$1:$A$4,$A60:$B60,AC$5:AC$10,"#") -> #NAME? | AE60: =_xll.GetCtData("CO-AMOUNT","CONS-AMOUNT",$A$1:$A$4,$A60:$B60,AE$5:AE$10,"#") -> #NAME? | AG60: =AC60-AE60 -> #NAME? | AI60: =_xll.GetCtData("CO-AMOUNT","CONS-AMOUNT",$A$1:$A$4,$A60:$B60,AI$5:AI$10,"#-23,71") -> #NAME? | AK60: =_xll.GetCtData("CO-AMOUNT","CONS-AMOUNT",$A$1:$A$4,$A60:$B60,AK$5:AK$10,"#-24,2") -> #NAME? | AM60: =AI60-AK60 -> #NAME? | AO60: =_xll.GetCtData("CO-AMOUNT","CONS-AMOUNT",$A$1:$A$4,$A60:$B60,AO$5:AO$10,"#-118,922") -> #NAME? | AQ60: =_xll.GetCtData("CO-AMOUNT","CONS-AMOUNT",$A$1:$A$4,$A60:$B60,AQ$5:AQ$10,"#-120,729") -> #NAME? | AS60: =AO60-AQ60 -> #NAME? | AU60: =W60+AC60+AI60+AO60 -> #NAME? | AW60: =Y60+AE60+AK60+AQ60 -> #NAME? | AY60: =AU60-AW60 -> #NAME? | BA60: =+Q60-AO60 -> #NAME? | BC60: =+S60-AQ60 -> #NAME? | BE60: =BA60-BC60 -> #NAME? | BG60: =_xll.GetCtData("CO-AMOUNT","CONS-AMOUNT",$A$1:$A$4,$A60:$B60,BG$5:BG$10,"#-93,99") -> #NAME? | BI60: =_xll.GetCtData("CO-AMOUNT","CONS-AMOUNT",$A$1:$A$4,$A60:$B60,BI$5:BI$10,"#-95,418") -> #NAME? | BK60: =BG60-BI60 -> #NAME? | BN60: =_xll.GetCtData("CO-AMOUNT","CONS-AMOUNT",$A$1:$A$4,$A60:$B60,BN$5:BN$10,"#-24,932") -> #NAME? | BP60: =_xll.GetCtData("CO-AMOUNT","CONS-AMOUNT",$A$1:$A$4,$A60:$B60,BP$5:BP$10,"#-25,311") -> #NAME? | BR60: =BN60-BP60 -> #NAME?
A61: OA sum AR0121 | B61: {RU=G-BE}+{RU=P-BE} | C61: BEL | D61: =CHOOSE([6]Traduction!$A$2,[6]Traduction!$A66,[6]Traduction!$B66) -> o/w Belgium | E61: =_xll.GetCtData("CO-AMOUNT","CONS-AMOUNT",$A$1:$A$4,$A61:$B61,E$5:E$10,"#1653") -> #NAME? | G61: =_xll.GetCtData("CO-AMOUNT","CONS-AMOUNT",$A$1:$A$4,$A61:$B61,G$5:G$10,"#1407,564") -> #NAME? | I61: =E61-G61 -> #NAME? | K61: =_xll.GetCtData("CO-AMOUNT","CONS-AMOUNT",$A$1:$A$4,$A61:$B61,K$5:K$10,"#-1574,813") -> #NAME? | M61: =_xll.GetCtData("CO-AMOUNT","CONS-AMOUNT",$A$1:$A$4,$A61:$B61,M$5:M$10,"#-1594,581") -> #NAME? | O61: =K61-M61 -> #NAME? | Q61: =_xll.GetCtData("CO-AMOUNT","CONS-AMOUNT",$A$1:$A$4,$A61:$B61,Q$5:Q$10,"#130,187") -> #NAME? | S61: =_xll.GetCtData("CO-AMOUNT","CONS-AMOUNT",$A$1:$A$4,$A61:$B61,S$5:S$10,"#-188,837") -> #NAME? | U61: =Q61-S61 -> #NAME? | W61: =_xll.GetCtData("CO-AMOUNT","CONS-AMOUNT",$A$1:$A$4,$A61:$B61,W$5:W$10,"#-4,36") -> #NAME? | Y61: =_xll.GetCtData("CO-AMOUNT","CONS-AMOUNT",$A$1:$A$4,$A61:$B61,Y$5:Y$10,"#-1") -> #NAME? | AA61: =W61-Y61 -> #NAME? | AC61: =_xll.GetCtData("CO-AMOUNT","CONS-AMOUNT",$A$1:$A$4,$A61:$B61,AC$5:AC$10,"#") -> #NAME? | AE61: =_xll.GetCtData("CO-AMOUNT","CONS-AMOUNT",$A$1:$A$4,$A61:$B61,AE$5:AE$10,"#") -> #NAME? | AG61: =AC61-AE61 -> #NAME? | AI61: =_xll.GetCtData("CO-AMOUNT","CONS-AMOUNT",$A$1:$A$4,$A61:$B61,AI$5:AI$10,"#-6,178") -> #NAME? | AK61: =_xll.GetCtData("CO-AMOUNT","CONS-AMOUNT",$A$1:$A$4,$A61:$B61,AK$5:AK$10,"#-4,17") -> #NAME? | AM61: =AI61-AK61 -> #NAME? | AO61: =_xll.GetCtData("CO-AMOUNT","CONS-AMOUNT",$A$1:$A$4,$A61:$B61,AO$5:AO$10,"#-82") -> #NAME? | AQ61: =_xll.GetCtData("CO-AMOUNT","CONS-AMOUNT",$A$1:$A$4,$A61:$B61,AQ$5:AQ$10,"#-87,48") -> #NAME? | AS61: =AO61-AQ61 -> #NAME? | AU61: =W61+AC61+AI61+AO61 -> #NAME? | AW61: =Y61+AE61+AK61+AQ61 -> #NAME? | AY61: =AU61-AW61 -> #NAME? | BA61: =+Q61-AO61 -> #NAME? | BC61: =+S61-AQ61 -> #NAME? | BE61: =BA61-BC61 -> #NAME? | BG61: =_xll.GetCtData("CO-AMOUNT","CONS-AMOUNT",$A$1:$A$4,$A61:$B61,BG$5:BG$10,"#-73") -> #NAME? | BI61: =_xll.GetCtData("CO-AMOUNT","CONS-AMOUNT",$A$1:$A$4,$A61:$B61,BI$5:BI$10,"#-72,16") -> #NAME? | BK61: =BG61-BI61 -> #NAME? | BN61: =_xll.GetCtData("CO-AMOUNT","CONS-AMOUNT",$A$1:$A$4,$A61:$B61,BN$5:BN$10,"#-9") -> #NAME? | BP61: =_xll.GetCtData("CO-AMOUNT","CONS-AMOUNT",$A$1:$A$4,$A61:$B61,BP$5:BP$10,"#-15,32") -> #NAME? | BR61: =BN61-BP61 -> #NAME?
A62: OA sum AR0121 | B62: RU=G-LX | C62: LUX | D62: =CHOOSE([6]Traduction!$A$2,[6]Traduction!$A53,[6]Traduction!$B53) -> o/w Luxembourg | E62: =_xll.GetCtData("CO-AMOUNT","CONS-AMOUNT",$A$1:$A$4,$A62:$B62,E$5:E$10,"#109,842") -> #NAME? | G62: =_xll.GetCtData("CO-AMOUNT","CONS-AMOUNT",$A$1:$A$4,$A62:$B62,G$5:G$10,"#317,589") -> #NAME? | I62: =E62-G62 -> #NAME? | K62: =_xll.GetCtData("CO-AMOUNT","CONS-AMOUNT",$A$1:$A$4,$A62:$B62,K$5:K$10,"#-374,34") -> #NAME? | M62: =_xll.GetCtData("CO-AMOUNT","CONS-AMOUNT",$A$1:$A$4,$A62:$B62,M$5:M$10,"#-428,081") -> #NAME? | O62: =K62-M62 -> #NAME? | Q62: =_xll.GetCtData("CO-AMOUNT","CONS-AMOUNT",$A$1:$A$4,$A62:$B62,Q$5:Q$10,"#-264,498") -> #NAME? | S62: =_xll.GetCtData("CO-AMOUNT","CONS-AMOUNT",$A$1:$A$4,$A62:$B62,S$5:S$10,"#-110,492") -> #NAME? | U62: =Q62-S62 -> #NAME? | W62: =_xll.GetCtData("CO-AMOUNT","CONS-AMOUNT",$A$1:$A$4,$A62:$B62,W$5:W$10,"#-2,908") -> #NAME? | Y62: =_xll.GetCtData("CO-AMOUNT","CONS-AMOUNT",$A$1:$A$4,$A62:$B62,Y$5:Y$10,"#-2,908") -> #NAME? | AA62: =W62-Y62 -> #NAME? | AC62: =_xll.GetCtData("CO-AMOUNT","CONS-AMOUNT",$A$1:$A$4,$A62:$B62,AC$5:AC$10,"#") -> #NAME? | AE62: =_xll.GetCtData("CO-AMOUNT","CONS-AMOUNT",$A$1:$A$4,$A62:$B62,AE$5:AE$10,"#") -> #NAME? | AG62: =AC62-AE62 -> #NAME? | AI62: =_xll.GetCtData("CO-AMOUNT","CONS-AMOUNT",$A$1:$A$4,$A62:$B62,AI$5:AI$10,"#-4,121") -> #NAME? | AK62: =_xll.GetCtData("CO-AMOUNT","CONS-AMOUNT",$A$1:$A$4,$A62:$B62,AK$5:AK$10,"#-4,122") -> #NAME? | AM62: =AI62-AK62 -> #NAME? | AO62: =_xll.GetCtData("CO-AMOUNT","CONS-AMOUNT",$A$1:$A$4,$A62:$B62,AO$5:AO$10,"#-20,81") -> #NAME? | AQ62: =_xll.GetCtData("CO-AMOUNT","CONS-AMOUNT",$A$1:$A$4,$A62:$B62,AQ$5:AQ$10,"#-19,965") -> #NAME? | AS62: =AO62-AQ62 -> #NAME? | AU62: =W62+AC62+AI62+AO62 -> #NAME? | AW62: =Y62+AE62+AK62+AQ62 -> #NAME? | AY62: =AU62-AW62 -> #NAME? | BA62: =+Q62-AO62 -> #NAME? | BC62: =+S62-AQ62 -> #NAME? | BE62: =BA62-BC62 -> #NAME? | BG62: =_xll.GetCtData("CO-AMOUNT","CONS-AMOUNT",$A$1:$A$4,$A62:$B62,BG$5:BG$10,"#-20,81") -> #NAME? | BI62: =_xll.GetCtData("CO-AMOUNT","CONS-AMOUNT",$A$1:$A$4,$A62:$B62,BI$5:BI$10,"#-19,965") -> #NAME? | BK62: =BG62-BI62 -> #NAME? | BN62: =_xll.GetCtData("CO-AMOUNT","CONS-AMOUNT",$A$1:$A$4,$A62:$B62,BN$5:BN$10,"#") -> #NAME? | BP62: =_xll.GetCtData("CO-AMOUNT","CONS-AMOUNT",$A$1:$A$4,$A62:$B62,BP$5:BP$10,"#") -> #NAME? | BR62: =BN62-BP62 -> #NAME?
A63: OA sum AR0121 | B63: RU sum AF026 | C63: ITA | D63: =CHOOSE([6]Traduction!$A$2,[6]Traduction!$A46,[6]Traduction!$B46) -> o/w Italy | E63: =_xll.GetCtData("CO-AMOUNT","CONS-AMOUNT",$A$1:$A$4,$A63:$B63,E$5:E$10,"#1000,451") -> #NAME? | G63: =_xll.GetCtData("CO-AMOUNT","CONS-AMOUNT",$A$1:$A$4,$A63:$B63,G$5:G$10,"#1295,202") -> #NAME? | I63: =E63-G63 -> #NAME? | K63: =_xll.GetCtData("CO-AMOUNT","CONS-AMOUNT",$A$1:$A$4,$A63:$B63,K$5:K$10,"#-2099,936") -> #NAME? | M63: =_xll.GetCtData("CO-AMOUNT","CONS-AMOUNT",$A$1:$A$4,$A63:$B63,M$5:M$10,"#-2193,497") -> #NAME? | O63: =K63-M63 -> #NAME? | Q63: =_xll.GetCtData("CO-AMOUNT","CONS-AMOUNT",$A$1:$A$4,$A63:$B63,Q$5:Q$10,"#-1099,485") -> #NAME? | S63: =_xll.GetCtData("CO-AMOUNT","CONS-AMOUNT",$A$1:$A$4,$A63:$B63,S$5:S$10,"#-898,294999999999") -> #NAME? | U63: =Q63-S63 -> #NAME? | W63: =_xll.GetCtData("CO-AMOUNT","CONS-AMOUNT",$A$1:$A$4,$A63:$B63,W$5:W$10,"#-6,543") -> #NAME? | Y63: =_xll.GetCtData("CO-AMOUNT","CONS-AMOUNT",$A$1:$A$4,$A63:$B63,Y$5:Y$10,"#-6,543") -> #NAME? | AA63: =W63-Y63 -> #NAME? | AC63: =_xll.GetCtData("CO-AMOUNT","CONS-AMOUNT",$A$1:$A$4,$A63:$B63,AC$5:AC$10,"#") -> #NAME? | AE63: =_xll.GetCtData("CO-AMOUNT","CONS-AMOUNT",$A$1:$A$4,$A63:$B63,AE$5:AE$10,"#") -> #NAME? | AG63: =AC63-AE63 -> #NAME? | AI63: =_xll.GetCtData("CO-AMOUNT","CONS-AMOUNT",$A$1:$A$4,$A63:$B63,AI$5:AI$10,"#-9,276") -> #NAME? | AK63: =_xll.GetCtData("CO-AMOUNT","CONS-AMOUNT",$A$1:$A$4,$A63:$B63,AK$5:AK$10,"#-9,276") -> #NAME? | AM63: =AI63-AK63 -> #NAME? | AO63: =_xll.GetCtData("CO-AMOUNT","CONS-AMOUNT",$A$1:$A$4,$A63:$B63,AO$5:AO$10,"#-83,086") -> #NAME? | AQ63: =_xll.GetCtData("CO-AMOUNT","CONS-AMOUNT",$A$1:$A$4,$A63:$B63,AQ$5:AQ$10,"#-83,077") -> #NAME? | AS63: =AO63-AQ63 -> #NAME? | AU63: =W63+AC63+AI63+AO63 -> #NAME? | AW63: =Y63+AE63+AK63+AQ63 -> #NAME? | AY63: =AU63-AW63 -> #NAME? | BA63: =+Q63-AO63 -> #NAME? | BC63: =+S63-AQ63 -> #NAME? | BE63: =BA63-BC63 -> #NAME? | BG63: =_xll.GetCtData("CO-AMOUNT","CONS-AMOUNT",$A$1:$A$4,$A63:$B63,BG$5:BG$10,"#-74,188") -> #NAME? | BI63: =_xll.GetCtData("CO-AMOUNT","CONS-AMOUNT",$A$1:$A$4,$A63:$B63,BI$5:BI$10,"#-74,18") -> #NAME? | BK63: =BG63-BI63 -> #NAME? | BN63: =_xll.GetCtData("CO-AMOUNT","CONS-AMOUNT",$A$1:$A$4,$A63:$B63,BN$5:BN$10,"#-8,898") -> #NAME? | BP63: =_xll.GetCtData("CO-AMOUNT","CONS-AMOUNT",$A$1:$A$4,$A63:$B63,BP$5:BP$10,"#-8,897") -> #NAME? | BR63: =BN63-BP63 -> #NAME?
A64: OA sum AR0121 | B64: RU=G-IR | C64: IRL | D64: =CHOOSE([6]Traduction!$A$2,[6]Traduction!$A72,[6]Traduction!$B72) -> o/w Ireland | E64: =_xll.GetCtData("CO-AMOUNT","CONS-AMOUNT",$A$1:$A$4,$A64:$B64,E$5:E$10,"#207") -> #NAME? | G64: =_xll.GetCtData("CO-AMOUNT","CONS-AMOUNT",$A$1:$A$4,$A64:$B64,G$5:G$10,"#446,2") -> #NAME? | I64: =E64-G64 -> #NAME? | K64: =_xll.GetCtData("CO-AMOUNT","CONS-AMOUNT",$A$1:$A$4,$A64:$B64,K$5:K$10,"#-685,13") -> #NAME? | M64: =_xll.GetCtData("CO-AMOUNT","CONS-AMOUNT",$A$1:$A$4,$A64:$B64,M$5:M$10,"#-594,061") -> #NAME? | O64: =K64-M64 -> #NAME? | Q64: =_xll.GetCtData("CO-AMOUNT","CONS-AMOUNT",$A$1:$A$4,$A64:$B64,Q$5:Q$10,"#-478,13") -> #NAME? | S64: =_xll.GetCtData("CO-AMOUNT","CONS-AMOUNT",$A$1:$A$4,$A64:$B64,S$5:S$10,"#-147,861") -> #NAME? | U64: =Q64-S64 -> #NAME? | W64: =_xll.GetCtData("CO-AMOUNT","CONS-AMOUNT",$A$1:$A$4,$A64:$B64,W$5:W$10,"#") -> #NAME? | Y64: =_xll.GetCtData("CO-AMOUNT","CONS-AMOUNT",$A$1:$A$4,$A64:$B64,Y$5:Y$10,"#-1,6") -> #NAME? | AA64: =W64-Y64 -> #NAME? | AC64: =_xll.GetCtData("CO-AMOUNT","CONS-AMOUNT",$A$1:$A$4,$A64:$B64,AC$5:AC$10,"#") -> #NAME? | AE64: =_xll.GetCtData("CO-AMOUNT","CONS-AMOUNT",$A$1:$A$4,$A64:$B64,AE$5:AE$10,"#") -> #NAME? | AG64: =AC64-AE64 -> #NAME? | AI64: =_xll.GetCtData("CO-AMOUNT","CONS-AMOUNT",$A$1:$A$4,$A64:$B64,AI$5:AI$10,"#") -> #NAME? | AK64: =_xll.GetCtData("CO-AMOUNT","CONS-AMOUNT",$A$1:$A$4,$A64:$B64,AK$5:AK$10,"#-1,5") -> #NAME? | AM64: =AI64-AK64 -> #NAME? | AO64: =_xll.GetCtData("CO-AMOUNT","CONS-AMOUNT",$A$1:$A$4,$A64:$B64,AO$5:AO$10,"#-18,1") -> #NAME? | AQ64: =_xll.GetCtData("CO-AMOUNT","CONS-AMOUNT",$A$1:$A$4,$A64:$B64,AQ$5:AQ$10,"#-15,183") -> #NAME? | AS64: =AO64-AQ64 -> #NAME? | AU64: =W64+AC64+AI64+AO64 -> #NAME? | AW64: =Y64+AE64+AK64+AQ64 -> #NAME? | AY64: =AU64-AW64 -> #NAME? | BA64: =+Q64-AO64 -> #NAME? | BC64: =+S64-AQ64 -> #NAME? | BE64: =BA64-BC64 -> #NAME? | BG64: =_xll.GetCtData("CO-AMOUNT","CONS-AMOUNT",$A$1:$A$4,$A64:$B64,BG$5:BG$10,"#-18,1") -> #NAME? | BI64: =_xll.GetCtData("CO-AMOUNT","CONS-AMOUNT",$A$1:$A$4,$A64:$B64,BI$5:BI$10,"#-15,183") -> #NAME? | BK64: =BG64-BI64 -> #NAME? | BN64: =_xll.GetCtData("CO-AMOUNT","CONS-AMOUNT",$A$1:$A$4,$A64:$B64,BN$5:BN$10,"#") -> #NAME? | BP64: =_xll.GetCtData("CO-AMOUNT","CONS-AMOUNT",$A$1:$A$4,$A64:$B64,BP$5:BP$10,"#") -> #NAME? | BR64: =BN64-BP64 -> #NAME?
A65: OA sum AR0121 | B65: {RU=G-POL}+{RU=P-POL} | C65: POL | D65: =CHOOSE([6]Traduction!$A$2,[6]Traduction!$A76,[6]Traduction!$B76) -> o/w Poland | E65: =_xll.GetCtData("CO-AMOUNT","CONS-AMOUNT",$A$1:$A$4,$A65:$B65,E$5:E$10,"#491,489818093343") -> #NAME? | G65: =_xll.GetCtData("CO-AMOUNT","CONS-AMOUNT",$A$1:$A$4,$A65:$B65,G$5:G$10,"#865,184101928261") -> #NAME? | I65: =E65-G65 -> #NAME? | K65: =_xll.GetCtData("CO-AMOUNT","CONS-AMOUNT",$A$1:$A$4,$A65:$B65,K$5:K$10,"#-1407,25746208516") -> #NAME? | M65: =_xll.GetCtData("CO-AMOUNT","CONS-AMOUNT",$A$1:$A$4,$A65:$B65,M$5:M$10,"#-1523,00358715936") -> #NAME? | O65: =K65-M65 -> #NAME? | Q65: =_xll.GetCtData("CO-AMOUNT","CONS-AMOUNT",$A$1:$A$4,$A65:$B65,Q$5:Q$10,"#-911,515418178705") -> #NAME? | S65: =_xll.GetCtData("CO-AMOUNT","CONS-AMOUNT",$A$1:$A$4,$A65:$B65,S$5:S$10,"#-655,793260140789") -> #NAME? | U65: =Q65-S65 -> #NAME? | W65: =_xll.GetCtData("CO-AMOUNT","CONS-AMOUNT",$A$1:$A$4,$A65:$B65,W$5:W$10,"#-4,06544712485597") -> #NAME? | Y65: =_xll.GetCtData("CO-AMOUNT","CONS-AMOUNT",$A$1:$A$4,$A65:$B65,Y$5:Y$10,"#-6,07060076870971") -> #NAME? | AA65: =W65-Y65 -> #NAME? | AC65: =_xll.GetCtData("CO-AMOUNT","CONS-AMOUNT",$A$1:$A$4,$A65:$B65,AC$5:AC$10,"#") -> #NAME? | AE65: =_xll.GetCtData("CO-AMOUNT","CONS-AMOUNT",$A$1:$A$4,$A65:$B65,AE$5:AE$10,"#") -> #NAME? | AG65: =AC65-AE65 -> #NAME? | AI65: =_xll.GetCtData("CO-AMOUNT","CONS-AMOUNT",$A$1:$A$4,$A65:$B65,AI$5:AI$10,"#7,64517520830933") -> #NAME? | AK65: =_xll.GetCtData("CO-AMOUNT","CONS-AMOUNT",$A$1:$A$4,$A65:$B65,AK$5:AK$10,"#6,81345497434792") -> #NAME? | AM65: =AI65-AK65 -> #NAME? | AO65: =_xll.GetCtData("CO-AMOUNT","CONS-AMOUNT",$A$1:$A$4,$A65:$B65,AO$5:AO$10,"#-71,0741315440058") -> #NAME? | AQ65: =_xll.GetCtData("CO-AMOUNT","CONS-AMOUNT",$A$1:$A$4,$A65:$B65,AQ$5:AQ$10,"#-72,1573142541268") -> #NAME? | AS65: =AO65-AQ65 -> #NAME? | AU65: =W65+AC65+AI65+AO65 -> #NAME? | AW65: =Y65+AE65+AK65+AQ65 -> #NAME? | AY65: =AU65-AW65 -> #NAME? | BA65: =+Q65-AO65 -> #NAME? | BC65: =+S65-AQ65 -> #NAME? | BE65: =BA65-BC65 -> #NAME? | BG65: =_xll.GetCtData("CO-AMOUNT","CONS-AMOUNT",$A$1:$A$4,$A65:$B65,BG$5:BG$10,"#-61,4926918050686") -> #NAME? | BI65: =_xll.GetCtData("CO-AMOUNT","CONS-AMOUNT",$A$1:$A$4,$A65:$B65,BI$5:BI$10,"#-62,510421451304") -> #NAME? | BK65: =BG65-BI65 -> #NAME? | BN65: =_xll.GetCtData("CO-AMOUNT","CONS-AMOUNT",$A$1:$A$4,$A65:$B65,BN$5:BN$10,"#-9,58143973893714") -> #NAME? | BP65: =_xll.GetCtData("CO-AMOUNT","CONS-AMOUNT",$A$1:$A$4,$A65:$B65,BP$5:BP$10,"#-9,64689280282283") -> #NAME? | BR65: =BN65-BP65 -> #NAME?
A66: OA sum AR0121 | B66: RU=G-NL | C66: NL | D66: =CHOOSE([6]Traduction!$A$2,[6]Traduction!$A77,[6]Traduction!$B77) -> o/w Netherlands | E66: =_xll.GetCtData("CO-AMOUNT","CONS-AMOUNT",$A$1:$A$4,$A66:$B66,E$5:E$10,"#580,54") -> #NAME? | G66: =_xll.GetCtData("CO-AMOUNT","CONS-AMOUNT",$A$1:$A$4,$A66:$B66,G$5:G$10,"#222,175") -> #NAME? | I66: =E66-G66 -> #NAME? | K66: =_xll.GetCtData("CO-AMOUNT","CONS-AMOUNT",$A$1:$A$4,$A66:$B66,K$5:K$10,"#-1245,272") -> #NAME? | M66: =_xll.GetCtData("CO-AMOUNT","CONS-AMOUNT",$A$1:$A$4,$A66:$B66,M$5:M$10,"#-1321,211") -> #NAME? | O66: =K66-M66 -> #NAME? | Q66: =_xll.GetCtData("CO-AMOUNT","CONS-AMOUNT",$A$1:$A$4,$A66:$B66,Q$5:Q$10,"#-664,732") -> #NAME? | S66: =_xll.GetCtData("CO-AMOUNT","CONS-AMOUNT",$A$1:$A$4,$A66:$B66,S$5:S$10,"#-1099,036") -> #NAME? | U66: =Q66-S66 -> #NAME? | W66: =_xll.GetCtData("CO-AMOUNT","CONS-AMOUNT",$A$1:$A$4,$A66:$B66,W$5:W$10,"#-13") -> #NAME? | Y66: =_xll.GetCtData("CO-AMOUNT","CONS-AMOUNT",$A$1:$A$4,$A66:$B66,Y$5:Y$10,"#-16") -> #NAME? | AA66: =W66-Y66 -> #NAME? | AC66: =_xll.GetCtData("CO-AMOUNT","CONS-AMOUNT",$A$1:$A$4,$A66:$B66,AC$5:AC$10,"#") -> #NAME? | AE66: =_xll.GetCtData("CO-AMOUNT","CONS-AMOUNT",$A$1:$A$4,$A66:$B66,AE$5:AE$10,"#") -> #NAME? | AG66: =AC66-AE66 -> #NAME? | AI66: =_xll.GetCtData("CO-AMOUNT","CONS-AMOUNT",$A$1:$A$4,$A66:$B66,AI$5:AI$10,"#-19") -> #NAME? | AK66: =_xll.GetCtData("CO-AMOUNT","CONS-AMOUNT",$A$1:$A$4,$A66:$B66,AK$5:AK$10,"#-18") -> #NAME? | AM66: =AI66-AK66 -> #NAME? | AO66: =_xll.GetCtData("CO-AMOUNT","CONS-AMOUNT",$A$1:$A$4,$A66:$B66,AO$5:AO$10,"#-37") -> #NAME? | AQ66: =_xll.GetCtData("CO-AMOUNT","CONS-AMOUNT",$A$1:$A$4,$A66:$B66,AQ$5:AQ$10,"#-36") -> #NAME? | AS66: =AO66-AQ66 -> #NAME? | AU66: =W66+AC66+AI66+AO66 -> #NAME? | AW66: =Y66+AE66+AK66+AQ66 -> #NAME? | AY66: =AU66-AW66 -> #NAME? | BA66: =+Q66-AO66 -> #NAME? | BC66: =+S66-AQ66 -> #NAME? | BE66: =BA66-BC66 -> #NAME? | BG66: =_xll.GetCtData("CO-AMOUNT","CONS-AMOUNT",$A$1:$A$4,$A66:$B66,BG$5:BG$10,"#-30") -> #NAME? | BI66: =_xll.GetCtData("CO-AMOUNT","CONS-AMOUNT",$A$1:$A$4,$A66:$B66,BI$5:BI$10,"#-32") -> #NAME? | BK66: =BG66-BI66 -> #NAME? | BN66: =_xll.GetCtData("CO-AMOUNT","CONS-AMOUNT",$A$1:$A$4,$A66:$B66,BN$5:BN$10,"#-7") -> #NAME? | BP66: =_xll.GetCtData("CO-AMOUNT","CONS-AMOUNT",$A$1:$A$4,$A66:$B66,BP$5:BP$10,"#-4") -> #NAME? | BR66: =BN66-BP66 -> #NAME?
A67: {OA=OA019O}+{OA=OA011} | B67: {RU=G-HDBNPPI}+{RU=P-HDBNPPI} | C67: FR | D67: =CHOOSE([6]Traduction!$A$2,[6]Traduction!$A62,[6]Traduction!$B62) -> o/w Coordination Team | E67: =_xll.GetCtData("CO-AMOUNT","CONS-AMOUNT",$A$1:$A$4,$A67:$B67,E$5:E$10,"#58,152") -> #NAME? | G67: =_xll.GetCtData("CO-AMOUNT","CONS-AMOUNT",$A$1:$A$4,$A67:$B67,G$5:G$10,"#58,963") -> #NAME? | I67: =E67-G67 -> #NAME? | K67: =_xll.GetCtData("CO-AMOUNT","CONS-AMOUNT",$A$1:$A$4,$A67:$B67,K$5:K$10,"#-148,28") -> #NAME? | M67: =_xll.GetCtData("CO-AMOUNT","CONS-AMOUNT",$A$1:$A$4,$A67:$B67,M$5:M$10,"#-22,5760000000001") -> #NAME? | O67: =K67-M67 -> #NAME? | Q67: =_xll.GetCtData("CO-AMOUNT","CONS-AMOUNT",$A$1:$A$4,$A67:$B67,Q$5:Q$10,"#-90,128") -> #NAME? | S67: =_xll.GetCtData("CO-AMOUNT","CONS-AMOUNT",$A$1:$A$4,$A67:$B67,S$5:S$10,"#36,387") -> #NAME? | U67: =Q67-S67 -> #NAME? | W67: =_xll.GetCtData("CO-AMOUNT","CONS-AMOUNT",$A$1:$A$4,$A67:$B67,W$5:W$10,"#") -> #NAME? | Y67: =_xll.GetCtData("CO-AMOUNT","CONS-AMOUNT",$A$1:$A$4,$A67:$B67,Y$5:Y$10,"#") -> #NAME? | AA67: =W67-Y67 -> #NAME? | AC67: =_xll.GetCtData("CO-AMOUNT","CONS-AMOUNT",$A$1:$A$4,$A67:$B67,AC$5:AC$10,"#") -> #NAME? | AE67: =_xll.GetCtData("CO-AMOUNT","CONS-AMOUNT",$A$1:$A$4,$A67:$B67,AE$5:AE$10,"#") -> #NAME? | AG67: =AC67-AE67 -> #NAME? | AI67: =_xll.GetCtData("CO-AMOUNT","CONS-AMOUNT",$A$1:$A$4,$A67:$B67,AI$5:AI$10,"#241,028") -> #NAME? | AK67: =_xll.GetCtData("CO-AMOUNT","CONS-AMOUNT",$A$1:$A$4,$A67:$B67,AK$5:AK$10,"#583,51") -> #NAME? | AM67: =AI67-AK67 -> #NAME? | AO67: =_xll.GetCtData("CO-AMOUNT","CONS-AMOUNT",$A$1:$A$4,$A67:$B67,AO$5:AO$10,"#") -> #NAME? | AQ67: =_xll.GetCtData("CO-AMOUNT","CONS-AMOUNT",$A$1:$A$4,$A67:$B67,AQ$5:AQ$10,"#") -> #NAME? | AS67: =AO67-AQ67 -> #NAME? | AU67: =W67+AC67+AI67+AO67 -> #NAME? | AW67: =Y67+AE67+AK67+AQ67 -> #NAME? | AY67: =AU67-AW67 -> #NAME? | BA67: =+Q67-AO67 -> #NAME? | BC67: =+S67-AQ67 -> #NAME? | BE67: =BA67-BC67 -> #NAME? | BG67: =_xll.GetCtData("CO-AMOUNT","CONS-AMOUNT",$A$1:$A$4,$A67:$B67,BG$5:BG$10,"#") -> #NAME? | BI67: =_xll.GetCtData("CO-AMOUNT","CONS-AMOUNT",$A$1:$A$4,$A67:$B67,BI$5:BI$10,"#") -> #NAME? | BK67: =BG67-BI67 -> #NAME? | BN67: =_xll.GetCtData("CO-AMOUNT","CONS-AMOUNT",$A$1:$A$4,$A67:$B67,BN$5:BN$10,"#") -> #NAME? | BP67: =_xll.GetCtData("CO-AMOUNT","CONS-AMOUNT",$A$1:$A$4,$A67:$B67,BP$5:BP$10,"#") -> #NAME? | BR67: =BN67-BP67 -> #NAME?
A68: {OA=OA070O}+{OA=OA071O}+{OA=OA073O}+{OA=OA072O} | B68: {RU=G-HDBNPPI}+{RU=P-HDBNPPI} | C68: FR | D68: =CHOOSE([6]Traduction!$A$2,[6]Traduction!$A79,[6]Traduction!$B79) -> o/w Holding BNPP RE | E68: =_xll.GetCtData("CO-AMOUNT","CONS-AMOUNT",$A$1:$A$4,$A68:$B68,E$5:E$10,"#") -> #NAME? | G68: =_xll.GetCtData("CO-AMOUNT","CONS-AMOUNT",$A$1:$A$4,$A68:$B68,G$5:G$10,"#") -> #NAME? | I68: =E68-G68 -> #NAME? | K68: =_xll.GetCtData("CO-AMOUNT","CONS-AMOUNT",$A$1:$A$4,$A68:$B68,K$5:K$10,"#") -> #NAME? | M68: =_xll.GetCtData("CO-AMOUNT","CONS-AMOUNT",$A$1:$A$4,$A68:$B68,M$5:M$10,"#") -> #NAME? | O68: =K68-M68 -> #NAME? | Q68: =_xll.GetCtData("CO-AMOUNT","CONS-AMOUNT",$A$1:$A$4,$A68:$B68,Q$5:Q$10,"#") -> #NAME? | S68: =_xll.GetCtData("CO-AMOUNT","CONS-AMOUNT",$A$1:$A$4,$A68:$B68,S$5:S$10,"#") -> #NAME? | U68: =Q68-S68 -> #NAME? | W68: =_xll.GetCtData("CO-AMOUNT","CONS-AMOUNT",$A$1:$A$4,$A68:$B68,W$5:W$10,"#") -> #NAME? | Y68: =_xll.GetCtData("CO-AMOUNT","CONS-AMOUNT",$A$1:$A$4,$A68:$B68,Y$5:Y$10,"#") -> #NAME? | AA68: =W68-Y68 -> #NAME? | AC68: =_xll.GetCtData("CO-AMOUNT","CONS-AMOUNT",$A$1:$A$4,$A68:$B68,AC$5:AC$10,"#") -> #NAME? | AE68: =_xll.GetCtData("CO-AMOUNT","CONS-AMOUNT",$A$1:$A$4,$A68:$B68,AE$5:AE$10,"#") -> #NAME? | AG68: =AC68-AE68 -> #NAME? | AI68: =_xll.GetCtData("CO-AMOUNT","CONS-AMOUNT",$A$1:$A$4,$A68:$B68,AI$5:AI$10,"#") -> #NAME? | AK68: =_xll.GetCtData("CO-AMOUNT","CONS-AMOUNT",$A$1:$A$4,$A68:$B68,AK$5:AK$10,"#") -> #NAME? | AM68: =AI68-AK68 -> #NAME? | AO68: =_xll.GetCtData("CO-AMOUNT","CONS-AMOUNT",$A$1:$A$4,$A68:$B68,AO$5:AO$10,"#") -> #NAME? | AQ68: =_xll.GetCtData("CO-AMOUNT","CONS-AMOUNT",$A$1:$A$4,$A68:$B68,AQ$5:AQ$10,"#") -> #NAME? | AS68: =AO68-AQ68 -> #NAME? | AU68: =W68+AC68+AI68+AO68 -> #NAME? | AW68: =Y68+AE68+AK68+AQ68 -> #NAME? | AY68: =AU68-AW68 -> #NAME? | BA68: =+Q68-AO68 -> #NAME? | BC68: =+S68-AQ68 -> #NAME? | BE68: =BA68-BC68 -> #NAME? | BG68: =_xll.GetCtData("CO-AMOUNT","CONS-AMOUNT",$A$1:$A$4,$A68:$B68,BG$5:BG$10,"#") -> #NAME? | BI68: =_xll.GetCtData("CO-AMOUNT","CONS-AMOUNT",$A$1:$A$4,$A68:$B68,BI$5:BI$10,"#") -> #NAME? | BK68: =BG68-BI68 -> #NAME? | BN68: =_xll.GetCtData("CO-AMOUNT","CONS-AMOUNT",$A$1:$A$4,$A68:$B68,BN$5:BN$10,"#") -> #NAME? | BP68: =_xll.GetCtData("CO-AMOUNT","CONS-AMOUNT",$A$1:$A$4,$A68:$B68,BP$5:BP$10,"#") -> #NAME? | BR68: =BN68-BP68 -> #NAME?
D69: Property Management | E69: =SUM(E70:E82)-E75 -> #NAME? | G69: =SUM(G70:G82)-G75 -> #NAME? | I69: =E69-G69 -> #NAME? | K69: =SUM(K70:K82)-K75 -> #NAME? | M69: =SUM(M70:M82)-M75 -> #NAME? | O69: =K69-M69 -> #NAME? | Q69: =SUM(Q70:Q82)-Q75 -> #NAME? | S69: =SUM(S70:S82)-S75 -> #NAME? | U69: =Q69-S69 -> #NAME? | W69: =SUM(W70:W82)-W75 -> #NAME? | Y69: =SUM(Y70:Y82)-Y75 -> #NAME? | AA69: =W69-Y69 -> #NAME? | AC69: =SUM(AC70:AC82)-AC75 -> #NAME? | AE69: =SUM(AE70:AE82)-AE75 -> #NAME? | AG69: =AC69-AE69 -> #NAME? | AI69: =SUM(AI70:AI82)-AI75 -> #NAME? | AK69: =SUM(AK70:AK82)-AK75 -> #NAME? | AM69: =AI69-AK69 -> #NAME? | AO69: =SUM(AO70:AO82)-AO75 -> #NAME? | AQ69: =SUM(AQ70:AQ82)-AQ75 -> #NAME? | AS69: =AO69-AQ69 -> #NAME? | AU69: =W69+AC69+AI69+AO69 -> #NAME? | AW69: =Y69+AE69+AK69+AQ69 -> #NAME? | AY69: =AU69-AW69 -> #NAME? | BA69: =+Q69-AO69 -> #NAME? | BC69: =+S69-AQ69 -> #NAME? | BE69: =BA69-BC69 -> #NAME? | BG69: =SUM(BG70:BG82)-BG75-#REF! -> #NAME? | BI69: =SUM(BI70:BI82)-BI75-#REF! -> #NAME? | BK69: =BG69-BI69 -> #NAME? | BN69: =SUM(BN70:BN82)-BN75-#REF! -> #NAME? | BP69: =SUM(BP70:BP82)-BP75-#REF! -> #NAME? | BR69: =BN69-BP69 -> #NAME?
A70: {OA=OA030}+{OA=OA031}+{OA=OA030E}+{OA=OA030O} | B70: {RU=G-CENTRAL}+{RU=P-CENTRAL} | C70: CENTRAL | D70: G-central | E70: =_xll.GetCtData("CO-AMOUNT","CONS-AMOUNT",$A$1:$A$4,$A70:$B70,E$5:E$10,"#") -> #NAME? | G70: =_xll.GetCtData("CO-AMOUNT","CONS-AMOUNT",$A$1:$A$4,$A70:$B70,G$5:G$10,"#") -> #NAME? | I70: =E70-G70 -> #NAME? | K70: =_xll.GetCtData("CO-AMOUNT","CONS-AMOUNT",$A$1:$A$4,$A70:$B70,K$5:K$10,"#") -> #NAME? | M70: =_xll.GetCtData("CO-AMOUNT","CONS-AMOUNT",$A$1:$A$4,$A70:$B70,M$5:M$10,"#") -> #NAME? | O70: =K70-M70 -> #NAME? | Q70: =_xll.GetCtData("CO-AMOUNT","CONS-AMOUNT",$A$1:$A$4,$A70:$B70,Q$5:Q$10,"#") -> #NAME? | S70: =_xll.GetCtData("CO-AMOUNT","CONS-AMOUNT",$A$1:$A$4,$A70:$B70,S$5:S$10,"#") -> #NAME? | U70: =Q70-S70 -> #NAME? | W70: =_xll.GetCtData("CO-AMOUNT","CONS-AMOUNT",$A$1:$A$4,$A70:$B70,W$5:W$10,"#") -> #NAME? | Y70: =_xll.GetCtData("CO-AMOUNT","CONS-AMOUNT",$A$1:$A$4,$A70:$B70,Y$5:Y$10,"#") -> #NAME? | AA70: =W70-Y70 -> #NAME? | AC70: =_xll.GetCtData("CO-AMOUNT","CONS-AMOUNT",$A$1:$A$4,$A70:$B70,AC$5:AC$10,"#") -> #NAME? | AE70: =_xll.GetCtData("CO-AMOUNT","CONS-AMOUNT",$A$1:$A$4,$A70:$B70,AE$5:AE$10,"#") -> #NAME? | AG70: =AC70-AE70 -> #NAME? | AI70: =_xll.GetCtData("CO-AMOUNT","CONS-AMOUNT",$A$1:$A$4,$A70:$B70,AI$5:AI$10,"#") -> #NAME? | AK70: =_xll.GetCtData("CO-AMOUNT","CONS-AMOUNT",$A$1:$A$4,$A70:$B70,AK$5:AK$10,"#") -> #NAME? | AM70: =AI70-AK70 -> #NAME? | AO70: =_xll.GetCtData("CO-AMOUNT","CONS-AMOUNT",$A$1:$A$4,$A70:$B70,AO$5:AO$10,"#") -> #NAME? | AQ70: =_xll.GetCtData("CO-AMOUNT","CONS-AMOUNT",$A$1:$A$4,$A70:$B70,AQ$5:AQ$10,"#") -> #NAME? | AS70: =AO70-AQ70 -> #NAME? | AU70: =W70+AC70+AI70+AO70 -> #NAME? | AW70: =Y70+AE70+AK70+AQ70 -> #NAME? | AY70: =AU70-AW70 -> #NAME? | BA70: =+Q70-AO70 -> #NAME? | BC70: =+S70-AQ70 -> #NAME? | BE70: =BA70-BC70 -> #NAME? | BG70: =_xll.GetCtData("CO-AMOUNT","CONS-AMOUNT",$A$1:$A$4,$A70:$B70,BG$5:BG$10,"#") -> #NAME? | BI70: =_xll.GetCtData("CO-AMOUNT","CONS-AMOUNT",$A$1:$A$4,$A70:$B70,BI$5:BI$10,"#") -> #NAME? | BK70: =BG70-BI70 -> #NAME? | BN70: =_xll.GetCtData("CO-AMOUNT","CONS-AMOUNT",$A$1:$A$4,$A70:$B70,BN$5:BN$10,"#") -> #NAME? | BP70: =_xll.GetCtData("CO-AMOUNT","CONS-AMOUNT",$A$1:$A$4,$A70:$B70,BP$5:BP$10,"#") -> #NAME? | BR70: =BN70-BP70 -> #NAME?
A71: {OA=OA031}+{OA=OA031O} | B71: {RU=G-FRMP}+{RU=P-FRMP} | C71: FR | D71: =CHOOSE([6]Traduction!$A$2,[6]Traduction!$A80,[6]Traduction!$B80) -> o/w Holding PM (incl. PDI) | E71: =_xll.GetCtData("CO-AMOUNT","CONS-AMOUNT",$A$1:$A$4,$A71:$B71,E$5:E$10,"#") -> #NAME? | G71: =_xll.GetCtData("CO-AMOUNT","CONS-AMOUNT",$A$1:$A$4,$A71:$B71,G$5:G$10,"#") -> #NAME? | I71: =E71-G71 -> #NAME? | K71: =_xll.GetCtData("CO-AMOUNT","CONS-AMOUNT",$A$1:$A$4,$A71:$B71,K$5:K$10,"#-598,595") -> #NAME? | M71: =_xll.GetCtData("CO-AMOUNT","CONS-AMOUNT",$A$1:$A$4,$A71:$B71,M$5:M$10,"#-516,538") -> #NAME? | O71: =K71-M71 -> #NAME? | Q71: =_xll.GetCtData("CO-AMOUNT","CONS-AMOUNT",$A$1:$A$4,$A71:$B71,Q$5:Q$10,"#-598,595") -> #NAME? | S71: =_xll.GetCtData("CO-AMOUNT","CONS-AMOUNT",$A$1:$A$4,$A71:$B71,S$5:S$10,"#-516,538") -> #NAME? | U71: =Q71-S71 -> #NAME? | W71: =_xll.GetCtData("CO-AMOUNT","CONS-AMOUNT",$A$1:$A$4,$A71:$B71,W$5:W$10,"#-25") -> #NAME? | Y71: =_xll.GetCtData("CO-AMOUNT","CONS-AMOUNT",$A$1:$A$4,$A71:$B71,Y$5:Y$10,"#-25") -> #NAME? | AA71: =W71-Y71 -> #NAME? | AC71: =_xll.GetCtData("CO-AMOUNT","CONS-AMOUNT",$A$1:$A$4,$A71:$B71,AC$5:AC$10,"#") -> #NAME? | AE71: =_xll.GetCtData("CO-AMOUNT","CONS-AMOUNT",$A$1:$A$4,$A71:$B71,AE$5:AE$10,"#") -> #NAME? | AG71: =AC71-AE71 -> #NAME? | AI71: =_xll.GetCtData("CO-AMOUNT","CONS-AMOUNT",$A$1:$A$4,$A71:$B71,AI$5:AI$10,"#") -> #NAME? | AK71: =_xll.GetCtData("CO-AMOUNT","CONS-AMOUNT",$A$1:$A$4,$A71:$B71,AK$5:AK$10,"#") -> #NAME? | AM71: =AI71-AK71 -> #NAME? | AO71: =_xll.GetCtData("CO-AMOUNT","CONS-AMOUNT",$A$1:$A$4,$A71:$B71,AO$5:AO$10,"#") -> #NAME? | AQ71: =_xll.GetCtData("CO-AMOUNT","CONS-AMOUNT",$A$1:$A$4,$A71:$B71,AQ$5:AQ$10,"#") -> #NAME? | AS71: =AO71-AQ71 -> #NAME? | AU71: =W71+AC71+AI71+AO71 -> #NAME? | AW71: =Y71+AE71+AK71+AQ71 -> #NAME? | AY71: =AU71-AW71 -> #NAME? | BA71: =+Q71-AO71 -> #NAME? | BC71: =+S71-AQ71 -> #NAME? | BE71: =BA71-BC71 -> #NAME? | BG71: =_xll.GetCtData("CO-AMOUNT","CONS-AMOUNT",$A$1:$A$4,$A71:$B71,BG$5:BG$10,"#") -> #NAME? | BI71: =_xll.GetCtData("CO-AMOUNT","CONS-AMOUNT",$A$1:$A$4,$A71:$B71,BI$5:BI$10,"#") -> #NAME? | BK71: =BG71-BI71 -> #NAME? | BN71: =_xll.GetCtData("CO-AMOUNT","CONS-AMOUNT",$A$1:$A$4,$A71:$B71,BN$5:BN$10,"#") -> #NAME? | BP71: =_xll.GetCtData("CO-AMOUNT","CONS-AMOUNT",$A$1:$A$4,$A71:$B71,BP$5:BP$10,"#") -> #NAME? | BR71: =BN71-BP71 -> #NAME?
A72: {OA=OA030}+{OA=OA030E}+{OA=OA030O} | B72: {RU=G-FRMP}+{RU=P-FRMP} | C72: FR | D72: =CHOOSE([6]Traduction!$A$2,[6]Traduction!$A45,[6]Traduction!$B45) -> o/w France | E72: =_xll.GetCtData("CO-AMOUNT","CONS-AMOUNT",$A$1:$A$4,$A72:$B72,E$5:E$10,"#13315,219") -> #NAME? | G72: =_xll.GetCtData("CO-AMOUNT","CONS-AMOUNT",$A$1:$A$4,$A72:$B72,G$5:G$10,"#13917,906") -> #NAME? | I72: =E72-G72 -> #NAME? | K72: =_xll.GetCtData("CO-AMOUNT","CONS-AMOUNT",$A$1:$A$4,$A72:$B72,K$5:K$10,"#-11737,948") -> #NAME? | M72: =_xll.GetCtData("CO-AMOUNT","CONS-AMOUNT",$A$1:$A$4,$A72:$B72,M$5:M$10,"#-11976,098") -> #NAME? | O72: =K72-M72 -> #NAME? | Q72: =_xll.GetCtData("CO-AMOUNT","CONS-AMOUNT",$A$1:$A$4,$A72:$B72,Q$5:Q$10,"#1623,002") -> #NAME? | S72: =_xll.GetCtData("CO-AMOUNT","CONS-AMOUNT",$A$1:$A$4,$A72:$B72,S$5:S$10,"#1841,808") -> #NAME? | U72: =Q72-S72 -> #NAME? | W72: =_xll.GetCtData("CO-AMOUNT","CONS-AMOUNT",$A$1:$A$4,$A72:$B72,W$5:W$10,"#") -> #NAME? | Y72: =_xll.GetCtData("CO-AMOUNT","CONS-AMOUNT",$A$1:$A$4,$A72:$B72,Y$5:Y$10,"#") -> #NAME? | AA72: =W72-Y72 -> #NAME? | AC72: =_xll.GetCtData("CO-AMOUNT","CONS-AMOUNT",$A$1:$A$4,$A72:$B72,AC$5:AC$10,"#") -> #NAME? | AE72: =_xll.GetCtData("CO-AMOUNT","CONS-AMOUNT",$A$1:$A$4,$A72:$B72,AE$5:AE$10,"#") -> #NAME? | AG72: =AC72-AE72 -> #NAME? | AI72: =_xll.GetCtData("CO-AMOUNT","CONS-AMOUNT",$A$1:$A$4,$A72:$B72,AI$5:AI$10,"#") -> #NAME? | AK72: =_xll.GetCtData("CO-AMOUNT","CONS-AMOUNT",$A$1:$A$4,$A72:$B72,AK$5:AK$10,"#") -> #NAME? | AM72: =AI72-AK72 -> #NAME? | AO72: =_xll.GetCtData("CO-AMOUNT","CONS-AMOUNT",$A$1:$A$4,$A72:$B72,AO$5:AO$10,"#-2542,589") -> #NAME? | AQ72: =_xll.GetCtData("CO-AMOUNT","CONS-AMOUNT",$A$1:$A$4,$A72:$B72,AQ$5:AQ$10,"#-2543,758") -> #NAME? | AS72: =AO72-AQ72 -> #NAME? | AU72: =W72+AC72+AI72+AO72 -> #NAME? | AW72: =Y72+AE72+AK72+AQ72 -> #NAME? | AY72: =AU72-AW72 -> #NAME? | BA72: =+Q72-AO72 -> #NAME? | BC72: =+S72-AQ72 -> #NAME? | BE72: =BA72-BC72 -> #NAME? | BG72: =_xll.GetCtData("CO-AMOUNT","CONS-AMOUNT",$A$1:$A$4,$A72:$B72,BG$5:BG$10,"#-2423,781") -> #NAME? | BI72: =_xll.GetCtData("CO-AMOUNT","CONS-AMOUNT",$A$1:$A$4,$A72:$B72,BI$5:BI$10,"#-2423,781") -> #NAME? | BK72: =BG72-BI72 -> #NAME? | BN72: =_xll.GetCtData("CO-AMOUNT","CONS-AMOUNT",$A$1:$A$4,$A72:$B72,BN$5:BN$10,"#-118,808") -> #NAME? | BP72: =_xll.GetCtData("CO-AMOUNT","CONS-AMOUNT",$A$1:$A$4,$A72:$B72,BP$5:BP$10,"#-119,977") -> #NAME? | BR72: =BN72-BP72 -> #NAME?
A73: {OA=OA030}+{OA=OA031}+{OA=OA030E}+{OA=OA030O} | B73: {RU=G-DE}+{RU=P-DE}+{RU=P-IMOPLAN} | C73: DE | D73: =CHOOSE([6]Traduction!$A$2,[6]Traduction!$A49,[6]Traduction!$B49) -> o/w Germany | E73: =_xll.GetCtData("CO-AMOUNT","CONS-AMOUNT",$A$1:$A$4,$A73:$B73,E$5:E$10,"#4242,655") -> #NAME? | G73: =_xll.GetCtData("CO-AMOUNT","CONS-AMOUNT",$A$1:$A$4,$A73:$B73,G$5:G$10,"#3889,312") -> #NAME? | I73: =E73-G73 -> #NAME? | K73: =_xll.GetCtData("CO-AMOUNT","CONS-AMOUNT",$A$1:$A$4,$A73:$B73,K$5:K$10,"#-5205,301") -> #NAME? | M73: =_xll.GetCtData("CO-AMOUNT","CONS-AMOUNT",$A$1:$A$4,$A73:$B73,M$5:M$10,"#-5280,153") -> #NAME? | O73: =K73-M73 -> #NAME? | Q73: =_xll.GetCtData("CO-AMOUNT","CONS-AMOUNT",$A$1:$A$4,$A73:$B73,Q$5:Q$10,"#-972,2") -> #NAME? | S73: =_xll.GetCtData("CO-AMOUNT","CONS-AMOUNT",$A$1:$A$4,$A73:$B73,S$5:S$10,"#-1390,97") -> #NAME? | U73: =Q73-S73 -> #NAME? | W73: =_xll.GetCtData("CO-AMOUNT","CONS-AMOUNT",$A$1:$A$4,$A73:$B73,W$5:W$10,"#") -> #NAME? | Y73: =_xll.GetCtData("CO-AMOUNT","CONS-AMOUNT",$A$1:$A$4,$A73:$B73,Y$5:Y$10,"#") -> #NAME? | AA73: =W73-Y73 -> #NAME? | AC73: =_xll.GetCtData("CO-AMOUNT","CONS-AMOUNT",$A$1:$A$4,$A73:$B73,AC$5:AC$10,"#") -> #NAME? | AE73: =_xll.GetCtData("CO-AMOUNT","CONS-AMOUNT",$A$1:$A$4,$A73:$B73,AE$5:AE$10,"#") -> #NAME? | AG73: =AC73-AE73 -> #NAME? | AI73: =_xll.GetCtData("CO-AMOUNT","CONS-AMOUNT",$A$1:$A$4,$A73:$B73,AI$5:AI$10,"#") -> #NAME? | AK73: =_xll.GetCtData("CO-AMOUNT","CONS-AMOUNT",$A$1:$A$4,$A73:$B73,AK$5:AK$10,"#") -> #NAME? | AM73: =AI73-AK73 -> #NAME? | AO73: =_xll.GetCtData("CO-AMOUNT","CONS-AMOUNT",$A$1:$A$4,$A73:$B73,AO$5:AO$10,"#-222,344") -> #NAME? | AQ73: =_xll.GetCtData("CO-AMOUNT","CONS-AMOUNT",$A$1:$A$4,$A73:$B73,AQ$5:AQ$10,"#-222,475") -> #NAME? | AS73: =AO73-AQ73 -> #NAME? | AU73: =W73+AC73+AI73+AO73 -> #NAME? | AW73: =Y73+AE73+AK73+AQ73 -> #NAME? | AY73: =AU73-AW73 -> #NAME? | BA73: =+Q73-AO73 -> #NAME? | BC73: =+S73-AQ73 -> #NAME? | BE73: =BA73-BC73 -> #NAME? | BG73: =_xll.GetCtData("CO-AMOUNT","CONS-AMOUNT",$A$1:$A$4,$A73:$B73,BG$5:BG$10,"#-166,142") -> #NAME? | BI73: =_xll.GetCtData("CO-AMOUNT","CONS-AMOUNT",$A$1:$A$4,$A73:$B73,BI$5:BI$10,"#-166,143") -> #NAME? | BK73: =BG73-BI73 -> #NAME? | BN73: =_xll.GetCtData("CO-AMOUNT","CONS-AMOUNT",$A$1:$A$4,$A73:$B73,BN$5:BN$10,"#-56,202") -> #NAME? | BP73: =_xll.GetCtData("CO-AMOUNT","CONS-AMOUNT",$A$1:$A$4,$A73:$B73,BP$5:BP$10,"#-56,332") -> #NAME? | BR73: =BN73-BP73 -> #NAME?
A74: {OA=OA020}+{OA=OA022}+{OA=OA030}+{OA=OA030O}+{OA=OA071O} | B74: {RU=G-UK}+{RU=P-UK}+{RU=G-UKSP}+{RU=G-UKPROMO} | C74: UK | D74: =CHOOSE([6]Traduction!$A$2,[6]Traduction!$A52,[6]Traduction!$B52) -> o/w UK | E74: =_xll.GetCtData("CO-AMOUNT","CONS-AMOUNT",$A$1:$A$4,$A74:$B74,E$5:E$10,"#11175,8934524405") -> #NAME? | G74: =_xll.GetCtData("CO-AMOUNT","CONS-AMOUNT",$A$1:$A$4,$A74:$B74,G$5:G$10,"#10897,0468629567") -> #NAME? | I74: =E74-G74 -> #NAME? | K74: =_xll.GetCtData("CO-AMOUNT","CONS-AMOUNT",$A$1:$A$4,$A74:$B74,K$5:K$10,"#-10427,9395046785") -> #NAME? | M74: =_xll.GetCtData("CO-AMOUNT","CONS-AMOUNT",$A$1:$A$4,$A74:$B74,M$5:M$10,"#-10642,0361559061") -> #NAME? | O74: =K74-M74 -> #NAME? | Q74: =_xll.GetCtData("CO-AMOUNT","CONS-AMOUNT",$A$1:$A$4,$A74:$B74,Q$5:Q$10,"#649,274009260109") -> #NAME? | S74: =_xll.GetCtData("CO-AMOUNT","CONS-AMOUNT",$A$1:$A$4,$A74:$B74,S$5:S$10,"#252,581660170337") -> #NAME? | U74: =Q74-S74 -> #NAME? | W74: =_xll.GetCtData("CO-AMOUNT","CONS-AMOUNT",$A$1:$A$4,$A74:$B74,W$5:W$10,"#") -> #NAME? | Y74: =_xll.GetCtData("CO-AMOUNT","CONS-AMOUNT",$A$1:$A$4,$A74:$B74,Y$5:Y$10,"#") -> #NAME? | AA74: =W74-Y74 -> #NAME? | AC74: =_xll.GetCtData("CO-AMOUNT","CONS-AMOUNT",$A$1:$A$4,$A74:$B74,AC$5:AC$10,"#") -> #NAME? | AE74: =_xll.GetCtData("CO-AMOUNT","CONS-AMOUNT",$A$1:$A$4,$A74:$B74,AE$5:AE$10,"#") -> #NAME? | AG74: =AC74-AE74 -> #NAME? | AI74: =_xll.GetCtData("CO-AMOUNT","CONS-AMOUNT",$A$1:$A$4,$A74:$B74,AI$5:AI$10,"#") -> #NAME? | AK74: =_xll.GetCtData("CO-AMOUNT","CONS-AMOUNT",$A$1:$A$4,$A74:$B74,AK$5:AK$10,"#") -> #NAME? | AM74: =AI74-AK74 -> #NAME? | AO74: =_xll.GetCtData("CO-AMOUNT","CONS-AMOUNT",$A$1:$A$4,$A74:$B74,AO$5:AO$10,"#-589,495277082831") -> #NAME? | AQ74: =_xll.GetCtData("CO-AMOUNT","CONS-AMOUNT",$A$1:$A$4,$A74:$B74,AQ$5:AQ$10,"#-690,784716201276") -> #NAME? | AS74: =AO74-AQ74 -> #NAME? | AU74: =W74+AC74+AI74+AO74 -> #NAME? | AW74: =Y74+AE74+AK74+AQ74 -> #NAME? | AY74: =AU74-AW74 -> #NAME? | BA74: =+Q74-AO74 -> #NAME? | BC74: =+S74-AQ74 -> #NAME? | BE74: =BA74-BC74 -> #NAME? | BG74: =_xll.GetCtData("CO-AMOUNT","CONS-AMOUNT",$A$1:$A$4,$A74:$B74,BG$5:BG$10,"#-413,70392965595") -> #NAME? | BI74: =_xll.GetCtData("CO-AMOUNT","CONS-AMOUNT",$A$1:$A$4,$A74:$B74,BI$5:BI$10,"#-511,269385955276") -> #NAME? | BK74: =BG74-BI74 -> #NAME? | BN74: =_xll.GetCtData("CO-AMOUNT","CONS-AMOUNT",$A$1:$A$4,$A74:$B74,BN$5:BN$10,"#-175,791347426881") -> #NAME? | BP74: =_xll.GetCtData("CO-AMOUNT","CONS-AMOUNT",$A$1:$A$4,$A74:$B74,BP$5:BP$10,"#-179,515330245999") -> #NAME? | BR74: =BN74-BP74 -> #NAME?
A75: {OA=OA020}+{OA=OA022}+{OA=OA030}+{OA=OA030O}+{OA=OA071O} | B75: {RU=G-UK}+{RU=P-UK}+{RU=G-UKSP}+{RU=G-UKPROMO} | C75: UK GBP | D75: UK (GBP) | E75: =_xll.GetCtData("CO-AMOUNT","AMOUNT",$A$1:$A$4,$A75:$B75,E$5:E$10,"#9704,052") -> #NAME? | G75: =_xll.GetCtData("CO-AMOUNT","AMOUNT",$A$1:$A$4,$A75:$B75,G$5:G$10,"#9447,813") -> #NAME? | I75: =E75-G75 -> #NAME? | K75: =_xll.GetCtData("CO-AMOUNT","AMOUNT",$A$1:$A$4,$A75:$B75,K$5:K$10,"#-9054,602") -> #NAME? | M75: =_xll.GetCtData("CO-AMOUNT","AMOUNT",$A$1:$A$4,$A75:$B75,M$5:M$10,"#-9226,717") -> #NAME? | O75: =K75-M75 -> #NAME? | Q75: =_xll.GetCtData("CO-AMOUNT","AMOUNT",$A$1:$A$4,$A75:$B75,Q$5:Q$10,"#563,766000000001") -> #NAME? | S75: =_xll.GetCtData("CO-AMOUNT","AMOUNT",$A$1:$A$4,$A75:$B75,S$5:S$10,"#218,990000000002") -> #NAME? | U75: =Q75-S75 -> #NAME? | W75: =_xll.GetCtData("CO-AMOUNT","AMOUNT",$A$1:$A$4,$A75:$B75,W$5:W$10,"#") -> #NAME? | Y75: =_xll.GetCtData("CO-AMOUNT","AMOUNT",$A$1:$A$4,$A75:$B75,Y$5:Y$10,"#") -> #NAME? | AA75: =W75-Y75 -> #NAME? | AC75: =_xll.GetCtData("CO-AMOUNT","AMOUNT",$A$1:$A$4,$A75:$B75,AC$5:AC$10,"#") -> #NAME? | AE75: =_xll.GetCtData("CO-AMOUNT","AMOUNT",$A$1:$A$4,$A75:$B75,AE$5:AE$10,"#") -> #NAME? | AG75: =AC75-AE75 -> #NAME? | AI75: =_xll.GetCtData("CO-AMOUNT","AMOUNT",$A$1:$A$4,$A75:$B75,AI$5:AI$10,"#") -> #NAME? | AK75: =_xll.GetCtData("CO-AMOUNT","AMOUNT",$A$1:$A$4,$A75:$B75,AK$5:AK$10,"#") -> #NAME? | AM75: =AI75-AK75 -> #NAME? | AO75: =_xll.GetCtData("CO-AMOUNT","AMOUNT",$A$1:$A$4,$A75:$B75,AO$5:AO$10,"#-511,86") -> #NAME? | AQ75: =_xll.GetCtData("CO-AMOUNT","AMOUNT",$A$1:$A$4,$A75:$B75,AQ$5:AQ$10,"#-598,915") -> #NAME? | AS75: =AO75-AQ75 -> #NAME? | AU75: =W75+AC75+AI75+AO75 -> #NAME? | AW75: =Y75+AE75+AK75+AQ75 -> #NAME? | AY75: =AU75-AW75 -> #NAME? | BA75: =+Q75-AO75 -> #NAME? | BC75: =+S75-AQ75 -> #NAME? | BE75: =BA75-BC75 -> #NAME? | BG75: =_xll.GetCtData("CO-AMOUNT","AMOUNT",$A$1:$A$4,$A75:$B75,BG$5:BG$10,"#-359,22") -> #NAME? | BI75: =_xll.GetCtData("CO-AMOUNT","AMOUNT",$A$1:$A$4,$A75:$B75,BI$5:BI$10,"#-443,274") -> #NAME? | BK75: =BG75-BI75 -> #NAME? | BN75: =_xll.GetCtData("CO-AMOUNT","AMOUNT",$A$1:$A$4,$A75:$B75,BN$5:BN$10,"#-152,64") -> #NAME? | BP75: =_xll.GetCtData("CO-AMOUNT","AMOUNT",$A$1:$A$4,$A75:$B75,BP$5:BP$10,"#-155,641") -> #NAME? | BR75: =BN75-BP75 -> #NAME?
A76: {OA=OA030}+{OA=OA031}+{OA=OA030E}+{OA=OA030O} | B76: RU sum AF026 | C76: ITA | D76: =CHOOSE([6]Traduction!$A$2,[6]Traduction!$A46,[6]Traduction!$B46) -> o/w Italy | E76: =_xll.GetCtData("CO-AMOUNT","CONS-AMOUNT",$A$1:$A$4,$A76:$B76,E$5:E$10,"#1792,964") -> #NAME? | G76: =_xll.GetCtData("CO-AMOUNT","CONS-AMOUNT",$A$1:$A$4,$A76:$B76,G$5:G$10,"#1800,925") -> #NAME? | I76: =E76-G76 -> #NAME? | K76: =_xll.GetCtData("CO-AMOUNT","CONS-AMOUNT",$A$1:$A$4,$A76:$B76,K$5:K$10,"#-2480,737") -> #NAME? | M76: =_xll.GetCtData("CO-AMOUNT","CONS-AMOUNT",$A$1:$A$4,$A76:$B76,M$5:M$10,"#-2481,493") -> #NAME? | O76: =K76-M76 -> #NAME? | Q76: =_xll.GetCtData("CO-AMOUNT","CONS-AMOUNT",$A$1:$A$4,$A76:$B76,Q$5:Q$10,"#-689,275") -> #NAME? | S76: =_xll.GetCtData("CO-AMOUNT","CONS-AMOUNT",$A$1:$A$4,$A76:$B76,S$5:S$10,"#-680,568") -> #NAME? | U76: =Q76-S76 -> #NAME? | W76: =_xll.GetCtData("CO-AMOUNT","CONS-AMOUNT",$A$1:$A$4,$A76:$B76,W$5:W$10,"#") -> #NAME? | Y76: =_xll.GetCtData("CO-AMOUNT","CONS-AMOUNT",$A$1:$A$4,$A76:$B76,Y$5:Y$10,"#") -> #NAME? | AA76: =W76-Y76 -> #NAME? | AC76: =_xll.GetCtData("CO-AMOUNT","CONS-AMOUNT",$A$1:$A$4,$A76:$B76,AC$5:AC$10,"#") -> #NAME? | AE76: =_xll.GetCtData("CO-AMOUNT","CONS-AMOUNT",$A$1:$A$4,$A76:$B76,AE$5:AE$10,"#") -> #NAME? | AG76: =AC76-AE76 -> #NAME? | AI76: =_xll.GetCtData("CO-AMOUNT","CONS-AMOUNT",$A$1:$A$4,$A76:$B76,AI$5:AI$10,"#") -> #NAME? | AK76: =_xll.GetCtData("CO-AMOUNT","CONS-AMOUNT",$A$1:$A$4,$A76:$B76,AK$5:AK$10,"#") -> #NAME? | AM76: =AI76-AK76 -> #NAME? | AO76: =_xll.GetCtData("CO-AMOUNT","CONS-AMOUNT",$A$1:$A$4,$A76:$B76,AO$5:AO$10,"#-97,946") -> #NAME? | AQ76: =_xll.GetCtData("CO-AMOUNT","CONS-AMOUNT",$A$1:$A$4,$A76:$B76,AQ$5:AQ$10,"#-97,948") -> #NAME? | AS76: =AO76-AQ76 -> #NAME? | AU76: =W76+AC76+AI76+AO76 -> #NAME? | AW76: =Y76+AE76+AK76+AQ76 -> #NAME? | AY76: =AU76-AW76 -> #NAME? | BA76: =+Q76-AO76 -> #NAME? | BC76: =+S76-AQ76 -> #NAME? | BE76: =BA76-BC76 -> #NAME? | BG76: =_xll.GetCtData("CO-AMOUNT","CONS-AMOUNT",$A$1:$A$4,$A76:$B76,BG$5:BG$10,"#-77,733") -> #NAME? | BI76: =_xll.GetCtData("CO-AMOUNT","CONS-AMOUNT",$A$1:$A$4,$A76:$B76,BI$5:BI$10,"#-77,733") -> #NAME? | BK76: =BG76-BI76 -> #NAME? | BN76: =_xll.GetCtData("CO-AMOUNT","CONS-AMOUNT",$A$1:$A$4,$A76:$B76,BN$5:BN$10,"#-20,213") -> #NAME? | BP76: =_xll.GetCtData("CO-AMOUNT","CONS-AMOUNT",$A$1:$A$4,$A76:$B76,BP$5:BP$10,"#-20,215") -> #NAME? | BR76: =BN76-BP76 -> #NAME?
A77: {OA=OA030}+{OA=OA031}+{OA=OA030E}+{OA=OA030O} | B77: {RU=G-BE}+{RU=P-BE} | C77: BEL | D77: =CHOOSE([6]Traduction!$A$2,[6]Traduction!$A66,[6]Traduction!$B66) -> o/w Belgium | E77: =_xll.GetCtData("CO-AMOUNT","CONS-AMOUNT",$A$1:$A$4,$A77:$B77,E$5:E$10,"#3470") -> #NAME? | G77: =_xll.GetCtData("CO-AMOUNT","CONS-AMOUNT",$A$1:$A$4,$A77:$B77,G$5:G$10,"#3444,916") -> #NAME? | I77: =E77-G77 -> #NAME? | K77: =_xll.GetCtData("CO-AMOUNT","CONS-AMOUNT",$A$1:$A$4,$A77:$B77,K$5:K$10,"#-2700,185") -> #NAME? | M77: =_xll.GetCtData("CO-AMOUNT","CONS-AMOUNT",$A$1:$A$4,$A77:$B77,M$5:M$10,"#-2907,01") -> #NAME? | O77: =K77-M77 -> #NAME? | Q77: =_xll.GetCtData("CO-AMOUNT","CONS-AMOUNT",$A$1:$A$4,$A77:$B77,Q$5:Q$10,"#808,815") -> #NAME? | S77: =_xll.GetCtData("CO-AMOUNT","CONS-AMOUNT",$A$1:$A$4,$A77:$B77,S$5:S$10,"#537,906") -> #NAME? | U77: =Q77-S77 -> #NAME? | W77: =_xll.GetCtData("CO-AMOUNT","CONS-AMOUNT",$A$1:$A$4,$A77:$B77,W$5:W$10,"#") -> #NAME? | Y77: =_xll.GetCtData("CO-AMOUNT","CONS-AMOUNT",$A$1:$A$4,$A77:$B77,Y$5:Y$10,"#") -> #NAME? | AA77: =W77-Y77 -> #NAME? | AC77: =_xll.GetCtData("CO-AMOUNT","CONS-AMOUNT",$A$1:$A$4,$A77:$B77,AC$5:AC$10,"#") -> #NAME? | AE77: =_xll.GetCtData("CO-AMOUNT","CONS-AMOUNT",$A$1:$A$4,$A77:$B77,AE$5:AE$10,"#") -> #NAME? | AG77: =AC77-AE77 -> #NAME? | AI77: =_xll.GetCtData("CO-AMOUNT","CONS-AMOUNT",$A$1:$A$4,$A77:$B77,AI$5:AI$10,"#") -> #NAME? | AK77: =_xll.GetCtData("CO-AMOUNT","CONS-AMOUNT",$A$1:$A$4,$A77:$B77,AK$5:AK$10,"#") -> #NAME? | AM77: =AI77-AK77 -> #NAME? | AO77: =_xll.GetCtData("CO-AMOUNT","CONS-AMOUNT",$A$1:$A$4,$A77:$B77,AO$5:AO$10,"#-125") -> #NAME? | AQ77: =_xll.GetCtData("CO-AMOUNT","CONS-AMOUNT",$A$1:$A$4,$A77:$B77,AQ$5:AQ$10,"#-120,02") -> #NAME? | AS77: =AO77-AQ77 -> #NAME? | AU77: =W77+AC77+AI77+AO77 -> #NAME? | AW77: =Y77+AE77+AK77+AQ77 -> #NAME? | AY77: =AU77-AW77 -> #NAME? | BA77: =+Q77-AO77 -> #NAME? | BC77: =+S77-AQ77 -> #NAME? | BE77: =BA77-BC77 -> #NAME? | BG77: =_xll.GetCtData("CO-AMOUNT","CONS-AMOUNT",$A$1:$A$4,$A77:$B77,BG$5:BG$10,"#-93") -> #NAME? | BI77: =_xll.GetCtData("CO-AMOUNT","CONS-AMOUNT",$A$1:$A$4,$A77:$B77,BI$5:BI$10,"#-92,44") -> #NAME? | BK77: =BG77-BI77 -> #NAME? | BN77: =_xll.GetCtData("CO-AMOUNT","CONS-AMOUNT",$A$1:$A$4,$A77:$B77,BN$5:BN$10,"#-32") -> #NAME? | BP77: =_xll.GetCtData("CO-AMOUNT","CONS-AMOUNT",$A$1:$A$4,$A77:$B77,BP$5:BP$10,"#-27,58") -> #NAME? | BR77: =BN77-BP77 -> #NAME?
A78: {OA=OA030}+{OA=OA031}+{OA=OA030E}+{OA=OA030O} | B78: {RU=G-POL}+{RU=P-POL} | C78: POL | D78: =CHOOSE([6]Traduction!$A$2,[6]Traduction!$A76,[6]Traduction!$B76) -> o/w Poland | E78: =_xll.GetCtData("CO-AMOUNT","CONS-AMOUNT",$A$1:$A$4,$A78:$B78,E$5:E$10,"#860,147028570612") -> #NAME? | G78: =_xll.GetCtData("CO-AMOUNT","CONS-AMOUNT",$A$1:$A$4,$A78:$B78,G$5:G$10,"#902,366947235987") -> #NAME? | I78: =E78-G78 -> #NAME? | K78: =_xll.GetCtData("CO-AMOUNT","CONS-AMOUNT",$A$1:$A$4,$A78:$B78,K$5:K$10,"#-962,449328916511") -> #NAME? | M78: =_xll.GetCtData("CO-AMOUNT","CONS-AMOUNT",$A$1:$A$4,$A78:$B78,M$5:M$10,"#-986,198566810051") -> #NAME? | O78: =K78-M78 -> #NAME? | Q78: =_xll.GetCtData("CO-AMOUNT","CONS-AMOUNT",$A$1:$A$4,$A78:$B78,Q$5:Q$10,"#-125,135345628597") -> #NAME? | S78: =_xll.GetCtData("CO-AMOUNT","CONS-AMOUNT",$A$1:$A$4,$A78:$B78,S$5:S$10,"#-102,035347377958") -> #NAME? | U78: =Q78-S78 -> #NAME? | W78: =_xll.GetCtData("CO-AMOUNT","CONS-AMOUNT",$A$1:$A$4,$A78:$B78,W$5:W$10,"#") -> #NAME? | Y78: =_xll.GetCtData("CO-AMOUNT","CONS-AMOUNT",$A$1:$A$4,$A78:$B78,Y$5:Y$10,"#") -> #NAME? | AA78: =W78-Y78 -> #NAME? | AC78: =_xll.GetCtData("CO-AMOUNT","CONS-AMOUNT",$A$1:$A$4,$A78:$B78,AC$5:AC$10,"#") -> #NAME? | AE78: =_xll.GetCtData("CO-AMOUNT","CONS-AMOUNT",$A$1:$A$4,$A78:$B78,AE$5:AE$10,"#") -> #NAME? | AG78: =AC78-AE78 -> #NAME? | AI78: =_xll.GetCtData("CO-AMOUNT","CONS-AMOUNT",$A$1:$A$4,$A78:$B78,AI$5:AI$10,"#") -> #NAME? | AK78: =_xll.GetCtData("CO-AMOUNT","CONS-AMOUNT",$A$1:$A$4,$A78:$B78,AK$5:AK$10,"#") -> #NAME? | AM78: =AI78-AK78 -> #NAME? | AO78: =_xll.GetCtData("CO-AMOUNT","CONS-AMOUNT",$A$1:$A$4,$A78:$B78,AO$5:AO$10,"#-43,5801197283742") -> #NAME? | AQ78: =_xll.GetCtData("CO-AMOUNT","CONS-AMOUNT",$A$1:$A$4,$A78:$B78,AQ$5:AQ$10,"#-44,1145679912843") -> #NAME? | AS78: =AO78-AQ78 -> #NAME? | AU78: =W78+AC78+AI78+AO78 -> #NAME? | AW78: =Y78+AE78+AK78+AQ78 -> #NAME? | AY78: =AU78-AW78 -> #NAME? | BA78: =+Q78-AO78 -> #NAME? | BC78: =+S78-AQ78 -> #NAME? | BE78: =BA78-BC78 -> #NAME? | BG78: =_xll.GetCtData("CO-AMOUNT","CONS-AMOUNT",$A$1:$A$4,$A78:$B78,BG$5:BG$10,"#-34,5332779037469") -> #NAME? | BI78: =_xll.GetCtData("CO-AMOUNT","CONS-AMOUNT",$A$1:$A$4,$A78:$B78,BI$5:BI$10,"#-35,0659008099457") -> #NAME? | BK78: =BG78-BI78 -> #NAME? | BN78: =_xll.GetCtData("CO-AMOUNT","CONS-AMOUNT",$A$1:$A$4,$A78:$B78,BN$5:BN$10,"#-9,04684182462722") -> #NAME? | BP78: =_xll.GetCtData("CO-AMOUNT","CONS-AMOUNT",$A$1:$A$4,$A78:$B78,BP$5:BP$10,"#-9,0486671813386") -> #NAME? | BR78: =BN78-BP78 -> #NAME?
A79: {OA=OA030}+{OA=OA031}+{OA=OA030E}+{OA=OA030O} | B79: RU=G-NL | C79: NL | D79: =CHOOSE([6]Traduction!$A$2,[6]Traduction!$A77,[6]Traduction!$B77) -> o/w Netherlands | E79: =_xll.GetCtData("CO-AMOUNT","CONS-AMOUNT",$A$1:$A$4,$A79:$B79,E$5:E$10,"#821,46") -> #NAME? | G79: =_xll.GetCtData("CO-AMOUNT","CONS-AMOUNT",$A$1:$A$4,$A79:$B79,G$5:G$10,"#814,824") -> #NAME? | I79: =E79-G79 -> #NAME? | K79: =_xll.GetCtData("CO-AMOUNT","CONS-AMOUNT",$A$1:$A$4,$A79:$B79,K$5:K$10,"#-780,73") -> #NAME? | M79: =_xll.GetCtData("CO-AMOUNT","CONS-AMOUNT",$A$1:$A$4,$A79:$B79,M$5:M$10,"#-778,792") -> #NAME? | O79: =K79-M79 -> #NAME? | Q79: =_xll.GetCtData("CO-AMOUNT","CONS-AMOUNT",$A$1:$A$4,$A79:$B79,Q$5:Q$10,"#40,73") -> #NAME? | S79: =_xll.GetCtData("CO-AMOUNT","CONS-AMOUNT",$A$1:$A$4,$A79:$B79,S$5:S$10,"#37,0319999999999") -> #NAME? | U79: =Q79-S79 -> #NAME? | W79: =_xll.GetCtData("CO-AMOUNT","CONS-AMOUNT",$A$1:$A$4,$A79:$B79,W$5:W$10,"#") -> #NAME? | Y79: =_xll.GetCtData("CO-AMOUNT","CONS-AMOUNT",$A$1:$A$4,$A79:$B79,Y$5:Y$10,"#") -> #NAME? | AA79: =W79-Y79 -> #NAME? | AC79: =_xll.GetCtData("CO-AMOUNT","CONS-AMOUNT",$A$1:$A$4,$A79:$B79,AC$5:AC$10,"#") -> #NAME? | AE79: =_xll.GetCtData("CO-AMOUNT","CONS-AMOUNT",$A$1:$A$4,$A79:$B79,AE$5:AE$10,"#") -> #NAME? | AG79: =AC79-AE79 -> #NAME? | AI79: =_xll.GetCtData("CO-AMOUNT","CONS-AMOUNT",$A$1:$A$4,$A79:$B79,AI$5:AI$10,"#") -> #NAME? | AK79: =_xll.GetCtData("CO-AMOUNT","CONS-AMOUNT",$A$1:$A$4,$A79:$B79,AK$5:AK$10,"#") -> #NAME? | AM79: =AI79-AK79 -> #NAME? | AO79: =_xll.GetCtData("CO-AMOUNT","CONS-AMOUNT",$A$1:$A$4,$A79:$B79,AO$5:AO$10,"#-18") -> #NAME? | AQ79: =_xll.GetCtData("CO-AMOUNT","CONS-AMOUNT",$A$1:$A$4,$A79:$B79,AQ$5:AQ$10,"#-20") -> #NAME? | AS79: =AO79-AQ79 -> #NAME? | AU79: =W79+AC79+AI79+AO79 -> #NAME? | AW79: =Y79+AE79+AK79+AQ79 -> #NAME? | AY79: =AU79-AW79 -> #NAME? | BA79: =+Q79-AO79 -> #NAME? | BC79: =+S79-AQ79 -> #NAME? | BE79: =BA79-BC79 -> #NAME? | BG79: =_xll.GetCtData("CO-AMOUNT","CONS-AMOUNT",$A$1:$A$4,$A79:$B79,BG$5:BG$10,"#-17") -> #NAME? | BI79: =_xll.GetCtData("CO-AMOUNT","CONS-AMOUNT",$A$1:$A$4,$A79:$B79,BI$5:BI$10,"#-19") -> #NAME? | BK79: =BG79-BI79 -> #NAME? | BN79: =_xll.GetCtData("CO-AMOUNT","CONS-AMOUNT",$A$1:$A$4,$A79:$B79,BN$5:BN$10,"#-1") -> #NAME? | BP79: =_xll.GetCtData("CO-AMOUNT","CONS-AMOUNT",$A$1:$A$4,$A79:$B79,BP$5:BP$10,"#-1") -> #NAME? | BR79: =BN79-BP79 -> #NAME?
A80: {OA=OA030}+{OA=OA031}+{OA=OA030E}+{OA=OA030O} | B80: RU=G-SP | C80: ESP | D80: =CHOOSE([6]Traduction!$A$2,[6]Traduction!$A48,[6]Traduction!$B48) -> o/w Spain | E80: =_xll.GetCtData("CO-AMOUNT","CONS-AMOUNT",$A$1:$A$4,$A80:$B80,E$5:E$10,"#558,043") -> #NAME? | G80: =_xll.GetCtData("CO-AMOUNT","CONS-AMOUNT",$A$1:$A$4,$A80:$B80,G$5:G$10,"#613,758") -> #NAME? | I80: =E80-G80 -> #NAME? | K80: =_xll.GetCtData("CO-AMOUNT","CONS-AMOUNT",$A$1:$A$4,$A80:$B80,K$5:K$10,"#-750,071") -> #NAME? | M80: =_xll.GetCtData("CO-AMOUNT","CONS-AMOUNT",$A$1:$A$4,$A80:$B80,M$5:M$10,"#-724,656") -> #NAME? | O80: =K80-M80 -> #NAME? | Q80: =_xll.GetCtData("CO-AMOUNT","CONS-AMOUNT",$A$1:$A$4,$A80:$B80,Q$5:Q$10,"#-201,818") -> #NAME? | S80: =_xll.GetCtData("CO-AMOUNT","CONS-AMOUNT",$A$1:$A$4,$A80:$B80,S$5:S$10,"#-112,794") -> #NAME? | U80: =Q80-S80 -> #NAME? | W80: =_xll.GetCtData("CO-AMOUNT","CONS-AMOUNT",$A$1:$A$4,$A80:$B80,W$5:W$10,"#") -> #NAME? | Y80: =_xll.GetCtData("CO-AMOUNT","CONS-AMOUNT",$A$1:$A$4,$A80:$B80,Y$5:Y$10,"#") -> #NAME? | AA80: =W80-Y80 -> #NAME? | AC80: =_xll.GetCtData("CO-AMOUNT","CONS-AMOUNT",$A$1:$A$4,$A80:$B80,AC$5:AC$10,"#") -> #NAME? | AE80: =_xll.GetCtData("CO-AMOUNT","CONS-AMOUNT",$A$1:$A$4,$A80:$B80,AE$5:AE$10,"#") -> #NAME? | AG80: =AC80-AE80 -> #NAME? | AI80: =_xll.GetCtData("CO-AMOUNT","CONS-AMOUNT",$A$1:$A$4,$A80:$B80,AI$5:AI$10,"#") -> #NAME? | AK80: =_xll.GetCtData("CO-AMOUNT","CONS-AMOUNT",$A$1:$A$4,$A80:$B80,AK$5:AK$10,"#") -> #NAME? | AM80: =AI80-AK80 -> #NAME? | AO80: =_xll.GetCtData("CO-AMOUNT","CONS-AMOUNT",$A$1:$A$4,$A80:$B80,AO$5:AO$10,"#-33,009") -> #NAME? | AQ80: =_xll.GetCtData("CO-AMOUNT","CONS-AMOUNT",$A$1:$A$4,$A80:$B80,AQ$5:AQ$10,"#-31,216") -> #NAME? | AS80: =AO80-AQ80 -> #NAME? | AU80: =W80+AC80+AI80+AO80 -> #NAME? | AW80: =Y80+AE80+AK80+AQ80 -> #NAME? | AY80: =AU80-AW80 -> #NAME? | BA80: =+Q80-AO80 -> #NAME? | BC80: =+S80-AQ80 -> #NAME? | BE80: =BA80-BC80 -> #NAME? | BG80: =_xll.GetCtData("CO-AMOUNT","CONS-AMOUNT",$A$1:$A$4,$A80:$B80,BG$5:BG$10,"#-26,089") -> #NAME? | BI80: =_xll.GetCtData("CO-AMOUNT","CONS-AMOUNT",$A$1:$A$4,$A80:$B80,BI$5:BI$10,"#-24,67") -> #NAME? | BK80: =BG80-BI80 -> #NAME? | BN80: =_xll.GetCtData("CO-AMOUNT","CONS-AMOUNT",$A$1:$A$4,$A80:$B80,BN$5:BN$10,"#-6,92") -> #NAME? | BP80: =_xll.GetCtData("CO-AMOUNT","CONS-AMOUNT",$A$1:$A$4,$A80:$B80,BP$5:BP$10,"#-6,546") -> #NAME? | BR80: =BN80-BP80 -> #NAME?
A81: {OA=OA030}+{OA=OA031}+{OA=OA030E}+{OA=OA030O} | B81: RU=G-IR | C81: IRL | D81: =CHOOSE([6]Traduction!$A$2,[6]Traduction!$A72,[6]Traduction!$B72) -> o/w Ireland | E81: =_xll.GetCtData("CO-AMOUNT","CONS-AMOUNT",$A$1:$A$4,$A81:$B81,E$5:E$10,"#420") -> #NAME? | G81: =_xll.GetCtData("CO-AMOUNT","CONS-AMOUNT",$A$1:$A$4,$A81:$B81,G$5:G$10,"#441") -> #NAME? | I81: =E81-G81 -> #NAME? | K81: =_xll.GetCtData("CO-AMOUNT","CONS-AMOUNT",$A$1:$A$4,$A81:$B81,K$5:K$10,"#-572,97") -> #NAME? | M81: =_xll.GetCtData("CO-AMOUNT","CONS-AMOUNT",$A$1:$A$4,$A81:$B81,M$5:M$10,"#-542,493") -> #NAME? | O81: =K81-M81 -> #NAME? | Q81: =_xll.GetCtData("CO-AMOUNT","CONS-AMOUNT",$A$1:$A$4,$A81:$B81,Q$5:Q$10,"#-152,97") -> #NAME? | S81: =_xll.GetCtData("CO-AMOUNT","CONS-AMOUNT",$A$1:$A$4,$A81:$B81,S$5:S$10,"#-101,493") -> #NAME? | U81: =Q81-S81 -> #NAME? | W81: =_xll.GetCtData("CO-AMOUNT","CONS-AMOUNT",$A$1:$A$4,$A81:$B81,W$5:W$10,"#") -> #NAME? | Y81: =_xll.GetCtData("CO-AMOUNT","CONS-AMOUNT",$A$1:$A$4,$A81:$B81,Y$5:Y$10,"#") -> #NAME? | AA81: =W81-Y81 -> #NAME? | AC81: =_xll.GetCtData("CO-AMOUNT","CONS-AMOUNT",$A$1:$A$4,$A81:$B81,AC$5:AC$10,"#") -> #NAME? | AE81: =_xll.GetCtData("CO-AMOUNT","CONS-AMOUNT",$A$1:$A$4,$A81:$B81,AE$5:AE$10,"#") -> #NAME? | AG81: =AC81-AE81 -> #NAME? | AI81: =_xll.GetCtData("CO-AMOUNT","CONS-AMOUNT",$A$1:$A$4,$A81:$B81,AI$5:AI$10,"#") -> #NAME? | AK81: =_xll.GetCtData("CO-AMOUNT","CONS-AMOUNT",$A$1:$A$4,$A81:$B81,AK$5:AK$10,"#") -> #NAME? | AM81: =AI81-AK81 -> #NAME? | AO81: =_xll.GetCtData("CO-AMOUNT","CONS-AMOUNT",$A$1:$A$4,$A81:$B81,AO$5:AO$10,"#-12,6") -> #NAME? | AQ81: =_xll.GetCtData("CO-AMOUNT","CONS-AMOUNT",$A$1:$A$4,$A81:$B81,AQ$5:AQ$10,"#-10,101") -> #NAME? | AS81: =AO81-AQ81 -> #NAME? | AU81: =W81+AC81+AI81+AO81 -> #NAME? | AW81: =Y81+AE81+AK81+AQ81 -> #NAME? | AY81: =AU81-AW81 -> #NAME? | BA81: =+Q81-AO81 -> #NAME? | BC81: =+S81-AQ81 -> #NAME? | BE81: =BA81-BC81 -> #NAME? | BG81: =_xll.GetCtData("CO-AMOUNT","CONS-AMOUNT",$A$1:$A$4,$A81:$B81,BG$5:BG$10,"#-12,6") -> #NAME? | BI81: =_xll.GetCtData("CO-AMOUNT","CONS-AMOUNT",$A$1:$A$4,$A81:$B81,BI$5:BI$10,"#-10,101") -> #NAME? | BK81: =BG81-BI81 -> #NAME? | BN81: =_xll.GetCtData("CO-AMOUNT","CONS-AMOUNT",$A$1:$A$4,$A81:$B81,BN$5:BN$10,"#") -> #NAME? | BP81: =_xll.GetCtData("CO-AMOUNT","CONS-AMOUNT",$A$1:$A$4,$A81:$B81,BP$5:BP$10,"#") -> #NAME? | BR81: =BN81-BP81 -> #NAME?
A82: {OA=OA030}+{OA=OA031}+{OA=OA030E}+{OA=OA030O} | B82: RU=G-LX | C82: LUX | D82: =CHOOSE([6]Traduction!$A$2,[6]Traduction!$A53,[6]Traduction!$B53) -> o/w Luxembourg | E82: =_xll.GetCtData("CO-AMOUNT","CONS-AMOUNT",$A$1:$A$4,$A82:$B82,E$5:E$10,"#778,87") -> #NAME? | G82: =_xll.GetCtData("CO-AMOUNT","CONS-AMOUNT",$A$1:$A$4,$A82:$B82,G$5:G$10,"#586,628") -> #NAME? | I82: =E82-G82 -> #NAME? | K82: =_xll.GetCtData("CO-AMOUNT","CONS-AMOUNT",$A$1:$A$4,$A82:$B82,K$5:K$10,"#-608,068") -> #NAME? | M82: =_xll.GetCtData("CO-AMOUNT","CONS-AMOUNT",$A$1:$A$4,$A82:$B82,M$5:M$10,"#-591,084") -> #NAME? | O82: =K82-M82 -> #NAME? | Q82: =_xll.GetCtData("CO-AMOUNT","CONS-AMOUNT",$A$1:$A$4,$A82:$B82,Q$5:Q$10,"#170,802") -> #NAME? | S82: =_xll.GetCtData("CO-AMOUNT","CONS-AMOUNT",$A$1:$A$4,$A82:$B82,S$5:S$10,"#-4,45599999999991") -> #NAME? | U82: =Q82-S82 -> #NAME? | W82: =_xll.GetCtData("CO-AMOUNT","CONS-AMOUNT",$A$1:$A$4,$A82:$B82,W$5:W$10,"#") -> #NAME? | Y82: =_xll.GetCtData("CO-AMOUNT","CONS-AMOUNT",$A$1:$A$4,$A82:$B82,Y$5:Y$10,"#") -> #NAME? | AA82: =W82-Y82 -> #NAME? | AC82: =_xll.GetCtData("CO-AMOUNT","CONS-AMOUNT",$A$1:$A$4,$A82:$B82,AC$5:AC$10,"#") -> #NAME? | AE82: =_xll.GetCtData("CO-AMOUNT","CONS-AMOUNT",$A$1:$A$4,$A82:$B82,AE$5:AE$10,"#") -> #NAME? | AG82: =AC82-AE82 -> #NAME? | AI82: =_xll.GetCtData("CO-AMOUNT","CONS-AMOUNT",$A$1:$A$4,$A82:$B82,AI$5:AI$10,"#") -> #NAME? | AK82: =_xll.GetCtData("CO-AMOUNT","CONS-AMOUNT",$A$1:$A$4,$A82:$B82,AK$5:AK$10,"#") -> #NAME? | AM82: =AI82-AK82 -> #NAME? | AO82: =_xll.GetCtData("CO-AMOUNT","CONS-AMOUNT",$A$1:$A$4,$A82:$B82,AO$5:AO$10,"#-21,231") -> #NAME? | AQ82: =_xll.GetCtData("CO-AMOUNT","CONS-AMOUNT",$A$1:$A$4,$A82:$B82,AQ$5:AQ$10,"#-21,231") -> #NAME? | AS82: =AO82-AQ82 -> #NAME? | AU82: =W82+AC82+AI82+AO82 -> #NAME? | AW82: =Y82+AE82+AK82+AQ82 -> #NAME? | AY82: =AU82-AW82 -> #NAME? | BA82: =+Q82-AO82 -> #NAME? | BC82: =+S82-AQ82 -> #NAME? | BE82: =BA82-BC82 -> #NAME? | BG82: =_xll.GetCtData("CO-AMOUNT","CONS-AMOUNT",$A$1:$A$4,$A82:$B82,BG$5:BG$10,"#-21,231") -> #NAME? | BI82: =_xll.GetCtData("CO-AMOUNT","CONS-AMOUNT",$A$1:$A$4,$A82:$B82,BI$5:BI$10,"#-21,231") -> #NAME? | BK82: =BG82-BI82 -> #NAME? | BN82: =_xll.GetCtData("CO-AMOUNT","CONS-AMOUNT",$A$1:$A$4,$A82:$B82,BN$5:BN$10,"#") -> #NAME? | BP82: =_xll.GetCtData("CO-AMOUNT","CONS-AMOUNT",$A$1:$A$4,$A82:$B82,BP$5:BP$10,"#") -> #NAME? | BR82: =BN82-BP82 -> #NAME?
D83: =CHOOSE([6]Traduction!$A$2,[6]Traduction!$A88,[6]Traduction!$B88) -> Platforms | E83: =E84+E85+E86+E87 -> #NAME? | G83: =G84+G85+G86+G87 -> #NAME? | I83: =E83-G83 -> #NAME? | K83: =K84+K85+K86+K87 -> #NAME? | M83: =M84+M85+M86+M87 -> #NAME? | O83: =K83-M83 -> #NAME? | Q83: =Q84+Q85+Q86+Q87 -> #NAME? | S83: =S84+S85+S86+S87 -> #NAME? | U83: =Q83-S83 -> #NAME? | W83: =W84+W85+W86+W87 -> #NAME? | Y83: =Y84+Y85+Y86+Y87 -> #NAME? | AA83: =W83-Y83 -> #NAME? | AC83: =AC84+AC85+AC86+AC87 -> #NAME? | AE83: =AE84+AE85+AE86+AE87 -> #NAME? | AG83: =AC83-AE83 -> #NAME? | AI83: =AI84+AI85+AI86+AI87 -> #NAME? | AK83: =AK84+AK85+AK86+AK87 -> #NAME? | AM83: =AI83-AK83 -> #NAME? | AO83: =AO84+AO85+AO86+AO87 -> #NAME? | AQ83: =AQ84+AQ85+AQ86+AQ87 -> #NAME? | AS83: =AO83-AQ83 -> #NAME? | AU83: =W83+AC83+AI83+AO83 -> #NAME? | AW83: =Y83+AE83+AK83+AQ83 -> #NAME? | AY83: =AU83-AW83 -> #NAME? | BA83: =+Q83-AO83 -> #NAME? | BC83: =+S83-AQ83 -> #NAME? | BE83: =BA83-BC83 -> #NAME? | BG83: =BG84+BG85+BG86+BG87 -> #NAME? | BI83: =BI84+BI85+BI86+BI87 -> #NAME? | BK83: =BG83-BI83 -> #NAME? | BN83: =BN84+BN85+BN86+BN87 -> #NAME? | BP83: =BP84+BP85+BP86+BP87 -> #NAME? | BR83: =BN83-BP83 -> #NAME?
A84: OA sum AR001 | B84: {RU=G-ASIEPF} | C84: PF | D84: =CHOOSE([6]Traduction!$A$2,[6]Traduction!$A89,[6]Traduction!$B89) -> o/w Asia | E84: =_xll.GetCtData("CO-AMOUNT","CONS-AMOUNT",$A$1:$A$4,$A84:$B84,E$5:E$10,"#-2,15") -> #NAME? | G84: =_xll.GetCtData("CO-AMOUNT","CONS-AMOUNT",$A$1:$A$4,$A84:$B84,G$5:G$10,"#-1,673") -> #NAME? | I84: =E84-G84 -> #NAME? | K84: =_xll.GetCtData("CO-AMOUNT","CONS-AMOUNT",$A$1:$A$4,$A84:$B84,K$5:K$10,"#-212,426") -> #NAME? | M84: =_xll.GetCtData("CO-AMOUNT","CONS-AMOUNT",$A$1:$A$4,$A84:$B84,M$5:M$10,"#-237,075") -> #NAME? | O84: =K84-M84 -> #NAME? | Q84: =_xll.GetCtData("CO-AMOUNT","CONS-AMOUNT",$A$1:$A$4,$A84:$B84,Q$5:Q$10,"#-214,576") -> #NAME? | S84: =_xll.GetCtData("CO-AMOUNT","CONS-AMOUNT",$A$1:$A$4,$A84:$B84,S$5:S$10,"#-238,748") -> #NAME? | U84: =Q84-S84 -> #NAME? | W84: =_xll.GetCtData("CO-AMOUNT","CONS-AMOUNT",$A$1:$A$4,$A84:$B84,W$5:W$10,"#") -> #NAME? | Y84: =_xll.GetCtData("CO-AMOUNT","CONS-AMOUNT",$A$1:$A$4,$A84:$B84,Y$5:Y$10,"#") -> #NAME? | AA84: =W84-Y84 -> #NAME? | AC84: =_xll.GetCtData("CO-AMOUNT","CONS-AMOUNT",$A$1:$A$4,$A84:$B84,AC$5:AC$10,"#") -> #NAME? | AE84: =_xll.GetCtData("CO-AMOUNT","CONS-AMOUNT",$A$1:$A$4,$A84:$B84,AE$5:AE$10,"#") -> #NAME? | AG84: =AC84-AE84 -> #NAME? | AI84: =_xll.GetCtData("CO-AMOUNT","CONS-AMOUNT",$A$1:$A$4,$A84:$B84,AI$5:AI$10,"#") -> #NAME? | AK84: =_xll.GetCtData("CO-AMOUNT","CONS-AMOUNT",$A$1:$A$4,$A84:$B84,AK$5:AK$10,"#") -> #NAME? | AM84: =AI84-AK84 -> #NAME? | AO84: =_xll.GetCtData("CO-AMOUNT","CONS-AMOUNT",$A$1:$A$4,$A84:$B84,AO$5:AO$10,"#") -> #NAME? | AQ84: =_xll.GetCtData("CO-AMOUNT","CONS-AMOUNT",$A$1:$A$4,$A84:$B84,AQ$5:AQ$10,"#") -> #NAME? | AS84: =AO84-AQ84 -> #NAME? | AU84: =W84+AC84+AI84+AO84 -> #NAME? | AW84: =Y84+AE84+AK84+AQ84 -> #NAME? | AY84: =AU84-AW84 -> #NAME? | BA84: =+Q84-AO84 -> #NAME? | BC84: =+S84-AQ84 -> #NAME? | BE84: =BA84-BC84 -> #NAME? | BG84: =_xll.GetCtData("CO-AMOUNT","CONS-AMOUNT",$A$1:$A$4,$A84:$B84,BG$5:BG$10,"#") -> #NAME? | BI84: =_xll.GetCtData("CO-AMOUNT","CONS-AMOUNT",$A$1:$A$4,$A84:$B84,BI$5:BI$10,"#") -> #NAME? | BK84: =BG84-BI84 -> #NAME? | BN84: =_xll.GetCtData("CO-AMOUNT","CONS-AMOUNT",$A$1:$A$4,$A84:$B84,BN$5:BN$10,"#") -> #NAME? | BP84: =_xll.GetCtData("CO-AMOUNT","CONS-AMOUNT",$A$1:$A$4,$A84:$B84,BP$5:BP$10,"#") -> #NAME? | BR84: =BN84-BP84 -> #NAME?
A85: OA sum AR001 | B85: {RU=G-MEPF} | C85: PF | D85: =CHOOSE([6]Traduction!$A$2,[6]Traduction!$A90,[6]Traduction!$B90) -> o/w Middle East | E85: =_xll.GetCtData("CO-AMOUNT","CONS-AMOUNT",$A$1:$A$4,$A85:$B85,E$5:E$10,"#10,36") -> #NAME? | G85: =_xll.GetCtData("CO-AMOUNT","CONS-AMOUNT",$A$1:$A$4,$A85:$B85,G$5:G$10,"#-15,123") -> #NAME? | I85: =E85-G85 -> #NAME? | K85: =_xll.GetCtData("CO-AMOUNT","CONS-AMOUNT",$A$1:$A$4,$A85:$B85,K$5:K$10,"#-133,1") -> #NAME? | M85: =_xll.GetCtData("CO-AMOUNT","CONS-AMOUNT",$A$1:$A$4,$A85:$B85,M$5:M$10,"#-223,354") -> #NAME? | O85: =K85-M85 -> #NAME? | Q85: =_xll.GetCtData("CO-AMOUNT","CONS-AMOUNT",$A$1:$A$4,$A85:$B85,Q$5:Q$10,"#-122,74") -> #NAME? | S85: =_xll.GetCtData("CO-AMOUNT","CONS-AMOUNT",$A$1:$A$4,$A85:$B85,S$5:S$10,"#-238,477") -> #NAME? | U85: =Q85-S85 -> #NAME? | W85: =_xll.GetCtData("CO-AMOUNT","CONS-AMOUNT",$A$1:$A$4,$A85:$B85,W$5:W$10,"#") -> #NAME? | Y85: =_xll.GetCtData("CO-AMOUNT","CONS-AMOUNT",$A$1:$A$4,$A85:$B85,Y$5:Y$10,"#") -> #NAME? | AA85: =W85-Y85 -> #NAME? | AC85: =_xll.GetCtData("CO-AMOUNT","CONS-AMOUNT",$A$1:$A$4,$A85:$B85,AC$5:AC$10,"#") -> #NAME? | AE85: =_xll.GetCtData("CO-AMOUNT","CONS-AMOUNT",$A$1:$A$4,$A85:$B85,AE$5:AE$10,"#") -> #NAME? | AG85: =AC85-AE85 -> #NAME? | AI85: =_xll.GetCtData("CO-AMOUNT","CONS-AMOUNT",$A$1:$A$4,$A85:$B85,AI$5:AI$10,"#") -> #NAME? | AK85: =_xll.GetCtData("CO-AMOUNT","CONS-AMOUNT",$A$1:$A$4,$A85:$B85,AK$5:AK$10,"#") -> #NAME? | AM85: =AI85-AK85 -> #NAME? | AO85: =_xll.GetCtData("CO-AMOUNT","CONS-AMOUNT",$A$1:$A$4,$A85:$B85,AO$5:AO$10,"#") -> #NAME? | AQ85: =_xll.GetCtData("CO-AMOUNT","CONS-AMOUNT",$A$1:$A$4,$A85:$B85,AQ$5:AQ$10,"#") -> #NAME? | AS85: =AO85-AQ85 -> #NAME? | AU85: =W85+AC85+AI85+AO85 -> #NAME? | AW85: =Y85+AE85+AK85+AQ85 -> #NAME? | AY85: =AU85-AW85 -> #NAME? | BA85: =+Q85-AO85 -> #NAME? | BC85: =+S85-AQ85 -> #NAME? | BE85: =BA85-BC85 -> #NAME? | BG85: =_xll.GetCtData("CO-AMOUNT","CONS-AMOUNT",$A$1:$A$4,$A85:$B85,BG$5:BG$10,"#") -> #NAME? | BI85: =_xll.GetCtData("CO-AMOUNT","CONS-AMOUNT",$A$1:$A$4,$A85:$B85,BI$5:BI$10,"#") -> #NAME? | BK85: =BG85-BI85 -> #NAME? | BN85: =_xll.GetCtData("CO-AMOUNT","CONS-AMOUNT",$A$1:$A$4,$A85:$B85,BN$5:BN$10,"#") -> #NAME? | BP85: =_xll.GetCtData("CO-AMOUNT","CONS-AMOUNT",$A$1:$A$4,$A85:$B85,BP$5:BP$10,"#") -> #NAME? | BR85: =BN85-BP85 -> #NAME?
A86: OA sum AR001 | B86: {RU=G-SGP} | C86: PF | D86: =CHOOSE([6]Traduction!$A$2,[6]Traduction!$A91,[6]Traduction!$B91) -> o/w Singapore | E86: =_xll.GetCtData("CO-AMOUNT","CONS-AMOUNT",$A$1:$A$4,$A86:$B86,E$5:E$10,"#-0,937584431780186") -> #NAME? | G86: =_xll.GetCtData("CO-AMOUNT","CONS-AMOUNT",$A$1:$A$4,$A86:$B86,G$5:G$10,"#-0,977966974869566") -> #NAME? | I86: =E86-G86 -> #NAME? | K86: =_xll.GetCtData("CO-AMOUNT","CONS-AMOUNT",$A$1:$A$4,$A86:$B86,K$5:K$10,"#12,0211718217531") -> #NAME? | M86: =_xll.GetCtData("CO-AMOUNT","CONS-AMOUNT",$A$1:$A$4,$A86:$B86,M$5:M$10,"#-62,0696345723679") -> #NAME? | O86: =K86-M86 -> #NAME? | Q86: =_xll.GetCtData("CO-AMOUNT","CONS-AMOUNT",$A$1:$A$4,$A86:$B86,Q$5:Q$10,"#11,0835873899729") -> #NAME? | S86: =_xll.GetCtData("CO-AMOUNT","CONS-AMOUNT",$A$1:$A$4,$A86:$B86,S$5:S$10,"#-63,0476015472374") -> #NAME? | U86: =Q86-S86 -> #NAME? | W86: =_xll.GetCtData("CO-AMOUNT","CONS-AMOUNT",$A$1:$A$4,$A86:$B86,W$5:W$10,"#") -> #NAME? | Y86: =_xll.GetCtData("CO-AMOUNT","CONS-AMOUNT",$A$1:$A$4,$A86:$B86,Y$5:Y$10,"#") -> #NAME? | AA86: =W86-Y86 -> #NAME? | AC86: =_xll.GetCtData("CO-AMOUNT","CONS-AMOUNT",$A$1:$A$4,$A86:$B86,AC$5:AC$10,"#") -> #NAME? | AE86: =_xll.GetCtData("CO-AMOUNT","CONS-AMOUNT",$A$1:$A$4,$A86:$B86,AE$5:AE$10,"#") -> #NAME? | AG86: =AC86-AE86 -> #NAME? | AI86: =_xll.GetCtData("CO-AMOUNT","CONS-AMOUNT",$A$1:$A$4,$A86:$B86,AI$5:AI$10,"#") -> #NAME? | AK86: =_xll.GetCtData("CO-AMOUNT","CONS-AMOUNT",$A$1:$A$4,$A86:$B86,AK$5:AK$10,"#") -> #NAME? | AM86: =AI86-AK86 -> #NAME? | AO86: =_xll.GetCtData("CO-AMOUNT","CONS-AMOUNT",$A$1:$A$4,$A86:$B86,AO$5:AO$10,"#") -> #NAME? | AQ86: =_xll.GetCtData("CO-AMOUNT","CONS-AMOUNT",$A$1:$A$4,$A86:$B86,AQ$5:AQ$10,"#") -> #NAME? | AS86: =AO86-AQ86 -> #NAME? | AU86: =W86+AC86+AI86+AO86 -> #NAME? | AW86: =Y86+AE86+AK86+AQ86 -> #NAME? | AY86: =AU86-AW86 -> #NAME? | BA86: =+Q86-AO86 -> #NAME? | BC86: =+S86-AQ86 -> #NAME? | BE86: =BA86-BC86 -> #NAME? | BG86: =_xll.GetCtData("CO-AMOUNT","CONS-AMOUNT",$A$1:$A$4,$A86:$B86,BG$5:BG$10,"#") -> #NAME? | BI86: =_xll.GetCtData("CO-AMOUNT","CONS-AMOUNT",$A$1:$A$4,$A86:$B86,BI$5:BI$10,"#") -> #NAME? | BK86: =BG86-BI86 -> #NAME? | BN86: =_xll.GetCtData("CO-AMOUNT","CONS-AMOUNT",$A$1:$A$4,$A86:$B86,BN$5:BN$10,"#") -> #NAME? | BP86: =_xll.GetCtData("CO-AMOUNT","CONS-AMOUNT",$A$1:$A$4,$A86:$B86,BP$5:BP$10,"#") -> #NAME? | BR86: =BN86-BP86 -> #NAME?
A87: {OA=OA006} | B87: {RU=G-HDBNPPI}+{RU=P-HDBNPPI} | C87: FR | D87: =CHOOSE([6]Traduction!$A$2,[6]Traduction!$A92,[6]Traduction!$B92) -> Internal SLA Reinvoicings | E87: =_xll.GetCtData("CO-AMOUNT","CONS-AMOUNT",$A$1:$A$4,$A87:$B87,E$5:E$10,"#") -> #NAME? | G87: =_xll.GetCtData("CO-AMOUNT","CONS-AMOUNT",$A$1:$A$4,$A87:$B87,G$5:G$10,"#") -> #NAME? | I87: =E87-G87 -> #NAME? | K87: =_xll.GetCtData("CO-AMOUNT","CONS-AMOUNT",$A$1:$A$4,$A87:$B87,K$5:K$10,"#584,54") -> #NAME? | M87: =_xll.GetCtData("CO-AMOUNT","CONS-AMOUNT",$A$1:$A$4,$A87:$B87,M$5:M$10,"#576,947") -> #NAME? | O87: =K87-M87 -> #NAME? | Q87: =_xll.GetCtData("CO-AMOUNT","CONS-AMOUNT",$A$1:$A$4,$A87:$B87,Q$5:Q$10,"#584,54") -> #NAME? | S87: =_xll.GetCtData("CO-AMOUNT","CONS-AMOUNT",$A$1:$A$4,$A87:$B87,S$5:S$10,"#576,947") -> #NAME? | U87: =Q87-S87 -> #NAME? | W87: =_xll.GetCtData("CO-AMOUNT","CONS-AMOUNT",$A$1:$A$4,$A87:$B87,W$5:W$10,"#584,54") -> #NAME? | Y87: =_xll.GetCtData("CO-AMOUNT","CONS-AMOUNT",$A$1:$A$4,$A87:$B87,Y$5:Y$10,"#769,27") -> #NAME? | AA87: =W87-Y87 -> #NAME? | AC87: =_xll.GetCtData("CO-AMOUNT","CONS-AMOUNT",$A$1:$A$4,$A87:$B87,AC$5:AC$10,"#") -> #NAME? | AE87: =_xll.GetCtData("CO-AMOUNT","CONS-AMOUNT",$A$1:$A$4,$A87:$B87,AE$5:AE$10,"#") -> #NAME? | AG87: =AC87-AE87 -> #NAME? | AI87: =_xll.GetCtData("CO-AMOUNT","CONS-AMOUNT",$A$1:$A$4,$A87:$B87,AI$5:AI$10,"#") -> #NAME? | AK87: =_xll.GetCtData("CO-AMOUNT","CONS-AMOUNT",$A$1:$A$4,$A87:$B87,AK$5:AK$10,"#") -> #NAME? | AM87: =AI87-AK87 -> #NAME? | AO87: =_xll.GetCtData("CO-AMOUNT","CONS-AMOUNT",$A$1:$A$4,$A87:$B87,AO$5:AO$10,"#") -> #NAME? | AQ87: =_xll.GetCtData("CO-AMOUNT","CONS-AMOUNT",$A$1:$A$4,$A87:$B87,AQ$5:AQ$10,"#") -> #NAME? | AS87: =AO87-AQ87 -> #NAME? | AU87: =W87+AC87+AI87+AO87 -> #NAME? | AW87: =Y87+AE87+AK87+AQ87 -> #NAME? | AY87: =AU87-AW87 -> #NAME? | BA87: =+Q87-AO87 -> #NAME? | BC87: =+S87-AQ87 -> #NAME? | BE87: =BA87-BC87 -> #NAME? | BG87: =_xll.GetCtData("CO-AMOUNT","CONS-AMOUNT",$A$1:$A$4,$A87:$B87,BG$5:BG$10,"#") -> #NAME? | BI87: =_xll.GetCtData("CO-AMOUNT","CONS-AMOUNT",$A$1:$A$4,$A87:$B87,BI$5:BI$10,"#") -> #NAME? | BK87: =BG87-BI87 -> #NAME? | BN87: =_xll.GetCtData("CO-AMOUNT","CONS-AMOUNT",$A$1:$A$4,$A87:$B87,BN$5:BN$10,"#") -> #NAME? | BP87: =_xll.GetCtData("CO-AMOUNT","CONS-AMOUNT",$A$1:$A$4,$A87:$B87,BP$5:BP$10,"#") -> #NAME? | BR87: =BN87-BP87 -> #NAME?
D88: Holding RE | E88: =E89+E90 -> #NAME? | G88: =G89+G90 -> #NAME? | H88: =H89+H90+#REF! -> #REF! | I88: =E88-G88 -> #NAME? | K88: =K89+K90 -> #NAME? | M88: =M89+M90 -> #NAME? | N88: =N89+N90+#REF! -> #REF! | O88: =K88-M88 -> #NAME? | Q88: =Q89+Q90 -> #NAME? | S88: =S89+S90 -> #NAME? | T88: =T89+T90+#REF! -> #REF! | U88: =Q88-S88 -> #NAME? | W88: =W89+W90 -> #NAME? | Y88: =Y89+Y90 -> #NAME? | Z88: =Z89+Z90+#REF! -> #REF! | AA88: =W88-Y88 -> #NAME? | AC88: =AC89+AC90 -> #NAME? | AE88: =AE89+AE90 -> #NAME? | AF88: =AF89+AF90+#REF! -> #REF! | AG88: =AC88-AE88 -> #NAME? | AI88: =AI89+AI90 -> #NAME? | AK88: =AK89+AK90 -> #NAME? | AL88: =AL89+AL90+#REF! -> #REF! | AM88: =AI88-AK88 -> #NAME? | AO88: =AO89+AO90 -> #NAME? | AQ88: =AQ89+AQ90 -> #NAME? | AR88: =AR89+AR90+#REF! -> #REF! | AS88: =AO88-AQ88 -> #NAME? | AU88: =W88+AC88+AI88+AO88 -> #NAME? | AW88: =Y88+AE88+AK88+AQ88 -> #NAME? | AX88: =AX89+AX90+#REF! -> #REF! | AY88: =AU88-AW88 -> #NAME? | BA88: =+Q88-AO88 -> #NAME? | BC88: =+S88-AQ88 -> #NAME? | BE88: =BA88-BC88 -> #NAME? | BG88: =BG89+BG90 -> #NAME? | BI88: =BI89+BI90 -> #NAME? | BJ88: =BJ89+BJ90+#REF! -> #REF! | BK88: =BG88-BI88 -> #NAME? | BN88: =BN89+BN90 -> #NAME? | BP88: =BP89+BP90 -> #NAME? | BQ88: =BQ89+BQ90+#REF! -> #REF! | BR88: =BN88-BP88 -> #NAME?
A89: {OA=OA005}+{OA=OA005O} | B89: {RU=G-HDBNPPI}+{RU=P-HDBNPPI} | C89: FR | D89: Holding BNPPRE | E89: =_xll.GetCtData("CO-AMOUNT","CONS-AMOUNT",$A$1:$A$4,$A89:$B89,E$5:E$10,"#1729,95") -> #NAME? | G89: =_xll.GetCtData("CO-AMOUNT","CONS-AMOUNT",$A$1:$A$4,$A89:$B89,G$5:G$10,"#2120,306") -> #NAME? | I89: =E89-G89 -> #NAME? | K89: =_xll.GetCtData("CO-AMOUNT","CONS-AMOUNT",$A$1:$A$4,$A89:$B89,K$5:K$10,"#-10933,496") -> #NAME? | M89: =_xll.GetCtData("CO-AMOUNT","CONS-AMOUNT",$A$1:$A$4,$A89:$B89,M$5:M$10,"#-13297,949") -> #NAME? | O89: =K89-M89 -> #NAME? | Q89: =_xll.GetCtData("CO-AMOUNT","CONS-AMOUNT",$A$1:$A$4,$A89:$B89,Q$5:Q$10,"#-9203,54600000001") -> #NAME? | S89: =_xll.GetCtData("CO-AMOUNT","CONS-AMOUNT",$A$1:$A$4,$A89:$B89,S$5:S$10,"#-11177,643") -> #NAME? | U89: =Q89-S89 -> #NAME? | W89: =_xll.GetCtData("CO-AMOUNT","CONS-AMOUNT",$A$1:$A$4,$A89:$B89,W$5:W$10,"#") -> #NAME? | Y89: =_xll.GetCtData("CO-AMOUNT","CONS-AMOUNT",$A$1:$A$4,$A89:$B89,Y$5:Y$10,"#") -> #NAME? | AA89: =W89-Y89 -> #NAME? | AC89: =_xll.GetCtData("CO-AMOUNT","CONS-AMOUNT",$A$1:$A$4,$A89:$B89,AC$5:AC$10,"#") -> #NAME? | AE89: =_xll.GetCtData("CO-AMOUNT","CONS-AMOUNT",$A$1:$A$4,$A89:$B89,AE$5:AE$10,"#") -> #NAME? | AG89: =AC89-AE89 -> #NAME? | AI89: =_xll.GetCtData("CO-AMOUNT","CONS-AMOUNT",$A$1:$A$4,$A89:$B89,AI$5:AI$10,"#") -> #NAME? | AK89: =_xll.GetCtData("CO-AMOUNT","CONS-AMOUNT",$A$1:$A$4,$A89:$B89,AK$5:AK$10,"#") -> #NAME? | AM89: =AI89-AK89 -> #NAME? | AO89: =_xll.GetCtData("CO-AMOUNT","CONS-AMOUNT",$A$1:$A$4,$A89:$B89,AO$5:AO$10,"#15234,97") -> #NAME? | AQ89: =_xll.GetCtData("CO-AMOUNT","CONS-AMOUNT",$A$1:$A$4,$A89:$B89,AQ$5:AQ$10,"#16287,64") -> #NAME? | AS89: =AO89-AQ89 -> #NAME? | AU89: =W89+AC89+AI89+AO89 -> #NAME? | AW89: =Y89+AE89+AK89+AQ89 -> #NAME? | AY89: =AU89-AW89 -> #NAME? | BA89: =+Q89-AO89 -> #NAME? | BC89: =+S89-AQ89 -> #NAME? | BE89: =BA89-BC89 -> #NAME? | BG89: =_xll.GetCtData("CO-AMOUNT","CONS-AMOUNT",$A$1:$A$4,$A89:$B89,BG$5:BG$10,"#16425,92") -> #NAME? | BI89: =_xll.GetCtData("CO-AMOUNT","CONS-AMOUNT",$A$1:$A$4,$A89:$B89,BI$5:BI$10,"#17469") -> #NAME? | BK89: =BG89-BI89 -> #NAME? | BN89: =_xll.GetCtData("CO-AMOUNT","CONS-AMOUNT",$A$1:$A$4,$A89:$B89,BN$5:BN$10,"#-1190,95") -> #NAME? | BP89: =_xll.GetCtData("CO-AMOUNT","CONS-AMOUNT",$A$1:$A$4,$A89:$B89,BP$5:BP$10,"#-1181,36") -> #NAME? | BR89: =BN89-BP89 -> #NAME?
C90: BCE | D90: =CHOOSE([6]Traduction!$A$2,[6]Traduction!$A83,[6]Traduction!$B83) -> Reprocessing accounting carto BCESTE | I90: =E90-G90 -> 0 | K90: =+[6]BCESTE!F17 -> 6783.928 | M90: =+[6]BCESTE!G17 -> 6783.928 | O90: =K90-M90 -> 0 | Q90: =+[6]BCESTE!F17 -> 6783.928 | S90: =+[6]BCESTE!G17 -> 6783.928 | U90: =Q90-S90 -> 0 | AA90: =W90-Y90 -> 0 | AG90: =AC90-AE90 -> 0 | AM90: =AI90-AK90 -> 0 | AS90: =AO90-AQ90 -> 0 | AU90: =W90+AC90+AI90+AO90 -> 0 | AW90: =Y90+AE90+AK90+AQ90 -> 0 | AY90: =AU90-AW90 -> 0 | BA90: =+Q90-AO90 -> 6783.928 | BC90: =+S90-AQ90 -> 6783.928 | BE90: =BA90-BC90 -> 0 | BK90: =BG90-BI90 -> 0 | BR90: =BN90-BP90 -> 0
A91: OA=OA005 | B91: RU sum AF026 | C91: ITA | D91: =CHOOSE([6]Traduction!$A$2,[6]Traduction!$A85,[6]Traduction!$B85) -> Holding Italy | E91: =_xll.GetCtData("CO-AMOUNT","CONS-AMOUNT",$A$1:$A$4,$A91:$B91,E$5:E$10,"#") -> #NAME? | G91: =_xll.GetCtData("CO-AMOUNT","CONS-AMOUNT",$A$1:$A$4,$A91:$B91,G$5:G$10,"#") -> #NAME? | I91: =E91-G91 -> #NAME? | K91: =_xll.GetCtData("CO-AMOUNT","CONS-AMOUNT",$A$1:$A$4,$A91:$B91,K$5:K$10,"#100,984") -> #NAME? | M91: =_xll.GetCtData("CO-AMOUNT","CONS-AMOUNT",$A$1:$A$4,$A91:$B91,M$5:M$10,"#97,056") -> #NAME? | O91: =K91-M91 -> #NAME? | Q91: =_xll.GetCtData("CO-AMOUNT","CONS-AMOUNT",$A$1:$A$4,$A91:$B91,Q$5:Q$10,"#100,984") -> #NAME? | S91: =_xll.GetCtData("CO-AMOUNT","CONS-AMOUNT",$A$1:$A$4,$A91:$B91,S$5:S$10,"#97,056") -> #NAME? | U91: =Q91-S91 -> #NAME? | W91: =_xll.GetCtData("CO-AMOUNT","CONS-AMOUNT",$A$1:$A$4,$A91:$B91,X$5:X$10,"#") -> #NAME? | Y91: =_xll.GetCtData("CO-AMOUNT","CONS-AMOUNT",$A$1:$A$4,$A91:$B91,Z$5:Z$10,"#") -> #NAME? | AA91: =W91-Y91 -> #NAME? | AC91: =_xll.GetCtData("CO-AMOUNT","CONS-AMOUNT",$A$1:$A$4,$A91:$B91,AD$5:AD$10,"#") -> #NAME? | AE91: =_xll.GetCtData("CO-AMOUNT","CONS-AMOUNT",$A$1:$A$4,$A91:$B91,AF$5:AF$10,"#") -> #NAME? | AG91: =AC91-AE91 -> #NAME? | AI91: =_xll.GetCtData("CO-AMOUNT","CONS-AMOUNT",$A$1:$A$4,$A91:$B91,AJ$5:AJ$10,"#") -> #NAME? | AK91: =_xll.GetCtData("CO-AMOUNT","CONS-AMOUNT",$A$1:$A$4,$A91:$B91,AL$5:AL$10,"#") -> #NAME? | AM91: =AI91-AK91 -> #NAME? | AO91: =_xll.GetCtData("CO-AMOUNT","CONS-AMOUNT",$A$1:$A$4,$A91:$B91,AP$5:AP$10,"#") -> #NAME? | AQ91: =_xll.GetCtData("CO-AMOUNT","CONS-AMOUNT",$A$1:$A$4,$A91:$B91,AR$5:AR$10,"#") -> #NAME? | AS91: =AO91-AQ91 -> #NAME? | AU91: =W91+AC91+AI91+AO91 -> #NAME? | AW91: =Y91+AE91+AK91+AQ91 -> #NAME? | AY91: =AU91-AW91 -> #NAME? | BA91: =+Q91-AO91 -> #NAME? | BC91: =+S91-AQ91 -> #NAME? | BE91: =BA91-BC91 -> #NAME? | BG91: =_xll.GetCtData("CO-AMOUNT","CONS-AMOUNT",$A$1:$A$4,$A91:$B91,BH$5:BH$10,"#La dimension AC (Rubrique) doit être initialisée") -> #NAME? | BI91: =_xll.GetCtData("CO-AMOUNT","CONS-AMOUNT",$A$1:$A$4,$A91:$B91,BJ$5:BJ$10,"#La dimension AC (Rubrique) doit être initialisée") -> #NAME? | BK91: =BG91-BI91 -> #NAME? | BN91: =_xll.GetCtData("CO-AMOUNT","CONS-AMOUNT",$A$1:$A$4,$A91:$B91,BO$5:BO$10,"#") -> #NAME? | BP91: =_xll.GetCtData("CO-AMOUNT","CONS-AMOUNT",$A$1:$A$4,$A91:$B91,BQ$5:BQ$10,"#") -> #NAME? | BR91: =BN91-BP91 -> #NAME?
A92: {OA=OA010O} | B92: {RU=G-FRMP}+{RU=P-FRMP}+{RU=G-FRAR}+{RU=P-FRAR} | C92: FR | D92: Advisory Residential Sales | E92: =_xll.GetCtData("CO-AMOUNT","CONS-AMOUNT",$A$1:$A$4,$A92:$B92,E$5:E$10,"#") -> #NAME? | G92: =_xll.GetCtData("CO-AMOUNT","CONS-AMOUNT",$A$1:$A$4,$A92:$B92,G$5:G$10,"#") -> #NAME? | I92: =E92-G92 -> #NAME? | K92: =_xll.GetCtData("CO-AMOUNT","CONS-AMOUNT",$A$1:$A$4,$A92:$B92,K$5:K$10,"#") -> #NAME? | M92: =_xll.GetCtData("CO-AMOUNT","CONS-AMOUNT",$A$1:$A$4,$A92:$B92,M$5:M$10,"#") -> #NAME? | O92: =K92-M92 -> #NAME? | Q92: =_xll.GetCtData("CO-AMOUNT","CONS-AMOUNT",$A$1:$A$4,$A92:$B92,Q$5:Q$10,"#") -> #NAME? | S92: =_xll.GetCtData("CO-AMOUNT","CONS-AMOUNT",$A$1:$A$4,$A92:$B92,S$5:S$10,"#") -> #NAME? | U92: =Q92-S92 -> #NAME? | W92: =_xll.GetCtData("CO-AMOUNT","CONS-AMOUNT",$A$1:$A$4,$A92:$B92,W$5:W$10,"#") -> #NAME? | Y92: =_xll.GetCtData("CO-AMOUNT","CONS-AMOUNT",$A$1:$A$4,$A92:$B92,Y$5:Y$10,"#") -> #NAME? | AA92: =W92-Y92 -> #NAME? | AC92: =_xll.GetCtData("CO-AMOUNT","CONS-AMOUNT",$A$1:$A$4,$A92:$B92,AC$5:AC$10,"#") -> #NAME? | AE92: =_xll.GetCtData("CO-AMOUNT","CONS-AMOUNT",$A$1:$A$4,$A92:$B92,AE$5:AE$10,"#") -> #NAME? | AG92: =AC92-AE92 -> #NAME? | AI92: =_xll.GetCtData("CO-AMOUNT","CONS-AMOUNT",$A$1:$A$4,$A92:$B92,AI$5:AI$10,"#") -> #NAME? | AK92: =_xll.GetCtData("CO-AMOUNT","CONS-AMOUNT",$A$1:$A$4,$A92:$B92,AK$5:AK$10,"#") -> #NAME? | AM92: =AI92-AK92 -> #NAME? | AO92: =_xll.GetCtData("CO-AMOUNT","CONS-AMOUNT",$A$1:$A$4,$A92:$B92,AO$5:AO$10,"#") -> #NAME? | AQ92: =_xll.GetCtData("CO-AMOUNT","CONS-AMOUNT",$A$1:$A$4,$A92:$B92,AQ$5:AQ$10,"#") -> #NAME? | AS92: =AO92-AQ92 -> #NAME? | AU92: =W92+AC92+AI92+AO92 -> #NAME? | AW92: =Y92+AE92+AK92+AQ92 -> #NAME? | AY92: =AU92-AW92 -> #NAME? | BA92: =+Q92-AO92 -> #NAME? | BC92: =+S92-AQ92 -> #NAME? | BE92: =BA92-BC92 -> #NAME? | BG92: =_xll.GetCtData("CO-AMOUNT","CONS-AMOUNT",$A$1:$A$4,$A92:$B92,BG$5:BG$10,"#") -> #NAME? | BI92: =_xll.GetCtData("CO-AMOUNT","CONS-AMOUNT",$A$1:$A$4,$A92:$B92,BI$5:BI$10,"#") -> #NAME? | BK92: =BG92-BI92 -> #NAME? | BN92: =_xll.GetCtData("CO-AMOUNT","CONS-AMOUNT",$A$1:$A$4,$A92:$B92,BN$5:BN$10,"#") -> #NAME? | BP92: =_xll.GetCtData("CO-AMOUNT","CONS-AMOUNT",$A$1:$A$4,$A92:$B92,BP$5:BP$10,"#") -> #NAME? | BR92: =BN92-BP92 -> #NAME?
A93: {OA=OA005}+{OA=OA005O}+{OA=OA006} | B93: RU=G-CENTRAL | C93: CENTRAL | D93: G-central HD | E93: =_xll.GetCtData("CO-AMOUNT","CONS-AMOUNT",$A$1:$A$4,$A93:$B93,E$5:E$10,"#") -> #NAME? | G93: =_xll.GetCtData("CO-AMOUNT","CONS-AMOUNT",$A$1:$A$4,$A93:$B93,G$5:G$10,"#") -> #NAME? | I93: =E93-G93 -> #NAME? | K93: =_xll.GetCtData("CO-AMOUNT","CONS-AMOUNT",$A$1:$A$4,$A93:$B93,K$5:K$10,"#-19035") -> #NAME? | M93: =_xll.GetCtData("CO-AMOUNT","CONS-AMOUNT",$A$1:$A$4,$A93:$B93,M$5:M$10,"#-15071") -> #NAME? | O93: =K93-M93 -> #NAME? | Q93: =_xll.GetCtData("CO-AMOUNT","CONS-AMOUNT",$A$1:$A$4,$A93:$B93,Q$5:Q$10,"#-19035") -> #NAME? | S93: =_xll.GetCtData("CO-AMOUNT","CONS-AMOUNT",$A$1:$A$4,$A93:$B93,S$5:S$10,"#-15071") -> #NAME? | U93: =Q93-S93 -> #NAME? | W93: =_xll.GetCtData("CO-AMOUNT","CONS-AMOUNT",$A$1:$A$4,$A93:$B93,W$5:W$10,"#") -> #NAME? | Y93: =_xll.GetCtData("CO-AMOUNT","CONS-AMOUNT",$A$1:$A$4,$A93:$B93,Y$5:Y$10,"#") -> #NAME? | AA93: =W93-Y93 -> #NAME? | AC93: =_xll.GetCtData("CO-AMOUNT","CONS-AMOUNT",$A$1:$A$4,$A93:$B93,AC$5:AC$10,"#") -> #NAME? | AE93: =_xll.GetCtData("CO-AMOUNT","CONS-AMOUNT",$A$1:$A$4,$A93:$B93,AE$5:AE$10,"#") -> #NAME? | AG93: =AC93-AE93 -> #NAME? | AI93: =_xll.GetCtData("CO-AMOUNT","CONS-AMOUNT",$A$1:$A$4,$A93:$B93,AI$5:AI$10,"#") -> #NAME? | AK93: =_xll.GetCtData("CO-AMOUNT","CONS-AMOUNT",$A$1:$A$4,$A93:$B93,AK$5:AK$10,"#") -> #NAME? | AM93: =AI93-AK93 -> #NAME? | AO93: =_xll.GetCtData("CO-AMOUNT","CONS-AMOUNT",$A$1:$A$4,$A93:$B93,AO$5:AO$10,"#") -> #NAME? | AQ93: =_xll.GetCtData("CO-AMOUNT","CONS-AMOUNT",$A$1:$A$4,$A93:$B93,AQ$5:AQ$10,"#-750") -> #NAME? | AS93: =AO93-AQ93 -> #NAME? | AU93: =W93+AC93+AI93+AO93 -> #NAME? | AW93: =Y93+AE93+AK93+AQ93 -> #NAME? | AY93: =AU93-AW93 -> #NAME? | BA93: =+Q93-AO93 -> #NAME? | BC93: =+S93-AQ93 -> #NAME? | BE93: =BA93-BC93 -> #NAME? | BG93: =_xll.GetCtData("CO-AMOUNT","CONS-AMOUNT",$A$1:$A$4,$A93:$B93,BG$5:BG$10,"#") -> #NAME? | BI93: =_xll.GetCtData("CO-AMOUNT","CONS-AMOUNT",$A$1:$A$4,$A93:$B93,BI$5:BI$10,"#-750") -> #NAME? | BK93: =BG93-BI93 -> #NAME? | BN93: =_xll.GetCtData("CO-AMOUNT","CONS-AMOUNT",$A$1:$A$4,$A93:$B93,BN$5:BN$10,"#") -> #NAME? | BP93: =_xll.GetCtData("CO-AMOUNT","CONS-AMOUNT",$A$1:$A$4,$A93:$B93,BP$5:BP$10,"#") -> #NAME? | BR93: =BN93-BP93 -> #NAME?
A94: OA=OA005 | B94: {RU=GT-BALE2}+{RU=GT-TUT}+{RU=G-ITBNL}+{RU=GT-BCESTE} | C94: GROUPE | D94: =CHOOSE([6]Traduction!$A$2,[6]Traduction!$A87,[6]Traduction!$B87) -> Group Costs | E94: =_xll.GetCtData("CO-AMOUNT","CONS-AMOUNT",$A$1:$A$4,$A94:$B94,E$4:E$9,"#-2047,644") -> #NAME? | G94: =_xll.GetCtData("CO-AMOUNT","CONS-AMOUNT",$A$1:$A$4,$A94:$B94,G$4:G$9,"#-1442,5") -> #NAME? | I94: =E94-G94 -> #NAME? | K94: =_xll.GetCtData("CO-AMOUNT","CONS-AMOUNT",$A$1:$A$4,$A94:$B94,K$4:K$9,"#-11678,936") -> #NAME? | M94: =_xll.GetCtData("CO-AMOUNT","CONS-AMOUNT",$A$1:$A$4,$A94:$B94,M$4:M$9,"#-11655,902") -> #NAME? | O94: =K94-M94 -> #NAME? | Q94: =_xll.GetCtData("CO-AMOUNT","CONS-AMOUNT",$A$1:$A$4,$A94:$B94,Q$4:Q$9,"#-13726,58") -> #NAME? | S94: =_xll.GetCtData("CO-AMOUNT","CONS-AMOUNT",$A$1:$A$4,$A94:$B94,S$4:S$9,"#-13098,402") -> #NAME? | U94: =Q94-S94 -> #NAME? | AA94: =W94-Y94 -> 0 | AG94: =AC94-AE94 -> 0 | AM94: =AI94-AK94 -> 0 | AS94: =AO94-AQ94 -> 0 | AU94: =W94+AC94+AI94+AO94 -> 0 | AW94: =Y94+AE94+AK94+AQ94 -> 0 | AY94: =AU94-AW94 -> 0 | BA94: =+Q94-AO94 -> #NAME? | BC94: =+S94-AQ94 -> #NAME? | BE94: =BA94-BC94 -> #NAME? | BK94: =BG94-BI94 -> 0 | BR94: =BN94-BP94 -> 0
D95: Total | E95: =+E94+E93+E91+E88+E69+E47+E34+E17+E83+E92 -> #NAME? | G95: =+G94+G93+G91+G88+G69+G47+G34+G17+G83+G92 -> #NAME? | I95: =+I94+I93+I91+I88+I69+I47+I34+I17++I83+I92 -> #NAME? | K95: =+K94+K93+K91+K88+K69+K47+K34+K17+K83+K92 -> #NAME? | M95: =+M94+M93+M91+M88+M69+M47+M34+M17+M83+M92 -> #NAME? | O95: =+O94+O93+O91+O88+O69+O47+O34+O17+O83+O92 -> #NAME? | Q95: =+Q94+Q93+Q91+Q88+Q69+Q47+Q34+Q17+Q83+Q92 -> #NAME? | R95: =+R94+R93+R91+R88+R69+R47+R34+#REF!+R17+#REF!+R83+R92 -> #REF! | S95: =+S94+S93+S91+S88+S69+S47+S34+S17+S83+S92 -> #NAME? | U95: =+U94+U93+U91+U88+U69+U47+U34+U17+U83+U92 -> #NAME? | W95: =+W94+W93+W91+W88+W69+W47+W34+W17+W83+W92 -> #NAME? | X95: =+X94+X93+X91+X88+X69+X47+X34+#REF!+X17+#REF!+X83+X92 -> #REF! | Y95: =+Y94+Y93+Y91+Y88+Y69+Y47+Y34+Y17+Y83+Y92 -> #NAME? | AA95: =+AA94+AA93+AA91+AA88+AA69+AA47+AA34+#REF!+AA17+#REF!+AA83+AA92 -> #NAME? | AC95: =+AC94+AC93+AC91+AC88+AC69+AC47+AC34+AC17+AC83+AC92 -> #NAME? | AD95: =+AD94+AD93+AD91+AD88+AD69+AD47+AD34+#REF!+AD17+#REF!+AD83+AD92 -> #REF! | AE95: =+AE94+AE93+AE91+AE88+AE69+AE47+AE34+AE17+AE83+AE92 -> #NAME? | AG95: =+AG94+AG93+AG91+AG88+AG69+AG47+AG34+#REF!+AG17+#REF!+AG83+AG92 -> #NAME? | AI95: =+AI94+AI93+AI91+AI88+AI69+AI47+AI34+AI17+AI83+AI92 -> #NAME? | AJ95: =+AJ94+AJ93+AJ91+AJ88+AJ69+AJ47+AJ34+#REF!+AJ17+#REF!+AJ83+AJ92 -> #REF! | AK95: =+AK94+AK93+AK91+AK88+AK69+AK47+AK34+AK17+AK83+AK92 -> #NAME? | AM95: =+AM94+AM93+AM91+AM88+AM69+AM47+AM34+#REF!+AM17+#REF!+AM83+AM92 -> #NAME? | AO95: =+AO94+AO93+AO91+AO88+AO69+AO47+AO34+AO17+AO83+AO92 -> #NAME? | AP95: =+AP94+AP93+AP91+AP88+AP69+AP47+AP34+#REF!+AP17+#REF!+AP83+AP92 -> #REF! | AQ95: =+AQ94+AQ93+AQ91+AQ88+AQ69+AQ47+AQ34+AQ17+AQ83+AQ92 -> #NAME? | AS95: =+AS94+AS93+AS91+AS88+AS69+AS47+AS34+#REF!+AS17+#REF!+AS83+AS92 -> #NAME? | AU95: =W95+AC95+AI95+AO95 -> #NAME? | AW95: =Y95+AE95+AK95+AQ95 -> #NAME? | AY95: =+AY94+AY93+AY91+AY88+AY69+AY47+AY34+#REF!+AY17+#REF!+AY83+AY92 -> #NAME? | BA95: =+Q95-AO95 -> #NAME? | BC95: =+S95-AQ95 -> #NAME? | BE95: =BA95-BC95 -> #NAME? | BG95: =+BG94+BG93+BG91+BG88+BG69+BG47+BG34+#REF!+BG17+#REF!+BG83+BG92 -> #NAME? | BH95: =+BH94+BH93+BH91+BH88+BH69+BH47+BH34+#REF!+BH17+#REF!+BH83+BH92 -> #REF! | BI95: =+BI94+BI93+BI91+BI88+BI69+BI47+BI34+#REF!+BI17+#REF!+BI83+BI92 -> #NAME? | BK95: =+BK94+BK93+BK91+BK88+BK69+BK47+BK34+#REF!+BK17+#REF!+BK83+BK92 -> #NAME? | BN95: =+BN94+BN93+BN91+BN88+BN69+BN47+BN34+#REF!+BN17+#REF!+BN83+BN92 -> #NAME? | BO95: =+BO94+BO93+BO91+BO88+BO69+BO47+BO34+#REF!+BO17+#REF!+BO83+BO92 -> #REF! | BP95: =+BP94+BP93+BP91+BP88+BP69+BP47+BP34+#REF!+BP17+#REF!+BP83+BP92 -> #NAME? | BR95: =+BR94+BR93+BR91+BR88+BR69+BR47+BR34+#REF!+BR17+#REF!+BR83+BR92 -> #NAME?
A96: OA sum AR001 | B96: RU sum AF001 | D96: Total Périmètre courant | E96: =_xll.GetCtData("CO-AMOUNT","CONS-AMOUNT",$A$1:$A$4,$A96:$B96,E$5:E$10,"#92851,3164471775") -> #NAME? | G96: =_xll.GetCtData("CO-AMOUNT","CONS-AMOUNT",$A$1:$A$4,$A96:$B96,G$5:G$10,"#92887,0463759191") -> #NAME? | I96: =E96-G96 -> #NAME? | K96: =_xll.GetCtData("CO-AMOUNT","CONS-AMOUNT",$A$1:$A$4,$A96:$B96,K$5:K$10,"#-176532,576534489") -> #NAME? | M96: =_xll.GetCtData("CO-AMOUNT","CONS-AMOUNT",$A$1:$A$4,$A96:$B96,M$5:M$10,"#-178213,931441316") -> #NAME? | O96: =K96-M96 -> #NAME? | Q96: =_xll.GetCtData("CO-AMOUNT","CONS-AMOUNT",$A$1:$A$4,$A96:$B96,Q$5:Q$10,"#-84377,5235658398") -> #NAME? | S96: =_xll.GetCtData("CO-AMOUNT","CONS-AMOUNT",$A$1:$A$4,$A96:$B96,S$5:S$10,"#-85527,6383550567") -> #NAME? | U96: =Q96-S96 -> #NAME? | W96: =_xll.GetCtData("CO-AMOUNT","CONS-AMOUNT",$A$1:$A$4,$A96:$B96,W$5:W$10,"#-119,137061911572") -> #NAME? | Y96: =_xll.GetCtData("CO-AMOUNT","CONS-AMOUNT",$A$1:$A$4,$A96:$B96,Y$5:Y$10,"#137,488776191027") -> #NAME? | AA96: =W96-Y96 -> #NAME? | AC96: =_xll.GetCtData("CO-AMOUNT","CONS-AMOUNT",$A$1:$A$4,$A96:$B96,AC$5:AC$10,"#22,98") -> #NAME? | AE96: =_xll.GetCtData("CO-AMOUNT","CONS-AMOUNT",$A$1:$A$4,$A96:$B96,AE$5:AE$10,"#9,264") -> #NAME? | AG96: =AC96-AE96 -> #NAME? | AI96: =_xll.GetCtData("CO-AMOUNT","CONS-AMOUNT",$A$1:$A$4,$A96:$B96,AI$5:AI$10,"#-65,1913655499593") -> #NAME? | AK96: =_xll.GetCtData("CO-AMOUNT","CONS-AMOUNT",$A$1:$A$4,$A96:$B96,AK$5:AK$10,"#385,177385203544") -> #NAME? | AM96: =AI96-AK96 -> #NAME? | AO96: =_xll.GetCtData("CO-AMOUNT","CONS-AMOUNT",$A$1:$A$4,$A96:$B96,AO$5:AO$10,"#-12821,1653475363")-AO98 -> #NAME? | AQ96: =_xll.GetCtData("CO-AMOUNT","CONS-AMOUNT",$A$1:$A$4,$A96:$B96,AQ$5:AQ$10,"#-12817,7351520246")-AQ98 -> #NAME? | AS96: =AO96-AQ96 -> #NAME? | BG96: =_xll.GetCtData("CO-AMOUNT","CONS-AMOUNT",$A$1:$A$4,$A96:$B96,BG$5:BG$10,"#-6631,80636538518")-BG98 -> #NAME? | BI96: =_xll.GetCtData("CO-AMOUNT","CONS-AMOUNT",$A$1:$A$4,$A96:$B96,BI$5:BI$10,"#-6600,17773957915")-BI98 -> #NAME? | BK96: =BG96-BI96 -> #NAME? | BN96: =_xll.GetCtData("CO-AMOUNT","CONS-AMOUNT",$A$1:$A$4,$A96:$B96,BN$5:BN$10,"#-6189,3589821511")-BN98 -> #NAME? | BP96: =_xll.GetCtData("CO-AMOUNT","CONS-AMOUNT",$A$1:$A$4,$A96:$B96,BP$5:BP$10,"#-6217,55741244546")-BP98 -> #NAME? | BR96: =BN96-BP96 -> #NAME?
D97: Ctrl | E97: =+E95-E96 -> #NAME? | G97: =+G95-G96 -> #NAME? | I97: =+I95-I96 -> #NAME? | K97: =+K95-K96 -> #NAME? | M97: =+M95-M96 -> #NAME? | O97: =+O95-O96 -> #NAME? | Q97: =+Q95-Q96 -> #NAME? | S97: =+S95-S96 -> #NAME? | U97: =+U95-U96 -> #NAME? | W97: =+W95-W96 -> #NAME? | Y97: =+Y95-Y96 -> #NAME? | AA97: =+AA95-AA96 -> #NAME? | AC97: =+AC95-AC96 -> #NAME? | AE97: =+AE95-AE96 -> #NAME? | AG97: =+AG95-AG96 -> #NAME? | AI97: =+AI95-AI96 -> #NAME? | AK97: =+AK95-AK96 -> #NAME? | AM97: =+AM95-AM96 -> #NAME? | AO97: =+AO95-AO96 -> #NAME? | AQ97: =+AQ95-AQ96 -> #NAME? | AS97: =+AS95-AS96 -> #NAME? | BG97: =+BG95-BG96 -> #NAME? | BI97: =+BI95-BI96 -> #NAME? | BK97: =+BK95-BK96 -> #NAME? | BN97: =+BN95-BN96 -> #NAME? | BP97: =+BP95-BP96 -> #NAME? | BR97: =+BR95-BR96 -> #NAME?
A98: OA=OA005 | B98: {RU=GT-TUT}+{RU=GT-BCESTE} | D98: Coûts Groupe | AO98: =_xll.GetCtData("CO-AMOUNT","CONS-AMOUNT",$A$1:$A$4,$A98:$B98,AO$5:AO$10,"#-10159,263") -> #NAME? | AQ98: =_xll.GetCtData("CO-AMOUNT","CONS-AMOUNT",$A$1:$A$4,$A98:$B98,AQ$5:AQ$10,"#-10159,263") -> #NAME? | AS98: =+AS96-AS97 -> #NAME? | BG98: =_xll.GetCtData("CO-AMOUNT","CONS-AMOUNT",$A$1:$A$4,$A98:$B98,BG$5:BG$10,"#-6648,763") -> #NAME? | BI98: =_xll.GetCtData("CO-AMOUNT","CONS-AMOUNT",$A$1:$A$4,$A98:$B98,BI$5:BI$10,"#-6648,763") -> #NAME? | BK98: =+BK96-BK97 -> #NAME? | BN98: =_xll.GetCtData("CO-AMOUNT","CONS-AMOUNT",$A$1:$A$4,$A98:$B98,BN$5:BN$10,"#-3510,5") -> #NAME? | BP98: =_xll.GetCtData("CO-AMOUNT","CONS-AMOUNT",$A$1:$A$4,$A98:$B98,BP$5:BP$10,"#-3510,5") -> #NAME? | BR98: =+BR96-BR97 -> #NAME?
D99: Arbitrages | E99: 0 | I99: =E99-G99 -> 0 | K99: 0 | O99: =K99-M99 -> 0 | Q99: =+E99+K99 -> 0 | U99: =Q99-S99 -> 0 | AO99: =AO97 -> #NAME? | BE99: =+U99 -> 0 | BG99: =BG97 -> #NAME? | BN99: =BN97 -> #NAME?
D100: Résultats par pays | E100: =E14 -> Actual Q1 2026 | G100: =G14 -> Estimate March Q1 2026 | I100: =I14 -> Variances | K100: =K14 -> Actual Q1 2026 | M100: =M14 -> Estimate March Q1 2026 | O100: =O14 -> Variances | Q100: =Q14 -> Actual Q1 2026 | S100: =S14 -> Estimate March Q1 2026 | U100: =O100 -> Variances | W100: =W14 -> Actual Q1 2026 | Y100: =Y14 -> Estimate March Q1 2026 | AA100: =V100 -> 0 | AC100: =AC14 -> Actual Q1 2026 | AE100: =AE14 -> Estimate March Q1 2026 | AG100: =AA100 -> 0 | AI100: =AI14 -> Actual Q1 2026 | AK100: =AK14 -> Estimate March Q1 2026 | AM100: =AG100 -> 0 | AO100: =AO14 -> Actual Q1 2026 | AQ100: =AQ14 -> Estimate March Q1 2026 | AS100: =AM100 -> 0 | AU100: =AU14 -> Actual Q1 2026 | AW100: =AW14 -> Estimate March Q1 2026 | AY100: =AS100 -> 0 | BA100: =BA14 -> Actual Q1 2026 | BC100: =BC14 -> Estimate March Q1 2026 | BE100: =BE14 -> Variances excl. Management Fees and equivalent | BG100: =BG14 -> Actual Q1 2026 | BI100: =BI14 -> Estimate March Q1 2026 | BK100: =BE100 -> Variances excl. Management Fees and equivalent | BN100: =BN14 -> 0 | BP100: =BP14 -> 0 | BR100: =BL100 -> 0
D101: France | E101: =E19+E33+E37+E55+E67+E68+E71+E72+E89+E92 -> #NAME? | G101: =G19+G33+G37+G55+G67+G68+G71+G72+G89+G92 -> #NAME? | H101: =H19+#REF!+H37+#REF!+H55+H71+H72+H88+#REF!-#REF!+H36 -> #REF! | I101: =E101-G101 -> #NAME? | K101: =K19+K33+K37+K55+K67+K68+K71+K72+K89+K92 -> #NAME? | M101: =M19+M33+M37+M55+M67+M68+M71+M72+M89+M92 -> #NAME? | O101: =K101-M101 -> #NAME? | Q101: =Q19+Q33+Q37+Q55+Q67+Q68+Q71+Q72+Q89+Q92 -> #NAME? | S101: =S19+S33+S37+S55+S67+S68+S71+S72+S89+S92 -> #NAME? | U101: =Q101-S101 -> #NAME? | W101: =W19+#REF!+W33+#REF!+#REF!+W37+W55+W67+W68+W71+W72+W89+#REF!+W92 -> #NAME? | Y101: =Y19+#REF!+Y33+#REF!+#REF!+Y37+Y55+Y67+Y68+Y71+Y72+Y89+#REF!+Y92 -> #NAME? | AA101: =W101-Y101 -> #NAME? | AC101: =AC19+#REF!+AC33+#REF!+#REF!+AC37+AC55+AC67+AC68+AC71+AC72+AC89+#REF!+AC92 -> #NAME? | AE101: =AE19+#REF!+AE33+#REF!+#REF!+AE37+AE55+AE67+AE68+AE71+AE72+AE89+#REF!+AE92 -> #NAME? | AG101: =AC101-AE101 -> #NAME? | AI101: =AI19+#REF!+AI33+#REF!+#REF!+AI37+AI55+AI67+AI68+AI71+AI72+AI89+#REF!+AI92+AI87 -> #NAME? | AK101: =AK19+#REF!+AK33+#REF!+#REF!+AK37+AK55+AK67+AK68+AK71+AK72+AK89+#REF!+AK92+AK87 -> #NAME? | AM101: =AI101-AK101 -> #NAME? | AO101: =AO19+#REF!+AO33+#REF!+#REF!+AO37+AO55+AO67+AO68+AO71+AO72+AO89+#REF!+AO92+AO87 -> #NAME? | AQ101: =AQ19+#REF!+AQ33+#REF!+#REF!+AQ37+AQ55+AQ67+AQ68+AQ71+AQ72+AQ89+#REF!+AQ92+AQ87 -> #NAME? | AS101: =AO101-AQ101 -> #NAME? | AU101: =AU19+#REF!+AU33+#REF!+#REF!+AU37+AU55+AU67+AU68+AU71+AU72+AU89+#REF!+AU92+AU87 -> #NAME? | AW101: =AW19+#REF!+AW33+#REF!+#REF!+AW37+AW55+AW67+AW68+AW71+AW72+AW89+#REF!+AW92+AW87 -> #NAME? | AY101: =AU101-AW101 -> #NAME? | BA101: =BA19+#REF!+BA33+#REF!+#REF!+BA37+BA55+BA67+BA68+BA71+BA72+BA89+#REF!+BA92 -> #NAME? | BC101: =BC19+#REF!+BC33+#REF!+#REF!+BC37+BC55+BC67+BC68+BC71+BC72+BC89+#REF!+BC92 -> #NAME? | BE101: =BA101-BC101 -> #NAME? | BG101: =BG19+#REF!+BG33+#REF!+#REF!+BG37+BG55+BG67+BG68+BG71+BG72+BG89+#REF!+BG92+BG87 -> #NAME? | BI101: =BI19+#REF!+BI33+#REF!+#REF!+BI37+BI55+BI67+BI68+BI71+BI72+BI89+#REF!+BI92+BI87 -> #NAME? | BK101: =BG101-BI101 -> #NAME? | BN101: =BN19+#REF!+BN33+#REF!+#REF!+BN37+BN55+BN67+BN68+BN71+BN72+BN89+#REF!+BN92+BN87 -> #NAME? | BP101: =BP19+#REF!+BP33+#REF!+#REF!+BP37+BP55+BP67+BP68+BP71+BP72+BP89+#REF!+BP92+BP87 -> #NAME? | BR101: =BN101-BP101 -> #NAME?
D102: UK | E102: =E30+E43+E49+E74 -> #NAME? | G102: =G30+G43+G49+G74 -> #NAME? | I102: =E102-G102 -> #NAME? | K102: =K30+K43+K49+K74 -> #NAME? | M102: =M30+M43+M49+M74 -> #NAME? | O102: =K102-M102 -> #NAME? | Q102: =Q30+Q43+Q49+Q74 -> #NAME? | S102: =S30+S43+S49+S74 -> #NAME? | U102: =Q102-S102 -> #NAME? | W102: =W30+W43+W49+W74 -> #NAME? | Y102: =Y30+Y43+Y49+Y74 -> #NAME? | AA102: =W102-Y102 -> #NAME? | AC102: =AC30+AC43+AC49+AC74 -> #NAME? | AE102: =AE30+AE43+AE49+AE74 -> #NAME? | AG102: =AC102-AE102 -> #NAME? | AI102: =AI30+AI43+AI49+AI74 -> #NAME? | AK102: =AK30+AK43+AK49+AK74 -> #NAME? | AM102: =AI102-AK102 -> #NAME? | AO102: =AO30+AO43+AO49+AO74 -> #NAME? | AQ102: =AQ30+AQ43+AQ49+AQ74 -> #NAME? | AS102: =AO102-AQ102 -> #NAME? | AU102: =AU30+AU43+AU49+AU74 -> #NAME? | AW102: =AW30+AW43+AW49+AW74 -> #NAME? | AY102: =AU102-AW102 -> #NAME? | BA102: =BA30+BA43+BA49+BA74 -> #NAME? | BC102: =BC30+BC43+BC49+BC74 -> #NAME? | BE102: =BA102-BC102 -> #NAME? | BG102: =BG30+BG43+BG49+BG74 -> #NAME? | BI102: =BI30+BI43+BI49+BI74 -> #NAME? | BK102: =BG102-BI102 -> #NAME? | BN102: =BN30+BN43+BN49+BN74 -> #NAME? | BP102: =BP30+BP43+BP49+BP74 -> #NAME? | BR102: =BN102-BP102 -> #NAME?
...

Sheet Réalisé Vs Estimé (Valeurs)
A1: SC=BNPPI-GEST
A2: CC=EUR
A3: FA sum AR002
A4: FL=F99 | E4: {AC=GFB001}+{AC=GFB002}+{AC=GFB004}+{AC=GFB008}+{AC=GFB009}+{AC=GFB003} | G4: {AC=GFB001}+{AC=GFB002}+{AC=GFB004}+{AC=GFB008}+{AC=GFB009}+{AC=GFB003} | K4: {AC=GFB005}+{AC=GFB006}+{AC=GFB110}+{AC=GFB111}+{AC=GFB112}+{AC=GFB120}+{AC=GFB121}+{AC=GFB122}+{AC=GFB100}+{AC=GFB101}+{AC=GFB102}+{AC=GFB130}+{AC=GFB131}+{AC=GFB132} | M4: {AC=GFB005}+{AC=GFB006}+{AC=GFB110}+{AC=GFB111}+{AC=GFB112}+{AC=GFB120}+{AC=GFB121}+{AC=GFB122}+{AC=GFB100}+{AC=GFB101}+{AC=GFB102}+{AC=GFB130}+{AC=GFB131}+{AC=GFB132} | Q4: AC sum RGFB | S4: AC sum RGFB | W4: AC sum RGFB | Y4: AC sum RGFB | AC4: AC sum RGFB | AE4: AC sum RGFB | AI4: AC sum RGFB | AK4: AC sum RGFB | AO4: AC sum RGFB | AQ4: AC sum RGFB | BA4: AC sum RGFB | BB4: AC sum RGFB | BC4: AC sum RGFB | BG4: AC sum RGFB | BI4: AC sum RGFB | BN4: AC sum RGFB | BO4: 0 | BP4: AC sum RGFB
E5: CA=A | G5: CA=E | K5: CA=A | L5: CA=A | M5: CA=E | N5: CA=E | Q5: CA=A | R5: CA=A | S5: CA=E | T5: CA=E | W5: CA=A | X5: CA=A | Y5: CA=E | Z5: CA=E | AC5: CA=A | AD5: CA=A | AE5: CA=E | AF5: CA=E | AI5: CA=A | AJ5: CA=A | AK5: CA=E | AL5: CA=E | AO5: CA=A | AP5: CA=A | AQ5: CA=E | AR5: CA=E | BA5: CA=A | BB5: CA=A | BC5: CA=E | BD5: CA=E | BG5: CA=A | BH5: CA=A | BI5: CA=E | BJ5: CA=E | BN5: CA=A | BO5: CA=A | BP5: CA=E | BQ5: CA=E
E6: DP=2026.03 | F6: DP=2024.13 | G6: DP=2026.03 | K6: DP=2026.03 | L6: DP=2026.03 | M6: DP=2026.03 | N6: DP=2026.03 | Q6: DP=2026.03 | R6: DP=2026.03 | S6: DP=2026.03 | T6: DP=2026.03 | W6: DP=2026.03 | X6: DP=2026.03 | Y6: DP=2026.03 | Z6: DP=2026.03 | AC6: DP=2026.03 | AD6: DP=2026.03 | AE6: DP=2026.03 | AF6: DP=2026.03 | AI6: DP=2026.03 | AJ6: DP=2026.03 | AK6: DP=2026.03 | AL6: DP=2026.03 | AO6: DP=2026.03 | AP6: DP=2026.03 | AQ6: DP=2026.03 | AR6: DP=2026.03 | BA6: DP=2026.03 | BB6: DP=2026.03 | BC6: DP=2026.03 | BD6: DP=2026.03 | BG6: DP=2026.03 | BH6: DP=2026.03 | BI6: DP=2026.03 | BJ6: DP=2026.03 | BN6: DP=2026.03 | BO6: DP=2026.03 | BP6: DP=2026.03 | BQ6: DP=2026.03
E7: PE=2026.03 | F7: PE=2024.13 | G7: PE=2026.03 | K7: PE=2026.03 | L7: PE=2026.03 | M7: PE=2026.03 | N7: PE=2026.03 | Q7: PE=2026.03 | R7: PE=2026.03 | S7: PE=2026.03 | T7: PE=2026.03 | W7: PE=2026.03 | X7: PE=2026.03 | Y7: PE=2026.03 | Z7: PE=2026.03 | AC7: PE=2026.03 | AD7: PE=2026.03 | AE7: PE=2026.03 | AF7: PE=2026.03 | AI7: PE=2026.03 | AJ7: PE=2026.03 | AK7: PE=2026.03 | AL7: PE=2026.03 | AO7: PE=2026.03 | AP7: PE=2026.03 | AQ7: PE=2026.03 | AR7: PE=2026.03 | BA7: PE=2026.03 | BB7: PE=2026.03 | BC7: PE=2026.03 | BD7: PE=2026.03 | BG7: PE=2026.03 | BH7: PE=2026.03 | BI7: PE=2026.03 | BJ7: PE=2026.03 | BN7: PE=2026.03 | BO7: PE=2026.03 | BP7: PE=2026.03 | BQ7: PE=2026.03
E8: AU sum GEST00 | G8: AU sum GEST00 | K8: AU sum GEST00 | L8: AU sum GEST00 | M8: AU sum GEST00 | N8: AU sum GEST00 | Q8: AU sum GEST00 | R8: AU sum GEST00 | S8: AU sum GEST00 | T8: AU sum GEST00 | W8: AU sum GEST00 | X8: AU sum GEST00 | Y8: AU sum GEST00 | Z8: AU sum GEST00 | AC8: AU sum GEST00 | AD8: AU sum GEST00 | AE8: AU sum GEST00 | AF8: AU sum GEST00 | AI8: AU sum GEST00 | AJ8: AU sum GEST00 | AK8: AU sum GEST00 | AL8: AU sum GEST00 | AO8: AU sum GEST00 | AP8: AU sum GEST00 | AQ8: AU sum GEST00 | AR8: AU sum GEST00 | BA8: AU sum GEST00 | BB8: AU sum GEST00 | BC8: AU sum GEST00 | BD8: AU sum GEST00 | BG8: AU sum GEST00 | BH8: AU sum GEST00 | BI8: AU sum GEST00 | BJ8: AU sum GEST00 | BN8: AU sum GEST00 | BO8: AU sum GEST00 | BP8: AU sum GEST00 | BQ8: AU sum GEST00
E9: VA=RECOMPO | G9: VA=RECOMPO | K9: VA=RECOMPO | L9: VA=RECOMPO | M9: VA=RECOMPO | N9: VA=RECOMPO | Q9: VA=RECOMPO | R9: VA=RECOMPO | S9: VA=RECOMPO | T9: VA=RECOMPO | W9: VA=RECOMPO | X9: VA=RECOMPO | Y9: VA=RECOMPO | Z9: VA=RECOMPO | AC9: VA=RECOMPO | AD9: VA=RECOMPO | AE9: VA=RECOMPO | AF9: VA=RECOMPO | AI9: VA=RECOMPO | AJ9: VA=RECOMPO | AK9: VA=RECOMPO | AL9: VA=RECOMPO | AO9: VA=RECOMPO | AP9: VA=RECOMPO | AQ9: VA=RECOMPO | AR9: VA=RECOMPO | BA9: VA=RECOMPO | BB9: VA=RECOMPO | BC9: VA=RECOMPO | BD9: VA=RECOMPO | BG9: VA=RECOMPO | BH9: VA=RECOMPO | BI9: VA=RECOMPO | BJ9: VA=RECOMPO | BN9: VA=RECOMPO | BO9: VA=RECOMPO | BP9: VA=RECOMPO | BQ9: VA=RECOMPO
E10: {AC=GPNBTOT}+{AC=GR5400} | G10: {AC=GPNBTOT}+{AC=GR5400} | K10: AC=GFDGT | L10: AC=GFDGHT | M10: AC=GFDGT | N10: AC=GFDGHT | Q10: AC=GRNAI | R10: AC=GS0911 | S10: AC=GRNAI | T10: AC=GS0911 | W10: AC=GRITC001 | X10: AC=GRITC001 | Y10: AC=GRITC001 | Z10: AC=GRITC001 | AC10: AC=GRITC002 | AD10: AC=GRITC002 | AE10: AC=GRITC002 | AF10: AC=GRITC002 | AI10: {AC=GRITC003}+{AC=GRITC004}+{AC=GRITC005} | AJ10: {AC=GRITC003}+{AC=GRITC004}+{AC=GRITC005} | AK10: {AC=GRITC003}+{AC=GRITC004}+{AC=GRITC005} | AL10: {AC=GRITC003}+{AC=GRITC004}+{AC=GRITC005} | AO10: {AC=GFB130}+{AC=GFB110} | AP10: {AC=GFB130}+{AC=GFB110} | AQ10: {AC=GFB130}+{AC=GFB110} | AR10: {AC=GFB130}+{AC=GFB110} | BA10: AC=GRNAI | BB10: AC=GS0911 | BC10: AC=GRNAI | BD10: AC=GS0911 | BG10: {AC=GFB130} | BI10: {AC=GFB130} | BN10: {AC=GFB110} | BO10: {AC=GFB110} | BP10: {AC=GFB110} | BQ10: {AC=GFB110}
D11: m€ | E11: Net Banking Income + Result of Co-Dev JVs | K11: General Operating Expenses | Q11: Pre-Tax Income | W11: SLA Plateforms | Z11: 0 | AC11: SLA Steering IM | AF11: 0 | AI11: SLA IIC+Retail+Logistics | AL11: 0 | AO11: Management Fees + BNPP SA rebilling | AR11: 0 | AU11: Total Internal SLA + MF + BNPP SA Rebilling | BG11: Management Fees + BNPP SA rebilling | BJ11: 0 | BN11: Management Fees + BNPP SA rebilling | BQ11: 0
A13: OA sum (TYPE-OA=OA06)
D14: Actual N vs Estimate-1 at perimeter & Historical conversion rate | E14: Actual Q1 2026 | G14: Estimate March Q1 2026 | I14: Variances | K14: Actual Q1 2026 | M14: Estimate March Q1 2026 | O14: Variances | Q14: Actual Q1 2026 | S14: Estimate March Q1 2026 | U14: Variances | W14: Actual Q1 2026 | Y14: Estimate March Q1 2026 | AA14: Variances | AC14: Actual Q1 2026 | AE14: Estimate March Q1 2026 | AG14: Variances | AI14: Actual Q1 2026 | AK14: Estimate March Q1 2026 | AM14: Variances | AO14: Actual Q1 2026 | AQ14: Estimate March Q1 2026 | AS14: Variances | AU14: Actual Q1 2026 | AW14: Estimate March Q1 2026 | AY14: Variances | BA14: Actual Q1 2026 | BC14: Estimate March Q1 2026 | BE14: Variances excl. Management Fees and equivalent | BG14: Actual Q1 2026 | BI14: Estimate March Q1 2026 | BK14: Variances | BN14: 0 | BP14: 0 | BR14: 0
E15: Standalone | G15: Standalone | K15: #REF! | M15: #REF! | Q15: Standalone | S15: Standalone | W15: Standalone | Y15: Standalone | AC15: Standalone | AE15: Standalone | AI15: Standalone | AK15: Standalone | AO15: Standalone | AQ15: Standalone | AU15: Standalone | AW15: Standalone | BA15: Standalone | BC15: Standalone | BE15: Σ | BG15: Standalone | BI15: Standalone | BN15: Standalone | BP15: Standalone
D17: Property Development | E17: -12412.955 | G17: -12973.404 | I17: 560.44886 | K17: -16226.109 | M17: -17214.29 | O17: 988.18137 | Q17: -28686.612 | S17: -30201.637 | U17: 1515.0252 | W17: -119.13706 | Y17: 139.30339 | AA17: -258.44046 | AC17: 45.96 | AE17: 16.534 | AG17: 29.426 | AI17: -65.191366 | AK17: 418.51144 | AM17: -483.70281 | AO17: -12830.983 | AQ17: -9622.1916 | AS17: -3208.7919 | AU17: -12969.352 | AW17: -9047.8428 | AY17: -3921.5091 | BA17: -15855.628 | BC17: -20579.445 | BE17: 4723.8171 | BG17: -6633.5245 | BI17: -4380.9436 | BK17: -2252.5809 | BN17: -6197.459 | BP17: -5241.248 | BR17: -956.21094
A18: {OA=OA040}+{OA=OA041} | B18: {RU=G-CENTRAL}+{RU=P-CENTRAL} | C18: FR | D18: G-central | E18: 0 | G18: 0 | I18: 0 | K18: 0 | M18: 0 | O18: 0 | Q18: 0 | S18: 0 | U18: 0 | W18: 0 | Y18: 0 | AA18: 0 | AC18: 0 | AE18: 0 | AG18: 0 | AI18: 0 | AK18: 0 | AM18: 0 | AO18: 0 | AQ18: 0 | AS18: 0 | AU18: 0 | AW18: 0 | AY18: 0 | BA18: 0 | BC18: 0 | BE18: 0 | BG18: 0 | BI18: 0 | BK18: 0 | BN18: 0 | BP18: 0 | BR18: 0
D19: o/w France | E19: -12685.24 | G19: -13466.844 | I19: 781.604 | K19: -15628.111 | M19: -16574.217 | O19: 946.106 | Q19: -28360.899 | S19: -30055.004 | U19: 1694.105 | W19: -119.13706 | Y19: 139.30339 | AA19: -258.44046 | AC19: 22.98 | AE19: 7.27 | AG19: 15.71 | AI19: -65.191366 | AK19: 418.51144 | AM19: -483.70281 | AO19: -12821.165 | AQ19: -9611.8317 | AS19: -3209.3336 | AU19: -12982.514 | AW19: -9046.7469 | AY19: -3935.7669 | BA19: -15539.734 | BC19: -20443.172 | BE19: 4903.4386 | BG19: -6631.8064 | BI19: -4370.5837 | BK19: -2261.2227 | BN19: -6189.359 | BP19: -5241.248 | BR19: -948.11094
A20: {OA=OA040}+{OA=OA041} | B20: {RU=G-FRMP}+{RU=P-FRMP}+{RU=G-FRAR}+{RU=P-FRAR} | C20: FR | D20: o/w Prop Dev Offices and Resid | E20: -14399.59 | G20: -14951.9 | I20: 552.31 | K20: -13734.963 | M20: -14506.73 | O20: 771.767 | Q20: -28134.553 | S20: -29458.63 | U20: 1324.077
A21: OA=OA015 | B21: {RU=G-FRMP}+{RU=P-FRMP} | C21: FR | D21: o/w Residential sales | E21: 0 | G21: 0 | I21: 0 | K21: 0 | M21: 0 | O21: 0 | Q21: 0 | S21: 0 | U21: 0
A22: OA sum AR021 | B22: {RU=G-FRMP}+{RU=P-FRMP} | C22: FR | D22: o/w Serviced Residences | E22: 1714.35 | G22: 1485.056 | I22: 229.294 | K22: -1893.148 | M22: -2067.487 | O22: 174.339 | Q22: -226.346 | S22: -596.374 | U22: 370.028
A23: OA=OA036 | B23: {RU=G-FRMP}+{RU=P-FRMP} | C23: FR | D23: o/w Students Residences | E23: 2620.14 | G23: 2458.496 | I23: 161.644 | K23: -1440.992 | M23: -1562.699 | O23: 121.707 | Q23: 1121.182 | S23: 870.797 | U23: 250.385
A24: OA=OA037 | B24: {RU=G-FRMP}+{RU=P-FRMP} | C24: FR | D24: o/w Business Travellers Residences | E24: -905.79 | G24: -973.44 | I24: 67.65 | K24: -452.156 | M24: -504.788 | O24: 52.632 | Q24: -1347.528 | S24: -1467.171 | U24: 119.643
D25: o/w International | E25: 272.28485 | G25: 493.43999 | I25: -221.15514 | K25: -597.99757 | M25: -640.07294 | O25: 42.075375 | Q25: -325.71271 | S25: -146.63295 | U25: -179.07976
A26: OA sum AR028 | B26: RU sum AF026 | C26: ITA | D26: o/w Italy | E26: -88.982 | G26: -88.772 | I26: -0.21 | K26: -67.413 | M26: -60.617 | O26: -6.796 | Q26: -156.395 | S26: -149.389 | U26: -7.006 | W26: 0 | Y26: 0 | AA26: 0 | AC26: -1.438 | AE26: -1.5 | AG26: 0.062 | AI26: 0 | AK26: 0 | AM26: 0 | AO26: 0 | AQ26: 0 | AS26: 0 | AU26: -1.438 | AW26: -1.5 | AY26: 0.062 | BA26: -156.395 | BC26: -149.389 | BE26: -7.006 | BG26: 0 | BI26: 0 | BK26: 0 | BN26: 0 | BP26: 0 | BR26: 0
A27: OA=OA040 | B27: RU=G-SP | C27: ESP | D27: o/w Spain | E27: 24.798 | G27: 28.693 | I27: -3.895 | K27: -10.801 | M27: -14.025 | O27: 3.224 | Q27: 13.997 | S27: 14.668 | U27: -0.671 | W27: 0 | Y27: 0 | AA27: 0 | AC27: 4.75 | AE27: -6.67 | AG27: 11.42 | AI27: 0 | AK27: 0 | AM27: 0 | AO27: 0 | AQ27: 0 | AS27: 0 | AU27: 4.75 | AW27: -6.67 | AY27: 11.42 | BA27: 13.997 | BC27: 14.668 | BE27: -0.671 | BG27: 0 | BI27: 0 | BK27: 0 | BN27: 0 | BP27: 0 | BR27: 0
A28: OA sum AR028 | B28: {RU=G-DE}+{RU=G-DEPROMO} | C28: DE | D28: o/w Germany | E28: -93.515 | G28: -85.636 | I28: -7.879 | K28: -148.525 | M28: -154.48 | O28: 5.955 | Q28: -242.04 | S28: -240.116 | U28: -1.924 | W28: 0 | Y28: 0 | AA28: 0 | AC28: -26.862 | AE28: -26.003 | AG28: -0.859 | AI28: 0 | AK28: 0 | AM28: 0 | AO28: -0.244 | AQ28: -0.18 | AS28: -0.064 | AU28: -27.106 | AW28: -26.183 | AY28: -0.923 | BA28: -241.796 | BC28: -239.936 | BE28: -1.86 | BG28: -0.244 | BI28: -0.18 | BK28: -0.064 | BN28: 0 | BP28: 0 | BR28: 0
A29: OA sum AR028 | B29: {RU=G-PRTPROMO} | C29: PRT | D29: o/w Portugal | E29: 321 | G29: 200.183 | I29: 120.817 | K29: -182.3 | M29: -231.556 | O29: 49.256 | Q29: 138.7 | S29: -31.373 | U29: 170.073 | W29: 0 | Y29: 0 | AA29: 0 | AC29: -24.25 | AE29: -24.333 | AG29: 0.083 | AI29: 0 | AK29: 0 | AM29: 0 | AO29: -8.1 | AQ29: -8.692 | AS29: 0.592 | AU29: -32.35 | AW29: -33.025 | AY29: 0.675 | BA29: 146.8 | BC29: -22.681 | BE29: 169.481 | BG29: 0 | BI29: -8.692 | BK29: 8.692 | BN29: -8.1 | BP29: 0 | BR29: -8.1
A30: {OA=OA040}+{OA=OA041} | B30: RU=G-UKPROMO | C30: UK | D30: o/w UK | E30: 12.633851 | G30: 12.57199 | I30: 0.061861397 | K30: -80.248566 | M30: -67.784941 | O30: -12.463625 | Q30: -67.614714 | S30: -55.212951 | U30: -12.401764 | W30: 0 | Y30: 0 | AA30: 0 | AC30: 0 | AE30: 0 | AG30: 0 | AI30: 0 | AK30: 0 | AM30: 0 | AO30: -1.4741413 | AQ30: -1.4878777 | AS30: 0.01373644 | AU30: -1.4741413 | AW30: -1.4878777 | AY30: 0.01373644 | BA30: -66.140573 | BC30: -53.725073 | BE30: -12.4155 | BG30: -1.4741413 | BI30: -1.4878777 | BK30: 0.01373644 | BN30: 0 | BP30: 0 | BR30: 0
A31: {OA=OA040}+{OA=OA041} | B31: RU=G-UKPROMO | C31: UK GBP | D31: UK (GBP) | E31: 10.97 | G31: 10.9 | I31: 0.07 | K31: -69.68 | M31: -58.77 | O31: -10.91 | Q31: -58.71 | S31: -47.87 | U31: -10.84 | W31: 0 | Y31: 0 | AA31: 0 | AC31: 0 | AE31: 0 | AG31: 0 | AI31: 0 | AK31: 0 | AM31: 0 | AO31: -1.28 | AQ31: -1.29 | AS31: 0.01 | AU31: -1.28 | AW31: -1.29 | AY31: 0.01 | BA31: -57.43 | BC31: -46.58 | BE31: -10.85 | BG31: -1.28 | BI31: -1.29 | BK31: 0.01 | BN31: 0 | BP31: 0 | BR31: 0
A32: OA sum AR028 | B32: RU=G-LX | C32: LUX | D32: o/w Luxembourg | E32: 0 | G32: 0 | I32: 0 | K32: 0 | M32: 0 | O32: 0 | Q32: 0 | S32: 0 | U32: 0 | W32: 0 | Y32: 0 | AA32: 0 | AC32: 0 | AE32: 0 | AG32: 0 | AI32: 0 | AK32: 0 | AM32: 0 | AO32: 0 | AQ32: 0 | AS32: 0 | AU32: 0 | AW32: 0 | AY32: 0 | BA32: 0 | BC32: 0 | BE32: 0 | BG32: 0 | BI32: 0 | BK32: 0 | BN32: 0 | BP32: 0 | BR32: 0
A33: OA=OA045 | B33: {RU=G-FRMP} | C33: FR | D33: o/w International Teams | E33: 96.35 | G33: 426.4 | I33: -330.05 | K33: -108.71 | M33: -111.61 | O33: 2.9 | Q33: -12.36 | S33: 314.79 | U33: -327.15 | W33: 0 | Y33: 0 | AA33: 0 | AC33: 70.78 | AE33: 67.77 | AG33: 3.01 | AI33: 0 | AK33: 0 | AM33: 0 | AO33: 0 | AQ33: 0 | AS33: 0 | AU33: 70.78 | AW33: 67.77 | AY33: 3.01 | BA33: -12.36 | BC33: 314.79 | BE33: -327.15 | BG33: 0 | BI33: 0 | BK33: 0 | BN33: 0 | BP33: 0 | BR33: 0
D34: Investment Management | E34: -0.001 | G34: -27.053 | I34: 27.052 | K34: -1.184 | M34: -0.271 | O34: -0.913 | Q34: -1.185 | S34: -27.324 | U34: 26.139 | W34: 0 | Y34: 0 | AA34: 0 | AC34: 0 | AE34: 0 | AG34: 0 | AI34: 0 | AK34: 0 | AM34: 0 | AO34: 0 | AQ34: 0 | AS34: 0 | AU34: 0 | AW34: 0 | AY34: 0 | BA34: -1.185 | BC34: -27.324 | BE34: 26.139 | BG34: 0 | BI34: 0 | BK34: 0 | BN34: 0 | BP34: 0 | BR34: 0
A35: {OA=OA060}+{OA=OA061}+{OA=OA069}+{OA=OA060E}+{OA=OA060O}+{OA=OA061O} | B35: {RU=G-CENTRAL}+{RU=P-CENTRAL} | C35: CENTRAL | D35: G-central | E35: 0 | G35: 0 | I35: 0 | K35: 0 | M35: 0 | O35: 0 | Q35: 0 | S35: 0 | U35: 0 | W35: 0 | Y35: 0 | AA35: 0 | AC35: 0 | AE35: 0 | AG35: 0 | AI35: 0 | AK35: 0 | AM35: 0 | AO35: 0 | AQ35: 0 | AS35: 0 | AU35: 0 | AW35: 0 | AY35: 0 | BA35: 0 | BC35: 0 | BE35: 0 | BG35: 0 | BI35: 0 | BK35: 0 | BN35: 0 | BP35: 0 | BR35: 0
A36: {OA=OA069}+{OA=OA005} | B36: {RU=G-FRMP}+{RU=P-FRMP}+{RU=G-REIMDE}+{RU=G-REIMI} | C36: DE | D36: o/w Coordination Team | E36: 0.001 | G36: -27.053 | I36: 27.054 | K36: -1.182 | M36: -0.398 | O36: -0.784 | Q36: -1.181 | S36: -27.451 | U36: 26.27 | W36: 0 | Y36: 0 | AA36: 0 | AC36: 0 | AE36: 0 | AG36: 0 | AI36: 0 | AK36: 0 | AM36: 0 | AO36: 0 | AQ36: 0 | AS36: 0 | AU36: 0 | AW36: 0 | AY36: 0 | BA36: -1.181 | BC36: -27.451 | BE36: 26.27 | BG36: 0 | BI36: 0 | BK36: 0 | BN36: 0 | BP36: 0 | BR36: 0
A37: {OA=OA060}+{OA=OA060E}+{OA=OA060O}+{OA=OA061}+{OA=OA061O} | B37: {RU=G-FRMP}+{RU=P-FRMP} | C37: FR | D37: o/w France | E37: -0.002 | G37: 0 | I37: -0.002 | K37: 0 | M37: 0 | O37: 0 | Q37: -0.002 | S37: 0 | U37: -0.002 | W37: 0 | Y37: 0 | AA37: 0 | AC37: 0 | AE37: 0 | AG37: 0 | AI37: 0 | AK37: 0 | AM37: 0 | AO37: 0 | AQ37: 0 | AS37: 0 | AU37: 0 | AW37: 0 | AY37: 0 | BA37: -0.002 | BC37: 0 | BE37: -0.002 | BG37: 0 | BI37: 0 | BK37: 0 | BN37: 0 | BP37: 0 | BR37: 0
A38: {OA=OA060}+{OA=OA061}+{OA=OA060E}+{OA=OA061O} | B38: {RU=G-DE}+{RU=P-DE}+{RU=G-REIMDE}+{RU=G-REIMI} | C38: DE | D38: o/w Germany | E38: 0 | G38: 0 | I38: 0 | K38: 0 | M38: 0 | O38: 0 | Q38: 0 | S38: 0 | U38: 0 | W38: 0 | Y38: 0 | AA38: 0 | AC38: 0 | AE38: 0 | AG38: 0 | AI38: 0 | AK38: 0 | AM38: 0 | AO38: 0 | AQ38: 0 | AS38: 0 | AU38: 0 | AW38: 0 | AY38: 0 | BA38: 0 | BC38: 0 | BE38: 0 | BG38: 0 | BI38: 0 | BK38: 0 | BN38: 0 | BP38: 0 | BR38: 0
A39: {OA=OA061} | B39: RU=G-REIMLUX | C39: ITA | D39: o/w Branch | E39: 0 | G39: 0 | I39: 0 | K39: 0 | M39: 0 | O39: 0 | Q39: 0 | S39: 0 | U39: 0 | W39: 0 | Y39: 0 | AA39: 0 | AC39: 0 | AE39: 0 | AG39: 0 | AI39: 0 | AK39: 0 | AM39: 0 | AO39: 0 | AQ39: 0 | AS39: 0 | AU39: 0 | AW39: 0 | AY39: 0 | BA39: 0 | BC39: 0 | BE39: 0 | BG39: 0 | BI39: 0 | BK39: 0 | BN39: 0 | BP39: 0 | BR39: 0
A40: {OA=OA060}+{OA=OA060E}+{OA=OA060O} | B40: RU sum AF026 | C40: ITA | D40: o/w REIM Italy | E40: 0 | G40: 0 | I40: 0 | K40: -0.002 | M40: 0.127 | O40: -0.129 | Q40: -0.002 | S40: 0.127 | U40: -0.129
C41: ITA | D41: o/w Italy | E41: 0 | G41: 0 | I41: 0 | K41: -0.002 | M41: 0.127 | O41: -0.129 | Q41: -0.002 | S41: 0.127 | U41: -0.129
A42: {OA=OA060}+{OA=OA060E}+{OA=OA060O} | B42: RU=G-REIMLUX | C42: LUX | D42: o/w Luxembourg | E42: 0 | G42: 0 | I42: 0 | K42: 0 | M42: 0 | O42: 0 | Q42: 0 | S42: 0 | U42: 0 | W42: 0 | Y42: 0 | AA42: 0 | AC42: 0 | AE42: 0 | AG42: 0 | AI42: 0 | AK42: 0 | AM42: 0 | AO42: 0 | AQ42: 0 | AS42: 0 | AU42: 0 | AW42: 0 | AY42: 0 | BA42: 0 | BC42: 0 | BE42: 0 | BG42: 0 | BI42: 0 | BK42: 0 | BN42: 0 | BP42: 0 | BR42: 0
A43: {OA=OA060}+{OA=OA061}+{OA=OA060E}+{OA=OA060O} | B43: {RU=G-UK}+{RU=P-UK}+{RU=G-REIMI} | C43: UK | D43: o/w UK | E43: 0 | G43: 0 | I43: 0 | K43: 0 | M43: 0 | O43: 0 | Q43: 0 | S43: 0 | U43: 0 | W43: 0 | Y43: 0 | AA43: 0 | AC43: 0 | AE43: 0 | AG43: 0 | AI43: 0 | AK43: 0 | AM43: 0 | AO43: 0 | AQ43: 0 | AS43: 0 | AU43: 0 | AW43: 0 | AY43: 0 | BA43: 0 | BC43: 0 | BE43: 0 | BG43: 0 | BI43: 0 | BK43: 0 | BN43: 0 | BP43: 0 | BR43: 0
A44: {OA=OA060}+{OA=OA061}+{OA=OA060E}+{OA=OA060O} | B44: {RU=G-UK}+{RU=P-UK} | C44: UK GBP | D44: UK (GBP) | E44: 0 | G44: 0 | I44: 0 | K44: 0 | M44: 0 | O44: 0 | Q44: 0 | S44: 0 | U44: 0 | W44: 0 | Y44: 0 | AA44: 0 | AC44: 0 | AE44: 0 | AG44: 0 | AI44: 0 | AK44: 0 | AM44: 0 | AO44: 0 | AQ44: 0 | AS44: 0 | AU44: 0 | AW44: 0 | AY44: 0 | BA44: 0 | BC44: 0 | BE44: 0 | BG44: 0 | BI44: 0 | BK44: 0 | BN44: 0 | BP44: 0 | BR44: 0
A45: {OA=OA060}+{OA=OA060E}+{OA=OA060O} | B45: {RU=G-BE}+{RU=P-BE} | C45: BEL | D45: o/w Belgium | E45: 0 | G45: 0 | I45: 0 | K45: 0 | M45: 0 | O45: 0 | Q45: 0 | S45: 0 | U45: 0 | W45: 0 | Y45: 0 | AA45: 0 | AC45: 0 | AE45: 0 | AG45: 0 | AI45: 0 | AK45: 0 | AM45: 0 | AO45: 0 | AQ45: 0 | AS45: 0 | AU45: 0 | AW45: 0 | AY45: 0 | BA45: 0 | BC45: 0 | BE45: 0 | BG45: 0 | BI45: 0 | BK45: 0 | BN45: 0 | BP45: 0 | BR45: 0
A46: {OA=OA060}+{OA=OA060E}+{OA=OA060O} | B46: {RU=G-REIMSP}+{RU=G-SP} | C46: ESP | D46: o/w Spain | E46: 0 | G46: 0 | I46: 0 | K46: 0 | M46: 0 | O46: 0 | Q46: 0 | S46: 0 | U46: 0 | W46: 0 | Y46: 0 | AA46: 0 | AC46: 0 | AE46: 0 | AG46: 0 | AI46: 0 | AK46: 0 | AM46: 0 | AO46: 0 | AQ46: 0 | AS46: 0 | AU46: 0 | AW46: 0 | AY46: 0 | BA46: 0 | BC46: 0 | BE46: 0 | BG46: 0 | BI46: 0 | BK46: 0 | BN46: 0 | BP46: 0 | BR46: 0
D47: Advisory | E47: 68139.443 | G47: 67918.789 | H47: 0 | I47: 220.65416 | K47: -88968.805 | M47: -90483.4 | N47: 0 | O47: 1514.5948 | Q47: -21420.45 | S47: -22629.764 | T47: 0 | U47: 1209.314 | W47: -628.67706 | Y47: -556.78122 | Z47: 0 | AA47: -71.895838 | AC47: 0 | AE47: 0 | AF47: 0 | AG47: 0 | AI47: -65.191366 | AK47: 385.17739 | AL47: 0 | AM47: -450.36875 | AO47: -9254.1528 | AQ47: -9423.794 | AR47: 0 | AS47: 169.64118 | AU47: -9948.0212 | AW47: -9595.3978 | AX47: 0 | AY47: -352.62341 | BA47: -12166.297 | BC47: -13205.97 | BD47: 0 | BE47: 1039.6728 | BG47: -8308.482 | BI47: -8465.5306 | BJ47: 0 | BK47: 157.04856 | BN47: -945.67079 | BP47: -958.26342 | BQ47: 0 | BR47: 12.592622
A48: OA sum AR0121 | B48: {RU=G-CENTRAL}+{RU=P-CENTRAL} | C48: CENTRAL | D48: G-central | E48: 0 | G48: 930 | I48: -930 | K48: 0 | M48: -684.5 | O48: 684.5 | Q48: 0 | S48: 245.5 | U48: -245.5 | W48: 0 | Y48: 0 | AA48: 0 | AC48: 0 | AE48: 0 | AG48: 0 | AI48: 0 | AK48: 0 | AM48: 0 | AO48: 0 | AQ48: 0 | AS48: 0 | AU48: 0 | AW48: 0 | AY48: 0 | BA48: 0 | BC48: 245.5 | BE48: -245.5 | BG48: 0 | BI48: 0 | BK48: 0 | BN48: 0 | BP48: 0 | BR48: 0
A49: {OA=OA005O}+{OA=OA006}+{OA=OA010}+{OA=OA011}+{OA=OA017}+{OA=OA021}+{OA=OA021O}+{OA=OA023}+{OA=OA024} | B49: {RU=G-UK}+{RU=P-UK}+{RU=G-UKSP} | C49: UK | D49: o/w UK | E49: 15362.798 | G49: 17116.125 | I49: -1753.3276 | K49: -26205.873 | M49: -27176.418 | O49: 970.54471 | Q49: -10931.313 | S49: -9989.2039 | U49: -942.10883 | W49: -144.99561 | Y49: -142.10962 | AA49: -2.8859917 | AC49: 0 | AE49: 0 | AG49: 0 | AI49: 205.81546 | AK49: 210.52893 | AM49: -4.713471 | AO49: -1288.5377 | AQ49: -1442.8977 | AS49: 154.36 | AU49: -1227.7178 | AW49: -1374.4784 | AY49: 146.76054 | BA49: -9642.775 | BC49: -8546.3062 | BE49: -1096.4688 | BG49: -904.48932 | BI49: -1061.7542 | BK49: 157.26483 | BN49: -384.04835 | BP49: -381.14352 | BR49: -2.9048309
